Workbook
Name Category: #REF!
Name Transaction: #REF!

Sheet Reloc
G1: Data Before
G2: RF 1 | I2: RF 2 | K2: RF 3 | M2: RF 4 | O2: AAU 1 | Q2: AAU 2 | S2: AAU 3 | U2: MW 1 | X2: MW 2 | AA2: MW 3 | AD2: MW 4
A3: NO | B3: Site ID Old | C3: Site Name Old | D3: Tenant | E3: Site ID Tenant | F3: Site Name Tenant | G3: Height | H3: Azimuth | I3: Height2 | J3: Azimuth3 | K3: Height4 | L3: Azimuth5 | M3: Height6 | N3: Azimuth7 | O3: Height8 | P3: Azimuth9 | Q3: Height10 | R3: Azimuth11 | S3: Height12 | T3: Azimuth13 | U3: Link | V3: Height14 | W3: Azimuth15 | X3: Link16 | Y3: Height17 | Z3: Azimuth18 | AA3: Link19 | AB3: Height20 | AC3: Azimuth21 | AD3: Link22 | AE3: Height23 | AF3: Azimuth24 | AG3: Site ID New | AH3: Site Name New | AI3: LATITUDE | AJ3: LONGITUDE | AK3: CR // CRQ // XLWO | AL3: Start Dismantle | AM3: Start Reinstall | AN3: OA | AO3: Data After
A4: 1 | B4: R1200302 | C4: BANGUN PURBA | D4: XLS | E4: SUM-SU-LBP-0405 | F4: BANGUN PURBA Relocation | G4: 69 | H4: 0 | I4: 69 | J4: 180 | K4: 69 | L4: 280 | U4: to SUM-SU-LBP-0023 | V4: 54 | W4: 130 | X4: to SUM-SU-SRH-1245 | Y4: 52 | Z4: 190 | AA4: to SUM-SU-LBP-0022 | AB4: 52 | AC4: 120 | AD4: to SUM-SU-SRH-8224 | AE4: 53 | AF4: 240 | AG4: ID-SU-03892 | AH4: BANGUN PURBA | AI4: 3.37141 | AJ4: 98.8149 | AK4: XLWO-20260522-00000051 | AL4: 46168 | AM4: 46169 | AN4: 46171 | AO4: RF 1 | AQ4: RF 2 | AS4: RF 3 | AU4: RF 4 | AW4: AAU 1 | AY4: AAU 2 | BA4: AAU 3 | BC4: MW 1 | BF4: MW 2 | BI4: MW 3 | BL4: MW 4
A5: 2 | B5: R3350421 | C5: KARANGJUNTI | D5: IOH | E5: 14BRS0006 | F5: KARANGJUNTI_CM | G5: 53 | H5: 120 | I5: 53 | J5: 215 | K5: 53 | L5: 340 | AG5: ID-JT-17956 | AH5: LOSARI KARANGJUNTI | AI5: -6.91628 | AJ5: 108.7941 | AK5: CR-20260529-00000297 | AL5: 46176 | AM5: 46179 | AN5: 46181 | AO5: Height | AP5: Azimuth | AQ5: Height | AR5: Azimuth | AS5: Height | AT5: Azimuth | AU5: Height | AV5: Azimuth | AW5: Height | AX5: Azimuth | AY5: Height | AZ5: Azimuth | BA5: Height | BB5: Azimuth | BC5: Link | BD5: Height | BE5: Azimuth | BF5: Link | BG5: Height | BH5: Azimuth | BI5: Link | BJ5: Height | BK5: Azimuth | BL5: Link | BM5: Height | BN5: Azimuth
A6: 3 | B6: R3350421 | C6: KARANGJUNTI | D6: XLS | E6: JAW-JT-BBS-0007 | F6: KARANGJUNTI Relocation | G6: 68 | H6: 0 | I6: 68 | J6: 160 | K6: 68 | L6: 310 | AG6: ID-JT-17956 | AH6: LOSARI KARANGJUNTI | AI6: -6.91429 | AJ6: 108.7941 | AK6: XLWO-20260619-00006228 | AL6: 46195 | AM6: 46196 | AN6: 46200 | AO6: 68 | AP6: 0 | AQ6: 68 | AR6: 180 | AS6: 68 | AT6: 280 | BC6: to SUM-SU-LBP-0023 | BD6: 54 | BE6: 130 | BF6: SUM-SU-SRH-1245 | BG6: 51 | BH6: 190 | BI6: to SUM-SU-LBP-0022 | BJ6: 60 | BK6: 120 | BL6: to SUM-SU-SRH-8224 | BM6: 53 | BN6: 240
A7: 4 | B7: E3200525 | C7: GEDUNG_LIPPO | D7: IOH | E7: 13BDG0292 | F7: IMGEDUNG_LIPPO_EP | G7: 3 | H7: 30 | AG7: ID-JB-03467 | AH7: PAKUHAJI WETAN NGAMPRAH | AI7: -6.82802 | AJ7: 10754079 | AL7: 45911 | AO7: 53 | AP7: 30 | AQ7: 53 | AR7: 120 | AS7: 53 | AT7: 240 | BC7: to 14BRS0013 | BD7: 51 | BE7: 40
A8: 5 | B8: E8200008 | C8: JAILOLO | D8: IOH | E8: 32HBR0001 | F8: JAILOLO_EP | G8: 58 | H8: 10 | I8: 58 | J8: 180 | K8: 58 | L8: 235 | U8: to 32HBR0002 | V8: 54 | W8: 35 | X8: to 32HBR0011 | Y8: 33 | Z8: 75 | AA8: to 32TER0004 main | AB8: 44 | AC8: 200 | AD8: to 32TER0004 standby | AE8: 29 | AF8: 200 | AG8: ID-MU-14641 | AH8: GUAEMAADU JAILOLO | AI8: 1.06156 | AJ8: 127.46364 | AK8: CR-20251215-00000284 | AL8: 46007 | AM8: 46012 | AN8: 46023
A9: 6 | B9: R3270681 | C9: JAPARA KUNINGAN | D9: XLS | E9: JAW-JB-KNG-1359 | F9: JAPARA KUNINGAN | AG9: E3200649 | AH9: JAPARA | AI9: -6.89649 | AJ9: 108.51681 | AO9: 47 | AP9: 20
A10: 7 | B10: E3200182 | C10: GEULIS_RESORT | D10: XLS | E10: JAW-JB-CBI-0515 | F10: GEULIS RESORT BOGOR | G10: 51 | H10: 190 | I10: 51 | J10: 270 | K10: 51 | L10: 320 | U10: to JAW-JB-BGR-0421 | V10: 49 | W10: 280 | AG10: ID-JB-14444 | AH10: GEULIS SUKARAJA | AI10: -6.6318 | AJ10: 106.8663 | AK10: XLWO-20260804-00000177 | AL10: 46244 | AM10: 46245 | AO10: 60 | AP10: 45 | AQ10: 60 | AR10: 190 | AS10: 60 | AT10: 240 | BC10: to 32HBR0002 | BD10: 71 | BE10: 10 | BF10: to 32HBR0011 | BG10: 55 | BH10: 110 | BI10: to 32TER0004 main | BJ10: 50 | BK10: 205 | BL10: to 32TER0004 standby | BM10: 80 | BN10: 205
A11: 8 | B11: E3200182 | C11: GEULIS_RESORT | D11: IOH | E11: 13CBN0771 | F11: GEULIS_RESORT_EP | G11: 67 | H11: 20 | I11: 67 | J11: 210 | K11: 67 | L11: 320 | AG11: ID-JB-14444 | AH11: GEULIS SUKARAJA | AI11: -6.6318 | AJ11: 106.8663 | AK11: CR-20260804-00000400 CR-20260804-00000411
A12: 9 | B12: R3270184 | C12: SETRAINDAH BARAT | D12: IOH | E12: 13BDG0084 | F12: SETRAINDAHBARAT_CM | G12: 18 | H12: 90 | I12: 18 | J12: 150 | K12: 18 | L12: 330 | AO12: 70 | AQ12: 70 | AS12: 70
A13: 10 | B13: R3270184 | C13: SETRAINDAH BARAT | D13: XLS | E13: JAW-JB-BDG-0045 | F13: SETRA INDAH BARAT | G13: 18 | H13: 30 | I13: 18 | J13: 130 | K13: 18 | L13: 320 | O13: 18 | P13: 50 | Q13: 18 | R13: 230 | S13: 18 | T13: 330 | AO13: 70 | AQ13: 70 | AS13: 70

Sheet Account
A1: No | B1: Account Project | C1: Vendor | D1: Project | E1: Coverage Area
A2: 1 | B2: SGP-TI-Nasional | C2: PT. Sempurna Global Pertama | D2: Telkom Infra | E2: Nasional
A3: 2 | B3: SGI-ZTE_XLSmart-Nasional | C3: PT. Star Global Indonesia | D3: ZTE_XLSmart | E3: Nasional
A4: 3 | B4: CMI-RBLD-Nasional | C4: PT. Centratama Menara Indonesi | D4: Rebuild | E4: Nasional
A5: 4 | B5: CMI-TMAIN-Nasional | C5: PT. Centratama Menara Indonesi | D5: Tower Maintenance | E5: Nasional
A6: 5 | B6: CMI-COLO-Nasional | C6: PT. Centratama Menara Indonesi | D6: Colocation | E6: Nasional
A7: 6 | B7: CMI-MAC-Nasional | C7: PT. Centratama Menara Indonesi | D7: MAC | E7: Nasional
A8: 7 | B8: MSG-RTGS-Bengkulu | C8: PT. Mitra Sistematika Global | D8: Remote Terminal Ground Segment | E8: Bengkulu
A9: 8 | B9: DMT-All-Nasional | C9: PT. Dayamitra Telekomunikasi | D9: All | E9: Nasional
A10: 9 | B10: CCSI-XLS_PLN-EJ | C10: PT. China Comservice Indonesia | D10: XLSmart_PLN | E10: East Java
A11: 10 | B11: MSG-COLO_IOH-Nasional | C11: PT. Mitra Sistematika Global | D11: Colocation_IOH | E11: Nasional
A12: 11 | B12: MSG-STH-Kalimantan | C12: PT. Mitra Sistematika Global | D12: Strengthening | E12: Kalimantan
A13: 12 | B13: CMI-TIP-Nasional | C13: PT. Centratama Menara Indonesia | D13: Tower Inspection Preventive | E13: Nasional
... A17: 16 | B17: CCSI-XLS_PLN-Sulawesi | C17: PT. China Comservice Indonesia | D17: XLSmart_PLN | E17: Sulawesi
A18: =+A17+1 -> 17 | B18: CMI-RLC-Nasional | C18: PT. Centratama Menara Indonesi | D18: Relocation | E18: Nasional
A19: =+A18+1 -> 18 | B19: CMI-SURGE-Nasional | C19: PT. Centratama Menara Indonesi | D19: SURGE | E19: Nasional

Sheet List Material Inbound
B4: Site ID | C4: Site Name | D4: Tenant | E4: Material | F4: UoM | G4: Qty | H4: SN | I4: Remark | J4: Inbound
B5: E3500375 | C5: MERPATI | D5: XLS | E5: Rack Recty | F5: unit | G5: 1
B6: E3500375 | C6: MERPATI | D6: XLS | E6: Recty EATON | F6: unit | G6: 1
B7: E3500375 | C7: MERPATI | D7: XLS | E7: Module recty | F7: pcs | G7: 6
B8: E3500375 | C8: MERPATI | D8: XLS | E8: RTN Huawei 950 | F8: unit | G8: 1
B9: E3500375 | C9: MERPATI | D9: XLS | E9: CSHU + 1 SFP | F9: unit | G9: 1
B10: E3500375 | C10: MERPATI | D10: XLS | E10: Fan RTN 950 | F10: unit | G10: 1
B11: E3500375 | C11: MERPATI | D11: XLS | E11: ISU 2 | F11: pcs | G11: 1
B12: E3500375 | C12: MERPATI | D12: XLS | E12: DCPD | F12: pcs | G12: 2
B13: E3500375 | C13: MERPATI | D13: XLS | E13: Kabel DCPD biru | F13: tarikan | G13: 4
B14: E3500375 | C14: MERPATI | D14: XLS | E14: Kabel DCPD hitam | F14: tarikan | G14: 4
B15: E3500375 | C15: MERPATI | D15: XLS | E15: BBU V9200 | F15: unit | G15: 1 | H15: 219634374099
B16: E3500375 | C16: MERPATI | D16: XLS | E16: VBPe2q | F16: pcs | G16: 1
B17: E3500375 | C17: MERPATI | D17: XLS | E17: VPDc1 | F17: pcs | G17: 1
B18: E3500375 | C18: MERPATI | D18: XLS | E18: VEMC4 | F18: pcs | G18: 1
B19: E3500375 | C19: MERPATI | D19: XLS | E19: VBPE3q | F19: pcs | G19: 1
B20: E3500375 | C20: MERPATI | D20: XLS | E20: VSWd1 | F20: pcs | G20: 1
B21: E3500375 | C21: MERPATI | D21: XLS | E21: SFP (VBPE2q) | F21: pcs | G21: 6
B22: E3500375 | C22: MERPATI | D22: XLS | E22: SFP (VBPE3q) | F22: pcs | G22: 5
B23: E3500375 | C23: MERPATI | D23: XLS | E23: SFP (VSWd1) | F23: pcs | G23: 2
B24: E3500375 | C24: MERPATI | D24: XLS | E24: Casing GPS | F24: pcs | G24: 1
B25: E3500375 | C25: MERPATI | D25: XLS | E25: LPU2 | F25: pcs | G25: 1 | H25: 219639300831
B26: E3500375 | C26: MERPATI | D26: XLS | E26: BLP2 | F26: pcs | G26: 2 | H26: 200145 200343
B27: E3500375 | C27: MERPATI | D27: XLS | E27: SCU | F27: pcs | G27: 1 | H27: 21964195814
B28: E3500375 | C28: MERPATI | D28: XLS | E28: 2XCTN 6120H-SC | F28: pcs | G28: 1 | H28: D80AE69CFF38
B29: E3500375 | C29: MERPATI | D29: XLS | E29: SFP (2XCTN) | F29: pcs | G29: 3
B30: E3500375 | C30: MERPATI | D30: XLS | E30: PW1DC (2XCTN) | F30: pcs | G30: 2
B31: E3500375 | C31: MERPATI | D31: XLS | E31: Battery ZTE ZXESM R311 | F31: pcs | G31: 3
B32: E3500375 | C32: MERPATI | D32: XLS | E32: Kabel power batt (biru) | F32: tarikan | G32: 3
B33: E3500375 | C33: MERPATI | D33: XLS | E33: Kabel power batt (hitam) | F33: tarikan | G33: 3
B34: E3500375 | C34: MERPATI | D34: XLS | E34: Kabel grounding batt | F34: tarikan | G34: 3
B35: E3500375 | C35: MERPATI | D35: XLS | E35: Kabel power BBU (biru-hitam) | F35: tarikan | G35: 1
B36: E3500375 | C36: MERPATI | D36: XLS | E36: Kabel power RTN 950 (biru-hitam) | F36: tarikan | G36: 1
B37: E3500375 | C37: MERPATI | D37: XLS | E37: Kabel power AAU | F37: tarikan | G37: 3
B38: E3500375 | C38: MERPATI | D38: XLS | E38: Kabel power RRU | F38: tarikan | G38: 5
B39: E3500375 | C39: MERPATI | D39: XLS | E39: Kabel optic AAU | F39: tarikan | G39: 3
B40: E3500375 | C40: MERPATI | D40: XLS | E40: Kabel optic RRU | F40: tarikan | G40: 8
... B48: E3500375 | C48: MERPATI | D48: XLS | E48: Belting kabinet | F48: pcs | G48: 1
B49: R3580695 | C49: 3G_KUPANG KRAJAN | D49: XLS | E49: Antenna sector | F49: pcs | G49: 3 | H49: KCK031874630005B KCK031874630011W KCK03187463000WW
B50: R3580695 | C50: 3G_KUPANG KRAJAN | D50: XLS | E50: RRU 9264 | F50: pcs | G50: 5 | H50: 219645649504 219644276184 219644276183 219645649564 219645642979
B51: R3580695 | C51: 3G_KUPANG KRAJAN | D51: XLS | E51: Antena AAU A9652D | F51: pcs | G51: 3 | H51: 219657872911 219657872872 219657873107
B52: R3580695 | C52: 3G_KUPANG KRAJAN | D52: XLS | E52: Battery Lithium | F52: pcs | G52: 3 | H52: UB2410015715 UB2410013042 219648643871
B53: R3580695 | C53: 3G_KUPANG KRAJAN | D53: XLS | E53: ZXEDMSCU601B | F53: pcs | G53: 1 | H53: 219653617801
B54: R3580695 | C54: 3G_KUPANG KRAJAN | D54: XLS | E54: DCPD 10B | F54: pcs | G54: 2 | H54: 265625312394 265625312349
B55: R3580695 | C55: 3G_KUPANG KRAJAN | D55: XLS | E55: RTN 950 | F55: pcs | G55: 1 | H55: 21021131746TBB90304
B56: R3580695 | C56: 3G_KUPANG KRAJAN | D56: XLS | E56: CSHU | F56: pcs | G56: 1 | H56: 021YTFCNG6008019
B57: R3580695 | C57: 3G_KUPANG KRAJAN | D57: XLS | E57: EMGTA | F57: pcs | G57: 1 | H57: E0247FB3ASE0-E5
B58: R3580695 | C58: 3G_KUPANG KRAJAN | D58: XLS | E58: EG4 | F58: pcs | G58: 1 | H58: 020MXKNJ8004447
B59: R3580695 | C59: 3G_KUPANG KRAJAN | D59: XLS | E59: SP3S | F59: pcs | G59: 1 | H59: 020SYWYOF2001053
B60: R3580695 | C60: 3G_KUPANG KRAJAN | D60: XLS | E60: ZXCTN G120H-SC | F60: pcs | G60: 1 | H60: 210133047678
B61: R3580695 | C61: 3G_KUPANG KRAJAN | D61: XLS | E61: SFP ZXCTN | F61: pcs | G61: 4
B62: R3580695 | C62: 3G_KUPANG KRAJAN | D62: XLS | E62: ZX RAN V9200 | F62: pcs | G62: 1 | H62: 219648108504
B63: R3580695 | C63: 3G_KUPANG KRAJAN | D63: XLS | E63: SFP RAN V9200 | F63: pcs | G63: 12
B64: R3580695 | C64: 3G_KUPANG KRAJAN | D64: XLS | E64: VSWD1 | F64: pcs | G64: 1 | H64: N/A
B65: R3580695 | C65: 3G_KUPANG KRAJAN | D65: XLS | E65: VBPE3P | F65: pcs | G65: 1 | H65: N/A
B66: R3580695 | C66: 3G_KUPANG KRAJAN | D66: XLS | E66: VBPE2Q | F66: pcs | G66: 1 | H66: N/A
B67: R3580695 | C67: 3G_KUPANG KRAJAN | D67: XLS | E67: VEMC4 | F67: pcs | G67: 1 | H67: N/A
B68: R3580695 | C68: 3G_KUPANG KRAJAN | D68: XLS | E68: VPDC1 | F68: pcs | G68: 1 | H68: N/A
B69: R3580695 | C69: 3G_KUPANG KRAJAN | D69: XLS | E69: FAN RECTY | F69: pcs | G69: 2 | H69: 2102120734N0EC000648
B70: R3580695 | C70: 3G_KUPANG KRAJAN | D70: XLS | E70: MODULE RECTY | F70: pcs | G70: 4 | H70: 245777891 246069500 245403719 245706645
B71: R3580695 | C71: 3G_KUPANG KRAJAN | D71: XLS | E71: DISPLAY RECTY | F71: pcs | G71: 1 | H71: N/A
B72: R3580695 | C72: 3G_KUPANG KRAJAN | D72: XLS | E72: RECTIFIER | F72: unit | G72: 1 | H72: APS63G-000713
B73: R3580695 | C73: 3G_KUPANG KRAJAN | D73: XLS | E73: RACK RECTY | F73: unit | G73: 1 | H73: SN BROKEN
B74: R3580695 | C74: 3G_KUPANG KRAJAN | D74: XLS | E74: KABEL POWER RRU | F74: tarikan | G74: 8
B75: R3580695 | C75: 3G_KUPANG KRAJAN | D75: XLS | E75: JUMPER | F75: pcs | G75: 18
B76: R3580695 | C76: 3G_KUPANG KRAJAN | D76: XLS | E76: OPTIC | F76: tarikan | G76: 8
B77: E3500307 | C77: MOROKREMBANGAN | D77: IOH | E77: Antenna sector | F77: pcs | G77: 3 | H77: 13CN101991425 13CN101992628 Blur | J77: 46196
B78: E3500307 | C78: MOROKREMBANGAN | D78: IOH | E78: CPRI | F78: tarikan | G78: 10 | J78: 46196
B79: E3500307 | C79: MOROKREMBANGAN | D79: IOH | E79: PMS | F79: pcs | G79: 1 | H79: 2101073846NON8000434 | J79: 46196
B80: E3500307 | C80: MOROKREMBANGAN | D80: IOH | E80: Battery ZTE | F80: pcs | G80: 1 | H80: 123014631011 | J80: 46196
B81: E3500307 | C81: MOROKREMBANGAN | D81: IOH | E81: MW NEC 1.2 + ODU | F81: set | G81: 1 | J81: 46196
B82: E3500307 | C82: MOROKREMBANGAN | D82: IOH | E82: MW RTN 0.6 + ODU | F82: set | G82: 1 | J82: 46196
B83: E3500307 | C83: MOROKREMBANGAN | D83: IOH | E83: Coax RTN | F83: tarikan | G83: 2 | J83: 46196
B84: E3500307 | C84: MOROKREMBANGAN | D84: IOH | E84: Jumper Antenna RF | F84: pcs | G84: 18 | J84: 46196
B85: E3500307 | C85: MOROKREMBANGAN | D85: IOH | E85: AHECC | F85: pcs | G85: 3 | H85: KG252518520 RW242300802 KG252911421 | J85: 46196
B86: E3500307 | C86: MOROKREMBANGAN | D86: IOH | E86: FXDB | F86: pcs | G86: 2 | H86: L6130818055 L6130914051 | J86: 46196
B87: E3500307 | C87: MOROKREMBANGAN | D87: IOH | E87: Kabel power biru-hitam | F87: tarikan | G87: 3 | J87: 46196
B88: E3500307 | C88: MOROKREMBANGAN | D88: IOH | E88: kabel hybrid | F88: tarikan | G88: 1 | J88: 46196
B89: E3500307 | C89: MOROKREMBANGAN | D89: IOH | E89: Rack Recty | F89: set | G89: 1 | I89: Westindo | J89: 46196
B90: E3500307 | C90: MOROKREMBANGAN | D90: IOH | E90: Sub Rack | F90: pcs | G90: 1 | I90: Eltek | J90: 46196
B91: E3500307 | C91: MOROKREMBANGAN | D91: IOH | E91: Modul ACDC | F91: pcs | G91: 4 | J91: 46196
B92: E3500307 | C92: MOROKREMBANGAN | D92: IOH | E92: IDU RTN | F92: pcs | G92: 1 | J92: 46196
B93: E3500307 | C93: MOROKREMBANGAN | D93: IOH | E93: AMIA | F93: pcs | G93: 1 | J93: 46196
B94: E3500307 | C94: MOROKREMBANGAN | D94: IOH | E94: ABIA | F94: pcs | G94: 1 | J94: 46196
B95: E3500307 | C95: MOROKREMBANGAN | D95: IOH | E95: ABIO | F95: pcs | G95: 1 | J95: 46196
B96: E3500307 | C96: MOROKREMBANGAN | D96: IOH | E96: ASIB | F96: pcs | G96: 1 | J96: 46196
B97: E3500307 | C97: MOROKREMBANGAN | D97: XLS | E97: Sub Rack | F97: set | G97: 1 | I97: 26.06.26 Diambil MS XLS | J97: 46199
B98: E3500307 | C98: MOROKREMBANGAN | D98: XLS | E98: Modul subrack | F98: pcs | G98: 4 | I98: 26.06.26 Diambil MS XLS | J98: 46199
B99: E3500307 | C99: MOROKREMBANGAN | D99: XLS | E99: Modul SMU | F99: pcs | G99: 1 | I99: 26.06.26 Diambil MS XLS | J99: 46199
B100: E3500307 | C100: MOROKREMBANGAN | D100: XLS | E100: Kabel power battery | F100: tarikan | G100: 2 | I100: 26.06.26 Diambil MS XLS | J100: 46199
B101: E3500307 | C101: MOROKREMBANGAN | D101: XLS | E101: Antenna sector | F101: pcs | G101: 3
B102: E3500307 | C102: MOROKREMBANGAN | D102: XLS | E102: Antenna AAU | F102: pcs | G102: 2
B103: E3500307 | C103: MOROKREMBANGAN | D103: XLS | E103: RRU | F103: pcs | G103: 5
B104: E3500307 | C104: MOROKREMBANGAN | D104: XLS | E104: Kabel power AAU | F104: tarikan | G104: 2
B105: E3500307 | C105: MOROKREMBANGAN | D105: XLS | E105: Kabel power RRU | F105: tarikan | G105: 5
B106: E3500307 | C106: MOROKREMBANGAN | D106: XLS | E106: Jumper | F106: pcs | G106: 18
B107: E3500307 | C107: MOROKREMBANGAN | D107: XLS | E107: DCPD 10B | F107: pcs | G107: 2
B108: E3500307 | C108: MOROKREMBANGAN | D108: XLS | E108: ZXRAN V9200 | F108: pcs | G108: 1 | H108: 219642055147
B109: E3500307 | C109: MOROKREMBANGAN | D109: XLS | E109: VBPe2q | F109: pcs | G109: 1
B110: E3500307 | C110: MOROKREMBANGAN | D110: XLS | E110: VPDc1 | F110: pcs | G110: 1
...

Sheet LOS Survey
C1: LINK INFORMATION
U2: 14BRS0006 KARANGJUNTI_CM | V2: 14BRS0011 RUNGKANG_TB
C3: Near End | I3: Far End | O3: Result | P3: Remark | T3: Latitude | U3: 6°54'51.5"S | V3: 6°54'58.1"S
A4: Site ID | B4: Site Name | C4: Site ID & Site Name (A) | D4: Longitude (e) | E4: Latitude (s) | F4: Antenna Height (m) | G4: Azimuth (º) | H4: Distance (Km) | I4: Candidate | J4: Site ID & Site Name (B) | K4: Longitude (e) | L4: Latitude (s) | M4: Antenna Height (m) | N4: Azimuth (º) | T4: Longitude | U4: 108°47'39.1"E | V4: 108°48'32.4"E
A5: R1200302 | B5: BANGUN PURBA | C5: SUM-SU-LBP-0054 BANGUN PURBA Relocation | F5: proposed at height 60 | G5: 185 | H5: 8.1 | J5: SUM-SU-SRH-1245 Sei Buaya | K5: 98.8075625 | L5: 3.2984375 | M5: proposed at height 50 | N5: 6 | O5: LOS | P5: Need actual survey | T5: True azimuth (°) | U5: 90 | V5: 15
A6: R1200302 | B6: BANGUN PURBA | C6: SUM-SU-LBP-0054 BANGUN PURBA Relocation | F6: proposed at height 52 | G6: 10.5 | H6: 6.6 | J6: SUM-SU-LBP-0412 Batu Lokong | K6: 98.8301875 | L6: 3.4295625 | M6: proposed at height 55 | N6: 195 | O6: LOS | P6: Need actual survey | T6: Elevation (m) | U6: 12 | V6: 18
A7: R1200302 | B7: BANGUN PURBA | C7: SUM-SU-LBP-0054 BANGUN PURBA Relocation | F7: proposed at height 53 | G7: 10 | H7: 12.9 | J7: SUM-SU-SRH-8224 SF_Pematang Raya 2_COLLECTOR | K7: 98.79774944 | L7: 3.255764722 | M7: proposed at height 55 | N7: 190 | O7: LOS | P7: Need actual survey
A8: E3500158 | B8: PLANDI | C8: 16JMB0118 SUMBER_MULYO_MT | D8: 112.26398 | E8: -7.56379 | F8: proposed at height 43 | G8: 220 | H8: 1.1 | I8: 1 | J8: 16JMB0108 PLANDI_JMB1_EP | K8: 112.257794 | L8: -7.57167 | M8: proposed at height 32 | N8: 40 | O8: LOS
A9: R3350421 | B9: KARANGJUNTI | C9: 14BRS0006 KARANGJUNTI_CM | D9: 108.7942 | E9: -6.9143 | F9: proposed at height 40 | G9: 190 | H9: 1.57 | I9: 1 | J9: 14BRS0004 KUBANGDJERO_TB | K9: 108.79078 | L9: -6.92804 | M9: proposed at height 38 | N9: 20 | O9: LOS
A10: R3350421 | B10: KARANGJUNTI | C10: 14BRS0006 KARANGJUNTI_CM | D10: 108.7942 | E10: -6.9143 | F10: proposed at height 40 | G10: 90 | H10: 1.64 | I10: 2 | J10: 14BRS0011 RUNGKANG_TB | K10: 108.809 | L10: -6.91615 | M10: proposed at height 40 | N10: 280 | O10: LOS
A11: R3350421 | B11: KARANGJUNTI | C11: 14BRS0006 KARANGJUNTI_CM | D11: 108.7942 | E11: -6.9143 | F11: proposed at height 40 | G11: 50 | H11: 2.37 | I11: 3 | J11: 14BRS0013 PEJAGAN3RUNGKANG_AG | K11: 108.81081 | L11: -6.90065 | M11: proposed at height 50 | N11: 230 | O11: LOS
A12: E3200182 | B12: GEULIS_RESORT | C12: E3200182 GEULIS_RESORT | D12: 106.866094 | E12: -6.631617 | F12: Proposed at height 49 | G12: 290 | H12: 3.51 | J12: JAW-JB-BGR-0421 GERBANG CIAWI | K12: 106.835292 | L12: -6.623942 | M12: Existing

Sheet List team
A1: No | B1: Nama | C1: ID KTP | D1: Tanggal Lahir | E1: Task | F1: Province | G1: Jenis Sertif | H1: No Sertif | I1: Contact
A2: 1 | B2: Utut Wahyu Eka | C2: 3175101512870006 | D2: 32126 | E2: Engineer | F2: BALI
A3: 2 | B3: Hoirul Anam | C3: 3509131008950005 | D3: 34921 | E3: Team Leader | F3: BALI | G3: TKPK1 | H3: 12625/TKPK-TK1/XII/2021
A4: 3 | B4: Muhammad Bahtiar | C4: 3501120202880002 | D4: 32175 | E4: Installer | F4: BALI | G4: TKPK1 | H4: 1221181022/N-TKPK1/31/X/2022
A5: 4 | B5: Martono | C5: 3511700407860004 | D5: 31597 | E5: Installer | F5: BALI
A6: 5 | B6: Ardiyanto Lase | C6: 2171121512900000 | D6: 15/12/1990 | E6: Installer | F6: BALI | G6: FA | H6: 00716/020/DSB/P3K/SEPTEMBER/22
A7: 6 | B7: M. Andrian Armeidiana | C7: 3522060205930005 | D7: 34005 | E7: Team Leader | F7: JAKARTA | G7: FA | H7: 00844/024/DSB/P3K/OCTOBER/22
A8: 7 | B8: Bagus Tri Wardani | C8: 3517071608910002 | D8: 16/8/1991 | E8: Installer | F8: JAKARTA | G8: TKPK1 | H8: 0184021122/N-TKPK1/32/XI/2022
A9: 8 | B9: Akhmad Soleh | C9: 3371010708840001 | D9: 7/8/1984 | E9: Installer | F9: JAKARTA
A10: 9 | B10: Akub | C10: 3604161201900001 | D10: 20/1/1990 | E10: Installer | F10: JAKARTA
A11: 10 | B11: Joko Dedoyo Kecil Liyanto | C11: 3315121502970005 | D11: 35476 | E11: Engineer | F11: JAWA TENGAH
A12: 11 | B12: Muhamad Ali Nur S | C12: 3315122911940002 | D12: 34667 | E12: Team Leader | F12: JAWA TENGAH | G12: TKPK1 | H12: 0843281022/N-TKPK1/33/X/2022
A13: 12 | B13: Jimmi Perdana Putra | C13: 3315120408010003 | D13: 36533 | E13: Member | F13: JAWA TENGAH | G13: TKPK1 | H13: 0414200922/N-TKPK1/31/IX/2022
A14: 13 | B14: Hengki Irawan | C14: 3315120107010009 | D14: 36532 | E14: Member | F14: JAWA TENGAH
A15: 14 | B15: Rano Aprilian Werdhana | C15: 3578040604880002 | D15: 32239 | E15: Team Leader | F15: JAWATIMUR | G15: TKPK1 | H15: 0218190522/N-TKPK1/31/V/2022
A16: 15 | B16: Adi Putra | C16: 3516070402920001 | D16: 33638 | E16: Installer | F16: JAWA TIMUR | G16: TKPK1 | H16: 5268/TKPKT-T1-TELKO/X/2021
A17: 16 | B17: Riza Brama Putra | C17: 3578041202860001 | D17: 31455 | E17: Installer | F17: JAWA TIMUR
A18: 17 | B18: Dicky Dermawan | C18: 3578042504020001 | D18: 37371 | E18: Installer | F18: JAWA TIMUR | G18: TKPK1 | H18: 3378/TKPK-TK1-TELKO/X/2020-BT
A19: 18 | B19: Widodo | C19: 3578091606740001 | D19: 16/06/1974 | E19: Installer | F19: JAWA TIMUR | G19: FA | H19: 01129/042/DSB/P3K/DECEMBER/22
A20: 19 | B20: Mohamad Hendra | C20: 5308181905860000 | D20: 19/05/1986 | E20: Team Leader | F20: KALIMANTAN TIMUR
A21: 20 | B21: Brayen Varmandhella | C21: 3506131805990001 | D21: 18/05/1999 | E21: Installer | F21: KALIMANTAN TIMUR | G21: TKPK1 | H21: 0548220722/N-TKPK1/51/VII/2022
A22: 21 | B22: Tri Nurdiansyah | C22: 3216071611950006 | D22: 16/11/1995 | E22: Installer | F22: KALIMANTAN TIMUR | G22: TKPK1 | H22: 22674/TKBT-TK2/X/2020-BT
A23: 22 | B23: Samsudin Bin Arbaa | C23: 5308181007910001 | D23: 33518 | E23: Installer | F23: KALIMANTAN TIMUR
A24: 25 | B24: Sunarji | C24: 3524161003880001 | D24: 31481 | E24: Installer | F24: LAMPUNG | G24: FA | H24: 01128/042/DSB/P3K/DECEMBER/22
A25: 27 | B25: ahmad | C25: 7371091507860007 | D25: 31608 | E25: Team Leader | F25: MALUKU UTARA
A26: 28 | B26: Putut Rahadi | C26: 3578140909680000 | D26: 27958 | E26: Installer | F26: MALUKU UTARA | G26: TKPK1 | H26: 4957/TKPK-TK1-TELKO/X/2021
A27: 29 | B27: Andi Kurniawan | C27: 3328181808890006 | D27: 32738 | E27: Installer | F27: MALUKU UTARA
A28: 30 | B28: Achmad Taufan Ardhitya Nugraha | C28: 3578082603000001 | D28: 36610 | E28: Installer | F28: MALUKU UTARA | G28: TKPK1 | H28: 0559220722/N-TKPK1/35/VII/2022
A29: 31 | B29: Obet Benmetan | C29: 5302072405020001 | D29: 37400 | E29: Engineer | F29: NTT
A30: 32 | B30: Tarman | C30: 3514011709780001 | D30: 28750 | E30: Team Leader | F30: NTT | G30: TKPK1 | H30: 0058011022/N-TKPK1/32/X/2022
A31: 33 | B31: Fredi Septi Arianto | C31: 3517132409880002 | D31: 32410 | E31: Member | F31: NTT | G31: TKPK1 | H31: 4350/TKPK-TK1-TELKO/IV/2021
A32: 34 | B32: Sunardi | C32: 3574030410840005 | D32: 30959 | E32: Member
A33: 35 | B33: ABD. KARIM JOKO WIBOWO | C33: 7306132109790002 | D33: 26563 | E33: Team Leader | F33: PAPUA TENGAH
A34: 36 | B34: MUH. SAMSUNAR S | C34: 7371120702030007 | D34: 36587 | E34: Member | F34: PAPUA TENGAH
A35: 37 | B35: SAPARUDDIN | C35: 7305011002850001 | D35: 31088 | E35: Member | F35: PAPUA TENGAH
A36: 38 | B36: Moch. Ridwan | C36: 3578141006820003 | D36: 30112 | E36: Member | F36: PAPUA TENGAH | G36: TKPK1 | H36: 4960/TKPK-TK1-TELKO/X/2021
A37: 39 | B37: Saddam Husein | C37: 3578071905920001 | D37: 33743 | E37: Member | F37: PAPUA TENGAH | G37: TKPK1 | H37: 4959/TKPK-TK1-TELKO/X/2021
A38: 40 | B38: Moch Haris Islami | C38: 3578060812840002 | D38: 31024 | E38: Team Leader | F38: RIAU | G38: TKPK1 | H38: 5/0783240622/AS.01.04/VI/2022
A39: 41 | B39: Rafsyanjani Akbar | C39: 3215051102870003 | D39: 31819 | E39: Member | F39: RIAU | G39: TKPK1 | H39: 4958/TKPK-TK1-TELKO/X/2021
A40: 42 | B40: Rekli Mustofa | C40: 3374131209790006 | D40: 29110 | E40: Member | F40: RIAU
A41: 43 | B41: Hari Jumardi | C41: 1302122903850001 | D41: 31135 | E41: Member | F41: RIAU
A42: 44 | B42: Defta Maulana | C42: 1408033011900001 | D42: 30/11/1990 | E42: Team Leader | F42: RIAU
A43: 45 | B43: Edi Suwanto | C43: 1471071007750042 | D43: 27674 | E43: Installer | F43: RIAU
A44: 46 | B44: Beri Ahmad | C44: 1403091612885463 | D44: 16/12/1988 | E44: Installer | F44: RIAU
A45: 47 | B45: Mawardi | C45: 1106023004860003 | D45: 31532 | E45: Installer | F45: RIAU | G45: TKPK1 | H45: 2855040624/N-TKPK1/14/VI/2024
A46: 48 | B46: Muh. Nur Rizky | C46: 7371091804010001 | D46: 36529 | E46: Engineer | F46: SULAWESI SELATAN
A47: 49 | B47: Imam Taupik | C47: 3523051007900001 | D47: 33064 | E47: Team Leader | F47: SULAWESI SELATAN | G47: TKPK1 | H47: 0563220722/N-TKPK1/35/VII/2022
A48: 50 | B48: Faisol Amir | C48: 3524050603850004 | D48: 31112 | E48: Member | F48: SULAWESI SELATAN | G48: TKPK1 | H48: P.17.1813/TKPK-TK1/XII/2021
A49: 51 | B49: Sapri | C49: 7306131810910001 | D49: 33529 | E49: Member | F49: SULAWESI SELATAN
A50: 52 | B50: Rahman | C50: 7306081708870020 | D50: 32006 | E50: Member | F50: SULAWESI SELATAN
A51: 58 | B51: Saiful S | C51: 7371121808790000 | D51: 18/08/1979 | E51: Team Leader | F51: SULAWESI TENGGARA
A52: 59 | B52: Muh.Amin | C52: 7305011504910000 | D52: 15/01/1991 | E52: Installer | F52: SULAWESI TENGGARA
A53: 62 | B53: MUH. AMIN | C53: 7305011504910001 | D53: 33343 | E53: Team Leader | F53: SULAWESI TENGGARA
A54: 63 | B54: SUARJO | C54: 7315043112950113 | D54: 35064 | E54: Member | F54: SULAWESI TENGGARA
A55: 64 | B55: SAMIR | C55: 7371091211810008 | D55: 29902 | E55: Member | F55: SULAWESI TENGGARA
A56: 65 | B56: Samson Hidayat | C56: 3524160202870004 | D56: 31810 | E56: Member | F56: SULAWESI TENGGARA | G56: TKPK1 | H56: 0561220722/722/N-TKPK1/35/VII/2022
A57: 67 | B57: Rizky Fernanda Nur LBS | C57: 1205143007020007 | D57: 37467 | E57: Engineer | F57: SUMATERA BARAT | G57: TKPK1 | H57: 2848040624/N-TKPK1/14/VI/2024
A58: 68 | B58: Alam Syah Ginta | C58: 1219011912800001 | D58: 29574 | E58: Team Leader | F58: SUMATERA BARAT | G58: TKPK1 | H58: 4336040624/N-TKPK1/14/VI/2024
A59: 69 | B59: Sediaman | C59: 1271211211780001 | E59: Member | F59: SUMATERA BARAT
A60: 70 | B60: Pardin Daulay | C60: 1203070609811001 | E60: Member | F60: SUMATERA BARAT
A61: 71 | B61: Tryas Catur Ananda | C61: 3522082005900000 | E61: Member | F61: SUMATERA BARAT | G61: FA | H61: 273/PJK3-MEJ-P3K-DTK/BDT-T/DSB/20/06/2022
A62: 72 | B62: Ismail | C62: 1271211204800003 | D62: 29323 | E62: Team Leader | F62: SUMATERA BARAT
A63: 74 | B63: Darwin | C63: 1271212912740003 | D63: 27392 | E63: Member | F63: SUMATERA BARAT | G63: TKPK1 | H63: 2849040624/N-TKPK1/14/VI/2024
A64: 75 | B64: Pirmansyah | C64: 1205130109980002 | D64: 36039 | E64: Member | F64: SUMATERA BARAT
A65: 72 | B65: Aldira Hidayat | C65: 1207211704020000 | D65: 37363 | E65: Member | F65: SUMATERA BARAT
A66: 74 | B66: Maolana Abdi | C66: 5271012108940004 | D66: 34066 | E66: Installer | F66: SUMATERA UTARA | G66: TKPK1 | H66: 0145071022/N-TKPK1/32/X/2022
A67: 75 | B67: Jumadi Tampubolon | C67: 5207062105870002 | D67: 31918 | E67: Installer | F67: SUMATERA UTARA
A68: 72 | B68: Endy | C68: 1207260704930008 | D68: 34066 | E68: Installer | F68: SUMATERA UTARA
B69: Amri Ricardo Sinaga | C69: 1208162305930002 | D69: 34112 | F69: SUMATERA UTARA | I69: +62 888-0774-1023
B70: Bento Sory Pinagar Silalahi | C70: 1208060911940002 | D70: 34647 | F70: SUMATERA UTARA
B71: Joy Denharris Manurung | C71: 1208160509970002 | D71: 36043 | F71: SUMATERA UTARA | H71: 2065090523/TKBT2/13/V/2023
B72: Juhendi Markus Sinaga | C72: 1208160405850001 | D72: 34703 | F72: SUMATERA UTARA | H72: 0547150526/N-TKPK1/30/V/2026

Sheet Email Permit
A1: No | B1: Name | C1: PIC Site | D1: ID KTP | E1: Contact Number | F1: Email Company | G1: Password | H1: Start Account | I1: Expired Account | J1: Validity Account
A2: 1 | B2: Muhamad Darmanto | D2: 3309142707940006 | E2: 087865247367 | F2: darmanto@tunggalsahabat.co.id | H2: 46119 | I2: 46179 | J2: =IF(I2="","",I2-TODAY()) -> -60
A3: =+A2+1 -> 2 | B3: Muchamad Faiz Fahmi | D3: 3325080505030004 | E3: 085643166021 | F3: faizfahmi@tunggalsahabat.co.id | H3: 46119 | I3: =+H3+60 -> 46179 | J3: =IF(I3="","",I3-TODAY()) -> -60
A4: =+A3+1 -> 3 | B4: Arrys Yasir Zulkarnain | D4: 3515111205800002 | E4: 089612377850 | F4: yasir@tunggalsahabat.co.id | H4: 46119 | I4: =+H4+60 -> 46179 | J4: =IF(I4="","",I4-TODAY()) -> -60
A5: =+A4+1 -> 4 | B5: FARIZ MEYER | D5: 3203112212830003 | E5: 08814372949 | F5: fariz@tunggalsahabat.co.id | H5: 46119 | I5: =+H5+60 -> 46179 | J5: =IF(I5="","",I5-TODAY()) -> -60
A6: =+A5+1 -> 5 | B6: TAUFIK HIDAYAT | D6: 3275081809800033 | E6: 081213207645 | F6: taufik@tunggalsahabat.co.id | H6: 46119 | I6: =+H6+60 -> 46179 | J6: =IF(I6="","",I6-TODAY()) -> -60
A7: =+A6+1 -> 6 | B7: Abe Taskura Rizal | D7: 3578020206890006 | E7: 082141021724 | F7: abe.taskurarizal@tunggalsahabat.co.id | H7: 46119 | I7: =+H7+60 -> 46179 | J7: =IF(I7="","",I7-TODAY()) -> -60
A8: =+A7+1 -> 7 | B8: JOKO NURSIO | D8: 3578182109800001 | E8: 087777788432 | F8: joko.nursio@tunggalsahabat.co.id | J8: =IF(I8="","",I8-TODAY())
A9: 8 | B9: Suliswanto | D9: 3316071612950001 | E9: 089670307305 | F9: suliswanto@tunggalsahabat.co.id | G9: &,=U^$rM*k^H
A10: =+A8+1 -> 8 | B10: Ilham Tirta Kawah | D10: 3578052606930002 | E10: 085933744676 | F10: Ilham.tirta@tunggalsahabat.co.id | H10: 46119 | I10: 46179 | J10: =IF(I10="","",I10-TODAY()) -> -60
A11: =+A10+1 -> 9 | B11: Munasirin | C11: Centra Java | D11: 3324012212860001 | E11: +62 812-5666-0163 | F11: munasirin.ext_cj@tunggalsahabat.co.id | G11: w[CatTrQLY7G | J11: =IF(I11="","",I11-TODAY())
A12: =+A11+1 -> 10 | B12: Rano Aprilian Werdhana | C12: East Java | D12: 3578040604880002 | E12: +62 896-7799-6532 | F12: rano.ext_jav@tunggalsahabat.co.id | G12: Pdyp4Pm,$!@X | J12: =IF(I12="","",I12-TODAY())
A13: =+A12+1 -> 11 | B13: Herawan Bin Nasir | C13: Kep. Riau | E13: +62 859-3834-20733 | F13: herawan.ext_sum@tunggalsahabat.co.id | G13: b,kTkZ&n4Db2 | J13: =IF(I13="","",I13-TODAY())
A14: =+A13+1 -> 12 | B14: Sunandar Sandya Ramdhan | C14: Central Kalimantan | D14: 7304032512990002 | E14: +62 823-5732-2405 | F14: sandya.ext_kal@tunggalsahabat.co.id | G14: OrDJNCv?J3oH | J14: =IF(I14="","",I14-TODAY())
A15: =+A14+1 -> 13 | B15: Adi Nugroho | E15: +62 812-3567-0006 | F15: adinugroho.ext@tunggalsahabat.co.id | G15: ~K,yBNDoX&@y | J15: =IF(I15="","",I15-TODAY())
A16: =+A15+1 -> 14 | B16: Andi Wawan | C16: West Java | D16: 3275010107750260 | E16: +62 819-9910-1650 | F16: andiwawan.ext_wj@tunggalsahabat.co.id | G16: wgwYgLGQbl$6 | J16: =IF(I16="","",I16-TODAY())
A17: =+A16+1 -> 15 | B17: Dedi Djunaidi | C17: Sulawesi | D17: 7171032606700001 | E17: +62 81-1412-1707 | F17: djunaidi.ext_sul@tunggalsahabat.co.id | G17: VPZ^J}VD8mWF | J17: =IF(I17="","",I17-TODAY())
A18: =+A17+1 -> 16 | B18: Safar | C18: Sulawesi Tenggara | D18: 7402020511850003 | E18: +62 852-4162-2480 | F18: safar.ext_ken@tunggalsahabat.co.id | G18: &eg?Q5Y2V~ff | J18: =IF(I18="","",I18-TODAY())
A19: =+A18+1 -> 17 | B19: Dwi Raharjo | C19: Jabo | D19: 3304121003890006 | E19: +62 838-4577-1263 | F19: raharjo.ext_jabo@tunggalsahabat.co.id | G19: *5tuQ@s?yw2# | J19: =IF(I19="","",I19-TODAY())
A20: =+A19+1 -> 18 | B20: Rangga Kenanga | C20: Jabo | D20: 3201201409810001 | E20: +62 895-1706-7001 | F20: rangga.kenanga@tunggalsahabat.co.id | G20: 6q5e*8)0UU9z | J20: =IF(I20="","",I20-TODAY())
A21: =+A20+1 -> 19 | B21: Dicky Dermawan | C21: East Java | D21: 3578042504020001 | E21: +62 819-590-886 | F21: dicky.dermawan_ext@tunghalsahabat.co.id | G21: 9@6Y549;*Y26 | J21: =IF(I21="","",I21-TODAY())
A22: =+A21+1 -> 20 | B22: Haslan | C22: Sulawesi Selatan | D22: 7372041010840003 | F22: haslan_ext@tunggalsahabat.co.id | G22: bv#(RWlm~VR= | J22: =IF(I22="","",I22-TODAY())
A23: =+A22+1 -> 21 | B23: Agus Sudarwanto | C23: East Java | D23: 3524131805850002 | F23: agus.sudarwanto_ext@tunggalsahabat.co.id | G23: +}aYEo)0ssT0% | J23: =IF(I23="","",I23-TODAY())
A24: =+A23+1 -> 22 | B24: Muchammad Adhim | C24: East Java | D24: 3515130404860005 | F24: muchammad.adhim_ext@tunggalsahabat.co.id | G24: pTo_[-2v7,{q | J24: =IF(I24="","",I24-TODAY())
A25: =+A24+1 -> 23 | B25: Hoirul Anam | C25: East Java | D25: 3524131805850002 | F25: hoirulanam.ext_ej@tunggalsahabat.co.id | G25: Td7Tj=mN$~t^ | J25: =IF(I25="","",I25-TODAY())
A26: =+A25+1 -> 24 | B26: Bayu Martin Iksanudin | C26: West Java | D26: 3315121209950002 | F26: bayu.martin_ext@tunggalsahabat.co.id | G26: zY$C^lcK47]l | J26: =IF(I26="","",I26-TODAY())
A27: =+A26+1 -> 25 | B27: Arif Moh Riyadi | C27: Central Java | D27: 3315121006860001 | F27: arif.mohriyadi_ext@tunggalsahabat.co.id | G27: Doiw4{hY}veM | J27: =IF(I27="","",I27-TODAY())
A28: =+A27+1 -> 26 | B28: Mubarok | C28: East Java | D28: 3578161408870011 | F28: mubarok_ext@tunggalsahabat.co.id | G28: 2#.ZVXUo;akB | J28: =IF(I28="","",I28-TODAY())
A29: =+A28+1 -> 27 | B29: Yuda | C29: West Java | D29: 3216220112820005 | F29: yuda.ext@tunggalsahabat.co.id | G29: wo&cF!d@olge | J29: =IF(I29="","",I29-TODAY())
A30: =+A29+1 -> 28 | B30: Haris Affandie | C30: Kalimantan | D30: 6471052008800013 | E30: 081258518280 | F30: haris.affandie_ext@tunggalsahabat.co.id | G30: -A_n-a5o#2Ha | J30: =IF(I30="","",I30-TODAY())
A31: =+A30+1 -> 29 | B31: Bambang Sumartono | C31: Central Java | D31: 3374091003740004 | E31: 085742288777 | F31: bambang_ext.cj@tunggalsahabat.co.id | G31: #1F;)ybihtst | J31: =IF(I31="","",I31-TODAY())
A32: =+A31+1 -> 30 | B32: Tri Margiyanto | C32: JAYENGAN | D32: 3311012907830000 | E32: 085332424444 | F32: tri.margiyanto_ext@tunggalsahabat.co.id | G32: QK4rwj]SJ2YF | J32: =IF(I32="","",I32-TODAY())
A33: =+A32+1 -> 31 | B33: Yoricho Bashkara | C33: PEMENANG BARAT | D33: 3275091304950022 | E33: 087845606243 | F33: yoricho.bashkara@tunggal.sahabat.co.id | G33: QJ0mrq3Vy,IN | J33: =IF(I33="","",I33-TODAY())
A34: =+A33+1 -> 32 | B34: Yayat | C34: Kayoon | D34: 3211180401790001 | E34: 083148960851 | F34: yayat_ext@tunggalsahabat.co.id | G34: En4W{a.vOGbc | J34: =IF(I34="","",I34-TODAY())
A35: =+A34+1 -> 33 | B35: Ajang Suprianto | E35: 08813913468 | F35: ajang.suprianto_ext@tunggalsahabat.co.id | G35: }2bt8Cs*O=-p | J35: =IF(I35="","",I35-TODAY())
A36: =+A35+1 -> 34 | B36: Dede Darno | E36: 083112166206 | F36: dede.darno_ext@tunggalsahabat.co.id | G36: r5%AXQTo$&ec | J36: =IF(I36="","",I36-TODAY())
A37: =+A36+1 -> 35 | B37: Edih | E37: 085600237809 | F37: edih_ext@tunggalsahabat.co.id | G37: j%V+3]?sfF.] | J37: =IF(I37="","",I37-TODAY())
A38: =+A37+1 -> 36 | B38: Priatna | C38: Kayoon | D38: 3211130901890002 | E38: 088295614399 | F38: priatna_ext@tunggalsahabat.co.id | G38: f?~.;{n36q#u | J38: =IF(I38="","",I38-TODAY())
A39: =+A38+1 -> 37 | B39: Supriatna | C39: Kayoon | D39: 3211112311740009 | E39: 082286731149 | F39: supriatna_ext@tunggalsahabat.co.id | G39: ,@,WRs)QS(NV | J39: =IF(I39="","",I39-TODAY())
A40: =+A39+1 -> 38 | B40: Wino | C40: Kayoon | D40: 3304141604820004 | E40: 085291104789 | F40: wino_ext@tunggalsahabat.co.id | G40: !?G~9r5=uyaj | J40: =IF(I40="","",I40-TODAY())
A41: =+A40+1 -> 39 | B41: Bibit Purwanto | C41: Kayoon | D41: 3373010201840002 | E41: +62 822-3408-7449 | F41: bibit.purwanto_ext@tunggalsahabat.co.id | G41: O.V}mG@4m-4} | J41: =IF(I41="","",I41-TODAY())
A42: =+A41+1 -> 40 | B42: Tri Heru Saputro | C42: Kayoon | D42: 3374131107810002 | E42: +62 856-4341-6014 | F42: tri.herusaputro_ext@tunggalsahabat.co.id | G42: 8n0X3d5_25N5 | J42: =IF(I42="","",I42-TODAY())
A43: =+A42+1 -> 41 | B43: Slamet Riyadi | C43: Kayoon | D43: 3306060307830004 | E43: +62 831-3121-2477 | F43: slamet.riyadi_ext@tunggalsahabat.co.id | G43: k*Q(qI+i(S$_ | J43: =IF(I43="","",I43-TODAY())
A44: =+A43+1 -> 42 | B44: Beni Prasetyo | C44: Kayoon | D44: 3373011001800006 | E44: +62 831-9397-3243 | F44: beni.prasetyo_ext@tunggalsahabat.co.id | G44: K#&&R-~IIfn* | J44: =IF(I44="","",I44-TODAY())
A45: =+A44+1 -> 43 | B45: Sodikin | C45: Kayoon | D45: 3322060912820001 | E45: +62 851-8935-4982 | F45: sodikin_ext@tunggalsahabat.co.id | G45: Tt]ee(aWmO#o | J45: =IF(I45="","",I45-TODAY())
A46: =+A45+1 -> 44 | B46: Eko Hariyanto | C46: Kayoon | D46: 3373012007830003 | E46: +62 857-0466-5890 | F46: eko.hariyanto_ext@tunggalsahabat.co.id | G46: 2]#aCG?p$K$h | J46: =IF(I46="","",I46-TODAY())
A47: =+A46+1 -> 45 | B47: Dafit Suhirwanto | C47: Kayoon | D47: 3322062408850001 | E47: +62 819-3668-3830 | F47: dafit.suhirwanto_ext@tunggalsahabat.co.id | G47: 8X6xX7df3ohm | J47: =IF(I47="","",I47-TODAY())
A48: =+A47+1 -> 46 | B48: Prolis Heru Murdiyanto | C48: Kayoon | D48: 3578060812800003 | E48: +62 822-2881-9193 | F48: prolisheru@tunggalsahabat.co.id | J48: =IF(I48="","",I48-TODAY())
A49: =+A48+1 -> 47 | B49: Kusmana Ardiansyah | F49: kusmana.ardiansyah_ext@tunggalsahabat.co.id | G49: v6bzIUL3?-[V | J49: =IF(I49="","",I49-TODAY())
A50: =+A49+1 -> 48 | B50: Al Kasan Sahbrawi | F50: alkasan.sahbrawi_ext@tunggalsahabat.co.id | G50: OCiAox(@n=a8 | J50: =IF(I50="","",I50-TODAY())
A51: =+A50+1 -> 49 | B51: H Ajo Eko | F51: h.ajoeko_ext@tunggalsahabat.co.id | G51: jXl$;%Xg9ph9 | J51: =IF(I51="","",I51-TODAY())
A52: =+A51+1 -> 50 | B52: Repah Eka Wigelar | F52: repah.eka_ext@tunggalsahabat.co.id | G52: noPXzC-TA!g& | J52: =IF(I52="","",I52-TODAY())
A53: =+A52+1 -> 51 | B53: Endi Suhendi | F53: endi.suhendi_ext@tunggalsahabat.co.id | G53: sUO$ZVnsgI%[ | J53: =IF(I53="","",I53-TODAY())
A54: =+A53+1 -> 52 | B54: Dedi | F54: dedi_ext@tunggalsahabat.co.id | G54: VOt,q%0kld_w | J54: =IF(I54="","",I54-TODAY())
A55: =+A54+1 -> 53 | B55: Mastam | F55: mastam_ext@tunggalsahabat.co.id | G55: Ab!CR8obxp=r | J55: =IF(I55="","",I55-TODAY())
A56: =+A55+1 -> 54 | B56: Nur Arifin | F56: nur.arifin_ext@tunggalsahabat.co.id | G56: ?42[Ggyk+XQz | J56: =IF(I56="","",I56-TODAY())
A57: =+A56+1 -> 55 | B57: Rifaldi | F57: rifaldi_ext@tunggalsahabat.co.id | G57: uq(T.y?km5qn | J57: =IF(I57="","",I57-TODAY())
A58: =+A57+1 -> 56 | B58: Taufan Agya Wiguna | F58: taufan.agya_ext@tunggalsahabat.co.id | G58: myJeqR}2e9-C | J58: =IF(I58="","",I58-TODAY())
A59: =+A58+1 -> 57 | B59: Demak Hutahean | C59: Sumatera Utara | D59: 1211012412890002 | J59: =IF(I59="","",I59-TODAY())
A60: =+A59+1 -> 58 | B60: Sumarlin Kaban | C60: Sumatera Utara | D60: 1211060207940001 | J60: =IF(I60="","",I60-TODAY())
A61: =+A60+1 -> 59 | B61: Jumadi Tampubolon | C61: Sumatera Utara | D61: 1207062105870002 | J61: =IF(I61="","",I61-TODAY())
A62: =+A61+1 -> 60 | B62: Arnold Zeneger Sigalingging | C62: Sumatera Utara | D62: 1211012911940002 | J62: =IF(I62="","",I62-TODAY())
A63: =+A62+1 -> 61 | B63: Miskam | C63: Sumatera Utara | D63: 3207361807810001 | J63: =IF(I63="","",I63-TODAY())
A64: =+A63+1 -> 62 | B64: Giyanto | C64: Jabo | D64: 3674040107780002 | E64: +62 812-9264-9788 | F64: giyanto.wj_ext@tunggalsahabat.co.id | G64: M#U.(Ni#fSt} | J64: =IF(I64="","",I64-TODAY())
A65: =+A64+1 -> 63 | B65: Stefanus Jatmiko | F65: stefanus.jatmiko_ext@tunggalsahabat.co.id | G65: DX_!HoF*>ZL | J65: =IF(I65="","",I65-TODAY())
A66: =+A65+1 -> 64 | B66: Yadi Hermansyah | F66: yadi.hermansyah_ext@tunggalsahabat.co.id | G66: XxkCR2#Up!., | J66: =IF(I66="","",I66-TODAY())
A67: =+A66+1 -> 65 | B67: Apudin Maulana | F67: apudin.maulana_ext@tunggalsahabat.co.id | G67: oVfC,o*Y2JB~ | J67: =IF(I67="","",I67-TODAY())
A68: =+A67+1 -> 66 | B68: Fauzi Arief | F68: fauzi.arief_ext@tunggalsahabat.co.id | G68: d}AItFWa-XG! | J68: =IF(I68="","",I68-TODAY())
A69: =+A68+1 -> 67 | B69: Ari Suryanto | F69: ari.suryanto_ext@tunggalsahabat.co.id | G69: s~lFTI1pvQ)I | J69: =IF(I69="","",I69-TODAY())
A70: =+A69+1 -> 68 | B70: Afryla Akbar | F70: afryla.akbar_ext@tunggalsahabat.co.id | G70: 8~Q{H?vaEhg3 | J70: =IF(I70="","",I70-TODAY())
A71: =+A70+1 -> 69 | B71: Husen Wahyudi | F71: husen.wahyudi_ext@tunggalsahabat.co.id | G71: ixB#YM-kiyWt | J71: =IF(I71="","",I71-TODAY())
A72: =+A71+1 -> 70 | B72: Onie Albert Manopo | F72: onie.albert_ext@tunggalsahabat.co.id | G72: tS&XSM.j]aR@ | J72: =IF(I72="","",I72-TODAY())
A73: =+A72+1 -> 71 | B73: Jefri Mokotika | F73: jefri.mokotika_ext@tunggalsahabat.co.id | G73: NmmPLD4Vk,xn | J73: =IF(I73="","",I73-TODAY())
A74: =+A73+1 -> 72 | B74: Ongky Kevin Tandaju | F74: ongky.kevin_ext@tunggalsahabat.co.id | G74: Y&?OB,04Rm32 | J74: =IF(I74="","",I74-TODAY())
A75: =+A74+1 -> 73 | B75: Yosua Ronaldo Andu | F75: yosua.ronaldo_ext@tunggalsahabat.co.id | G75: 3B~FW4d*+=2y | J75: =IF(I75="","",I75-TODAY())
A76: =+A75+1 -> 74 | B76: Saharuddin | F76: saharuddin_ext@tunggalsahabat.co.id | G76: 5^+30,Pj=07M | J76: =IF(I76="","",I76-TODAY())
... A78: =+A77+1 -> 76 | B78: Yoan Rivandi | F78: yoan.rivandi_ext@tunggalsahabat.co.id | G78: y+!~4SMQhLrQ | J78: =IF(I78="","",I78-TODAY())

Sheet SPH
L1: 6826391.4
B2: {=COUNTA(_xlfn.UNIQUE(_xlfn._xlws.FILTER(B4:B973,SUBTOTAL(3,OFFSET(B4,ROW(B4:B973)-ROW(B4),0)))))} -> 1 | C2: {=COUNTA(_xlfn.UNIQUE(_xlfn._xlws.FILTER(C4:C973,SUBTOTAL(3,OFFSET(C4,ROW(C4:C973)-ROW(C4),0)))))} -> 1 | D2: {=COUNTA(_xlfn.UNIQUE(_xlfn._xlws.FILTER(D4:D973,SUBTOTAL(3,OFFSET(D4,ROW(D4:D973)-ROW(D4),0)))))} -> 1 | L2: =+SUBTOTAL(9,L4:L978) -> 6.6794751e+08
A3: No | B3: Account Project | C3: Site ID | D3: Site Name | E3: Create Date | F3: SPH Number | G3: Scope | H3: Description | I3: Qty | J3: UoM | K3: Price | L3: Total | M3: DRM | N3: BAN App | O3: BAN Number | P3: Remark
B4: CMI-RLC-Nasional | C4: E3500300 | D4: DUKUH_KUPANG | E4: 45891 | F4: 006/TSA-SPH-CMI/VIII/2025 | G4: Dismantle Tower | H4: Biaya buat Pagar site keliling 48 m² | I4: 1 | J4: All In | K4: 75000000 | L4: =+I4*K4 -> 75000000 | N4: 45960
B5: CMI-RLC-Nasional | C5: E3500300 | D5: DUKUH_KUPANG | E5: 45891 | F5: 006/TSA-SPH-CMI/VIII/2025 | G5: Dismantle Tower | H5: Management fee pembuatan Pagar | I5: 0.1 | J5: All In | K5: 75000000 | L5: =+I5*K5 -> 7500000 | N5: 45960
B6: CMI-RLC-Nasional | C6: E3500300 | D6: DUKUH_KUPANG | E6: 45891 | F6: 006/TSA-SPH-CMI/VIII/2025 | G6: Dismantle Tower | H6: sewa genset 5 kva | I6: 2 | J6: day | K6: 1200000 | L6: =+I6*K6 -> 2400000 | N6: 45960
B7: CMI-RLC-Nasional | C7: E3500300 | D7: DUKUH_KUPANG | E7: 45891 | F7: 006/TSA-SPH-CMI/VIII/2025 | G7: Dismantle Tower | H7: BBM Genset | I7: 2 | J7: day | K7: 150000 | L7: =+I7*K7 -> 300000 | N7: 45960
B8: CMI-RLC-Nasional | C8: E3500300 | D8: DUKUH_KUPANG | E8: 45891 | F8: 006/TSA-SPH-CMI/VIII/2025 | G8: Dismantle Tower | H8: Operator Genset | I8: 2 | J8: day | K8: 150000 | L8: =+I8*K8 -> 300000 | N8: 45960
B9: CMI-RLC-Nasional | C9: E3500300 | D9: DUKUH_KUPANG | E9: 45891 | F9: 006/TSA-SPH-CMI/VIII/2025 | G9: Relocation Equipment | H9: Kabel AWG 10 XL | I9: 100 | J9: meter | K9: 35000 | L9: =+I9*K9 -> 3500000 | N9: 45960
B10: CMI-RLC-Nasional | C10: E3500300 | D10: DUKUH_KUPANG | E10: 45891 | F10: 006/TSA-SPH-CMI/VIII/2025 | G10: Relocation Equipment | H10: Kabel AWG 6 IOH | I10: 200 | J10: meter | K10: 55000 | L10: =+I10*K10 -> 11000000 | N10: 45960
B11: CMI-RLC-Nasional | C11: E3500300 | D11: DUKUH_KUPANG | E11: 45891 | F11: 006/TSA-SPH-CMI/VIII/2025 | G11: Relocation Equipment | H11: Kabel Feeder 7/8 | I11: 500 | J11: meter | K11: 50000 | L11: =+I11*K11 -> 25000000 | N11: 45960
B12: CMI-RLC-Nasional | C12: E3500300 | D12: DUKUH_KUPANG | E12: 45891 | F12: 006/TSA-SPH-CMI/VIII/2025 | G12: Relocation Equipment | H12: Jumper Feeder | I12: 10 | J12: pcs | K12: 450000 | L12: =+I12*K12 -> 4500000 | N12: 45960
B13: CMI-RLC-Nasional | C13: E3500300 | D13: DUKUH_KUPANG | E13: 45891 | F13: 006/TSA-SPH-CMI/VIII/2025 | G13: Relocation Equipment | H13: Connector Feeder | I13: 20 | J13: pcs | K13: 75000 | L13: =+I13*K13 -> 1500000 | N13: 45960
B14: CMI-RLC-Nasional | C14: E3300285 | D14: JAYENGAN | E14: 45961 | F14: 014/TSA-SPH-CMI/X/2025 | G14: Dismantle Tower | H14: Pembongkaran pondasi ex tower dan bts serta perapian renovasi gedung oleh pihak pemilik lahan | I14: 1 | J14: Ls | K14: 4650000 | L14: =+I14*K14 -> 4650000 | N14: 46028
B15: CMI-RLC-Nasional | C15: E3300285 | D15: JAYENGAN | E15: 45961 | F15: 014/TSA-SPH-CMI/X/2025 | G15: Dismantle Tower | H15: Management Fee | I15: 1 | J15: Ls | K15: 2700000 | L15: =+I15*K15 -> 2700000 | N15: 46028
... B24: CMI-RLC-Nasional | C24: E1200372 | D24: NONGSA_RESORT_1 | E24: 45943 | F24: 007/TSA-SPH-CMI/X/2025 | G24: Relocation Equipment | H24: Tiket Pesawat Batam - Jakarta | I24: 4 | J24: Person | K24: 1000000 | L24: =+I24*K24 -> 4000000 | N24: 46000
B25: CMI-RLC-Nasional | C25: E3600214 | D25: SUPERMAL | E25: 45959 | F25: 013/TSA-SPH-CMI/X/2025 | G25: Dismantle Tower | H25: Management Fee | I25: 1 | J25: Ls | K25: 2700000 | L25: =+I25*K25 -> 2700000
B26: CMI-RLC-Nasional | C26: E3600214 | D26: SUPERMAL | E26: 45959 | F26: 013/TSA-SPH-CMI/X/2025 | G26: Relocation Equipment | H26: Pembelian Rack Outdoor include delivery | I26: 2 | J26: unit | K26: 7000000 | L26: =+I26*K26 -> 14000000
B27: CMI-RLC-Nasional | C27: E3600214 | D27: SUPERMAL | E27: 45959 | F27: 013/TSA-SPH-CMI/X/2025 | G27: Relocation Equipment | H27: Pembelian Kabel AWG 10 | I27: 175 | J27: meter | K27: 35000 | L27: =+I27*K27 -> 6125000
B28: CMI-RLC-Nasional | C28: E3600214 | D28: SUPERMAL | E28: 45959 | F28: 013/TSA-SPH-CMI/X/2025 | G28: Relocation Equipment | H28: Pembelian opctic CPRI 70 meter | I28: 7 | J28: pcs | K28: 250000 | L28: =+I28*K28 -> 1750000
B29: CMI-RLC-Nasional | C29: E3600214 | D29: SUPERMAL | E29: 45959 | F29: 013/TSA-SPH-CMI/X/2025 | G29: Relocation Equipment | H29: Pembelian Kabel coax RG8 | I29: 100 | J29: meter | K29: 15000 | L29: =+I29*K29 -> 1500000
B30: CMI-RLC-Nasional | C30: E1200351 | D30: DANAGRAHA_BUILDING1 / DANA GRAHA | E30: 45965 | F30: 001/TSA-SPH-CMI/XI/2025 | G30: Dismantle Tower | H30: Scrap Lokal onsite | I30: 1488.6 | J30: Kg | K30: -1500 | L30: =+I30*K30 -> -2232900 | N30: 46365
B31: CMI-RLC-Nasional | C31: E1200351 | D31: DANAGRAHA_BUILDING1 / DANA GRAHA | E31: 45965 | F31: 001/TSA-SPH-CMI/XI/2025 | G31: Dismantle Tower | H31: Management Fee | I31: 1 | J31: Ls | K31: 2700000 | L31: =+I31*K31 -> 2700000 | N31: 46365
B32: CMI-RLC-Nasional | C32: E1200351 | D32: DANAGRAHA_BUILDING1 / DANA GRAHA | E32: 45965 | F32: 001/TSA-SPH-CMI/XI/2025 | G32: Dismantle Tower | H32: Membrane bakar merk fosroc 14 meter (2 rol x 10 m) | I32: 2 | J32: roll | K32: 1700000 | L32: =+I32*K32 -> 3400000 | N32: 46365
B33: CMI-RLC-Nasional | C33: E1200351 | D33: DANAGRAHA_BUILDING1 / DANA GRAHA | E33: 45965 | F33: 001/TSA-SPH-CMI/XI/2025 | G33: Dismantle Tower | H33: Tukang pasang membrane bakar | I33: 14 | J33: meter | K33: 80000 | L33: =+I33*K33 -> 1120000 | N33: 46365
B34: CMI-RLC-Nasional | C34: E1200351 | D34: DANAGRAHA_BUILDING1 / DANA GRAHA | E34: 45965 | F34: 001/TSA-SPH-CMI/XI/2025 | G34: Dismantle Tower | H34: Ongkos unloading material ke lt 6 | I34: 1 | J34: Ls | K34: 300000 | L34: =+I34*K34 -> 300000 | N34: 46365
B35: CMI-RLC-Nasional | C35: E1200351 | D35: DANAGRAHA_BUILDING1 / DANA GRAHA | E35: 45965 | F35: 001/TSA-SPH-CMI/XI/2025 | G35: Dismantle Tower | H35: PB-CME-266 Plester Aci | I35: 22 | J35: M² | K35: 56000 | L35: =+I35*K35 -> 1232000 | N35: 46365
B36: CMI-RLC-Nasional | C36: E1200351 | D36: DANAGRAHA_BUILDING1 / DANA GRAHA | E36: 45965 | F36: 001/TSA-SPH-CMI/XI/2025 | G36: Dismantle Tower | H36: PB-CME-266 Waterproofing (SikaTop 107 Seal) | I36: 22 | J36: M² | K36: 44000 | L36: =+I36*K36 -> 968000 | N36: 46365
B37: CMI-RLC-Nasional | C37: E1200351 | D37: DANAGRAHA_BUILDING1 / DANA GRAHA | E37: 45965 | F37: 001/TSA-SPH-CMI/XI/2025 | G37: Dismantle Tower | H37: PB-CME-271 Pengecatan | I37: 29 | J37: M² | K37: 64000 | L37: =+I37*K37 -> 1856000 | N37: 46365
B38: CMI-RLC-Nasional | C38: R5100062 | D38: SMPK_THOMAS_AQUINO | E38: 45939 | F38: 006/TSA-SPH-CMI/X/2025 | G38: Dismantle Tower | H38: Project Management fee | I38: 1 | J38: Ls | K38: 2700000 | L38: =+I38*K38 -> 2700000 | N38: 45999
B39: CMI-RLC-Nasional | C39: R5100062 | D39: SMPK_THOMAS_AQUINO | E39: 45939 | F39: 006/TSA-SPH-CMI/X/2025 | G39: Dismantle Tower | H39: Delivery material scrap | I39: 1193.68 | J39: Kg | K39: 1800 | L39: =+I39*K39 -> 2148624 | N39: 45999
B40: CMI-RLC-Nasional | C40: R5100062 | D40: SMPK_THOMAS_AQUINO | E40: 45939 | F40: 006/TSA-SPH-CMI/X/2025 | G40: Dismantle Tower | H40: Biaya Langsir roaster dari site ke WH TSA Surabaya | I40: 1 | J40: Ls | K40: 6000000 | L40: =+I40*K40 -> 6000000 | N40: 45999
B41: CMI-RLC-Nasional | C41: E6400049 | D41: WADUK MANGGAR | E41: 46002 | F41: 001/TSA-SPH-CMI/XII/2025 | G41: Dismantle Tower | H41: Ticket Pesawat Semarang to Balikpapan | I41: 5 | J41: orang | K41: 1800000 | L41: =+I41*K41 -> 9000000 | N41: 46028
... B54: CMI-RLC-Nasional | C54: R6300038 | D54: TRANS KALIMANTAN | E54: 46059 | F54: 002/TSA-SPH-CMI/II/2026 | G54: Relocation Equipment | H54: Cable Power RRU Awg 2x10 XLS | I54: 30 | J54: meter | K54: 35000 | L54: =+I54*K54 -> 1050000 | N54: 46135
B55: CMI-RLC-Nasional | C55: E1200343 | D55: TEMIANG_BATAM / BUKIT MATA KUCING 2 | E55: 46020 | F55: 009/TSA-SPH-CMI/XI/2025 | G55: Dismantle Tower | I55: 8236.656 | J55: Kg | K55: -1500 | L55: =+I55*K55 -> -12354984 | N55: 46049
B56: CMI-RLC-Nasional | C56: E1200343 | D56: TEMIANG_BATAM / BUKIT MATA KUCING 2 | E56: 46020 | F56: 009/TSA-SPH-CMI/XI/2025 | G56: Dismantle Tower | H56: Project Management fee | I56: 1 | J56: Ls | K56: 2700000 | L56: =+I56*K56 -> 2700000 | N56: 46049
B57: CMI-RLC-Nasional | C57: E1200343 | D57: TEMIANG_BATAM / BUKIT MATA KUCING 2 | E57: 46020 | F57: 009/TSA-SPH-CMI/XI/2025 | G57: Relocation Equipment | H57: Pembelian kabel twisted 2 x 16 (70m x 3tarikan) | I57: 210 | J57: M | K57: 45000 | L57: =+I57*K57 -> 9450000 | N57: 46049
B58: CMI-RLC-Nasional | C58: E1200343 | D58: TEMIANG_BATAM / BUKIT MATA KUCING 2 | E58: 46020 | F58: 009/TSA-SPH-CMI/XI/2025 | G58: Relocation Equipment | H58: Pembelian optic 100m x 3tarikan | I58: 300 | J58: M | K58: 10000 | L58: =+I58*K58 -> 3000000 | N58: 46049
B59: CMI-RLC-Nasional | C59: R3100450 | D59: KEBON SIRIH | E59: 46014 | F59: 004/TSA-SPH-CMI/XII/2025 | G59: Relocation Equipment | H59: Management Fee | I59: 1 | J59: Ls | K59: 2700000 | L59: =+I59*K59 -> 2700000 | N59: 46050
B60: CMI-RLC-Nasional | C60: R3100450 | D60: KEBON SIRIH | E60: 46014 | F60: 004/TSA-SPH-CMI/XII/2025 | G60: Relocation Equipment | H60: Jasa Kontraktor / AKLI | I60: 1 | J60: Ls | K60: 3300000 | L60: =+I60*K60 -> 3300000 | N60: 46050
B61: CMI-RLC-Nasional | C61: R3100450 | D61: KEBON SIRIH | E61: 46014 | F61: 004/TSA-SPH-CMI/XII/2025 | G61: Relocation Equipment | H61: Multiguna PLN 24-12-25 sd 20-01-26 | I61: 1 | J61: Ls | K61: 14947622 | L61: =+I61*K61 -> 14947622 | N61: 46050
B62: CMI-RLC-Nasional | C62: R3580411 | D62: PEGANTENAN | E62: 46020 | F62: 002/TSA-SPH-CMI/XII/2025 | G62: Dismantle Tower | H62: Sewa Alat Berat | I62: 7 | J62: hari | K62: 4600000 | L62: =+I62*K62 -> 32200000 | N62: 46118
B63: CMI-RLC-Nasional | C63: R3580411 | D63: PEGANTENAN | E63: 46020 | F63: 002/TSA-SPH-CMI/XII/2025 | G63: Dismantle Tower | H63: Buang puing pondasi | I63: 29 | J63: rit | K63: 250000 | L63: =+I63*K63 -> 7250000 | N63: 46118
B64: CMI-RLC-Nasional | C64: R3580411 | D64: PEGANTENAN | E64: 46020 | F64: 002/TSA-SPH-CMI/XII/2025 | G64: Dismantle Tower | H64: Import Soil | I64: 70.4 | J64: m3 | K64: 125000 | L64: =+I64*K64 -> 8800000 | N64: 46118
B65: CMI-RLC-Nasional | C65: R3580411 | D65: PEGANTENAN | E65: 46020 | F65: 002/TSA-SPH-CMI/XII/2025 | G65: Dismantle Tower | H65: Management Fee sewa alat berat & buang pondasi | I65: 1 | J65: Ls | K65: 3945000 | L65: =+I65*K65 -> 3945000 | N65: 46118
B66: CMI-RLC-Nasional | C66: E3600061 | D66: PARUNGSARI | E66: 46097 | F66: 007/TSA-SPH-CMI/I/2026 | G66: Relocation Equipment | H66: Kabel power twist 4x16mm | I66: 100 | J66: meter | K66: 22500 | L66: =+I66*K66 -> 2250000 | N66: 46118
B67: CMI-RLC-Nasional | C67: E3600061 | D67: PARUNGSARI | E67: 46097 | F67: 007/TSA-SPH-CMI/I/2026 | G67: Relocation Equipment | H67: Tiang FO 7m IOH | I67: 1 | J67: pcs | K67: 1500000 | L67: =+I67*K67 -> 1500000 | N67: 46118
... B76: CMI-RLC-Nasional | C76: E6400129 | D76: SUSUK | E76: 46034 | F76: 005/TSA-SPH-CMI/I/2026 | G76: Relocation Equipment | H76: Travel Samarinda to Site PP | I76: 5 | J76: orang | K76: 600000 | L76: =+I76*K76 -> 3000000 | N76: 46051
B77: CMI-RLC-Nasional | C77: R6400134 | D77: BATUAH KM.45 | E77: 46036 | F77: 006/TSA-SPH-CMI/I/2026 | G77: Relocation Equipment | H77: PB-PWR-18 Re instal Genset,Fuel tank,ATS (Inc wiring,Commisioning and Fungtional Test) | I77: 1 | J77: Ls | K77: 4000000 | L77: =+I77*K77 -> 4000000
B78: CMI-RLC-Nasional | C78: E3200525 | D78: GEDUNG_LIPPO | E78: 46058 | F78: 001/TSA-SPH-CMI/II/2026 | G78: Relocation Equipment | H78: Cable Optik CPRI SM 70m | I78: 1 | J78: tarikan | K78: 250000 | L78: =+I78*K78 -> 250000 | N78: 46118 | P78: Cancel
B79: CMI-RLC-Nasional | C79: E3200525 | D79: GEDUNG_LIPPO | E79: 46058 | F79: 001/TSA-SPH-CMI/II/2026 | G79: Relocation Equipment | H79: Cable Jumper DM-N4310 3m | I79: 2 | J79: pcs | K79: 350000 | L79: =+I79*K79 -> 700000 | N79: 46118 | P79: Cancel
B80: CMI-RLC-Nasional | C80: E3200525 | D80: GEDUNG_LIPPO | E80: 46058 | F80: 001/TSA-SPH-CMI/II/2026 | G80: Relocation Equipment | H80: P02-003-017 Supply and Install NYFGBY 4x16 mm2 include Accessories | I80: 7 | J80: meter | K80: 165000 | L80: =+I80*K80 -> 1155000 | N80: 46118 | P80: Cancel
B81: CMI-RLC-Nasional | C81: E3200525 | D81: GEDUNG_LIPPO | E81: 46058 | F81: 001/TSA-SPH-CMI/II/2026 | G81: Relocation Equipment | H81: Cable Power RRU Awg 2x10 | I81: 60 | J81: meter | K81: 35000 | L81: =+I81*K81 -> 2100000 | N81: 46118 | P81: Cancel
B82: CMI-RLC-Nasional | C82: R5100118 | D82: PENYARINGAN RELOC | E82: 46062 | F82: 003/TSA-SPH-CMI/II/2026 | G82: Relocation Equipment | H82: Cable coax MW IOH | I82: 40 | J82: meter | K82: 20000 | L82: =+I82*K82 -> 800000 | N82: 46118 | O82: 011-DR-BAN/0426
B83: CMI-RLC-Nasional | C83: R5100118 | D83: PENYARINGAN RELOC | E83: 46062 | F83: 003/TSA-SPH-CMI/II/2026 | G83: Relocation Equipment | H83: Cable Power RRU IOH 15 meter x 6 tarikan | I83: 90 | J83: meter | K83: 35000 | L83: =+I83*K83 -> 3150000 | N83: 46118 | O83: 011-DR-BAN/0426
B84: CMI-RLC-Nasional | C84: R5100118 | D84: PENYARINGAN RELOC | E84: 46062 | F84: 003/TSA-SPH-CMI/II/2026 | G84: Relocation Equipment | H84: Cable Power RRU XL 20 meter x 6 tarikan | I84: 120 | J84: meter | K84: 35000 | L84: =+I84*K84 -> 4200000 | N84: 46118 | O84: 011-DR-BAN/0426
B85: CMI-RLC-Nasional | C85: R5100118 | D85: PENYARINGAN RELOC | E85: 46062 | F85: 003/TSA-SPH-CMI/II/2026 | G85: Relocation Equipment | H85: Cable Power RRU Tsel 10 meter x 7 tarikan | I85: 70 | J85: meter | K85: 35000 | L85: =+I85*K85 -> 2450000 | N85: 46118 | O85: 011-DR-BAN/0426
B86: CMI-RLC-Nasional | C86: R7300203 | D86: KIMA 2 | E86: 46065 | F86: 004/TSA-SPH-CMI/II/2026 | G86: Relocation Equipment | H86: Cable Power RRU IOH 4 Meter x 4 Tarikan | I86: 16 | J86: meter | K86: 35000 | L86: =+I86*K86 -> 560000 | N86: 46135
B87: CMI-RLC-Nasional | C87: R1200302 | D87: BANGUN PURBA | E87: 46080 | F87: 005/TSA-SPH-CMI/II/2026 | G87: Relocation Equipment | H87: PB-PWR-18 Reinstall Genset, Fuel Tank, ATS (Inc. Wiring, Commisioning and Fungtional Test) | I87: 1 | J87: set | K87: 4000000 | L87: =+I87*K87 -> 4000000 | N87: 46147
B88: CMI-RLC-Nasional | C88: R1200302 | D88: BANGUN PURBA | E88: 46080 | F88: 005/TSA-SPH-CMI/II/2026 | G88: Relocation Equipment | H88: Pembelian Rak Outdoor + Delivery | I88: 1 | J88: set | K88: 7000000 | L88: =+I88*K88 -> 7000000 | N88: 46147
B89: CMI-RLC-Nasional | C89: R35780005 | D89: WONOKESUMO | E89: 46093 | F89: 001/TSA-SPH-CMI/IV/2026 | G89: Relocation Equipment | H89: Pulling cable FO | I89: 200 | J89: meter | K89: 5000 | L89: =+I89*K89 -> 1000000 | N89: 46135
B90: CMI-RLC-Nasional | C90: R35780005 | D90: WONOKESUMO | E90: 46093 | F90: 001/TSA-SPH-CMI/IV/2026 | G90: Relocation Equipment | H90: Bongkar pasang OTB | I90: 1 | J90: pcs | K90: 350000 | L90: =+I90*K90 -> 350000 | N90: 46135
B91: CMI-RLC-Nasional | C91: R35780005 | D91: WONOKESUMO | E91: 46093 | F91: 001/TSA-SPH-CMI/IV/2026 | G91: Relocation Equipment | H91: Joint core | I91: 144 | J91: core | K91: 40000 | L91: =+I91*K91 -> 5760000 | N91: 46135 | O91: 017-DR-BAN 0426
B92: CMI-RLC-Nasional | C92: E3100287 | D92: KAMPUNG_SAWAH | E92: 46119 | F92: 002/TSA-SPH-CMI/IV/2026 | G92: Relocation Equipment | H92: Kabel Power Twisted | I92: 50 | J92: meter | K92: 14000 | L92: =+I92*K92 -> 700000
B93: CMI-RLC-Nasional | C93: E3100287 | D93: KAMPUNG_SAWAH | E93: 46119 | F93: 002/TSA-SPH-CMI/IV/2026 | G93: Relocation Equipment | H93: PB-PWR-18 Reinstall Genset, Fuel Tank, ATS (Inc. Wiring, Commisioning and Fungtional Test) | I93: 1 | J93: set | K93: 4000000 | L93: =+I93*K93 -> 4000000
B94: CMI-RLC-Nasional | C94: E3100287 | D94: KAMPUNG_SAWAH | E94: 46119 | F94: 002/TSA-SPH-CMI/IV/2026 | G94: Relocation Equipment | H94: E02-005-002 Galian tanah pondasi | I94: 1.56 | J94: m3 | K94: 43698 | L94: =+I94*K94 -> 68168.88
B95: CMI-RLC-Nasional | C95: E3100287 | D95: KAMPUNG_SAWAH | E95: 46119 | F95: 002/TSA-SPH-CMI/IV/2026 | G95: Relocation Equipment | H95: E02-005-003 Urugan kembali tanah pondasi | I95: 0.55 | J95: m3 | K95: 34656 | L95: =+I95*K95 -> 19060.8
B96: CMI-RLC-Nasional | C96: E3100287 | D96: KAMPUNG_SAWAH | E96: 46119 | F96: 002/TSA-SPH-CMI/IV/2026 | G96: Relocation Equipment | H96: E02-005-007-1 Volume beton K-225 tanpa tulangan | I96: 0.53 | J96: m3 | K96: 2084061 | L96: =+I96*K96 -> 1104552.3
B97: CMI-RLC-Nasional | C97: E3100287 | D97: KAMPUNG_SAWAH | E97: 46119 | F97: 002/TSA-SPH-CMI/IV/2026 | G97: Relocation Equipment | H97: E02-005-008 Pondasi batu kali incl tangga | I97: 3.27 | J97: m3 | K97: 483357 | L97: =+I97*K97 -> 1580577.4
B98: CMI-RLC-Nasional | C98: E3100287 | D98: KAMPUNG_SAWAH | E98: 46119 | F98: 002/TSA-SPH-CMI/IV/2026 | G98: Relocation Equipment | H98: E02-005-012 Sand layer | I98: 0.2 | J98: m3 | K98: 270160 | L98: =+I98*K98 -> 54032
B99: CMI-RLC-Nasional | C99: E3200269 | D99: CILEUNGSIKIDUL | E99: 46127 | F99: 003/TSA-SPH-CMI/IV/2026 | G99: Relocation Equipment | H99: Pulling cable FO IOH & SF | I99: 90 | J99: meter | K99: 5000 | L99: =+I99*K99 -> 450000 | M99: 46142 | N99: 46147 | O99: 020-DR-BAN 0526
B100: CMI-RLC-Nasional | C100: E3200269 | D100: CILEUNGSIKIDUL | E100: 46127 | F100: 003/TSA-SPH-CMI/IV/2026 | G100: Relocation Equipment | H100: Bongkar pasang OTB IOH & SF | I100: 2 | J100: pcs | K100: 350000 | L100: =+I100*K100 -> 700000 | M100: 46142 | N100: 46147 | O100: 020-DR-BAN 0526
B101: CMI-RLC-Nasional | C101: E3200269 | D101: CILEUNGSIKIDUL | E101: 46127 | F101: 003/TSA-SPH-CMI/IV/2026 | G101: Relocation Equipment | H101: Joint core IOH & SF | I101: 120 | J101: core | K101: 40000 | L101: =+I101*K101 -> 4800000 | M101: 46142 | N101: 46147 | O101: 020-DR-BAN 0526
B102: CMI-RLC-Nasional | C102: E6400127 | D102: N_KALIORANG | E102: 46121 | F102: 005/TSA-SPH-CMI/IV/2026 | G102: Relocation Equipment | H102: Delivery Cabinet from Balikpapan to site | I102: 1 | J102: Ls | K102: 2000000 | L102: =+I102*K102 -> 2000000 | N102: 46147 | O102: 022-DR-BAN 0526
B103: CMI-RLC-Nasional | C103: E6400127 | D103: N_KALIORANG | E103: 46121 | F103: 005/TSA-SPH-CMI/IV/2026 | G103: Relocation Equipment | H103: Kabel NYY 4x16 ACPDB to Recty | I103: 5 | J103: meter | K103: 130000 | L103: =+I103*K103 -> 650000 | N103: 46147 | O103: 022-DR-BAN 0526
B104: CMI-RLC-Nasional | C104: E6400127 | D104: N_KALIORANG | E104: 46121 | F104: 005/TSA-SPH-CMI/IV/2026 | G104: Relocation Equipment | H104: Pengadaan rack enclosure | I104: 1 | J104: pcs | K104: 3000000 | L104: =+I104*K104 -> 3000000 | N104: 46147 | O104: 022-DR-BAN 0526
B105: CMI-RLC-Nasional | C105: E6400127 | D105: N_KALIORANG | E105: 46121 | F105: 005/TSA-SPH-CMI/IV/2026 | G105: Relocation Equipment | H105: Akomodasi Team 2 orang | I105: 3 | J105: hari | K105: 400000 | L105: =+I105*K105 -> 1200000 | N105: 46147 | O105: 022-DR-BAN 0526
B106: CMI-RLC-Nasional | C106: R35780005 | D106: WONOKESUMO | E106: 46122 | F106: 006/TSA-SPH-CMI/IV/2026 | G106: Relocation Equipment | H106: Cable Power RRU Telkomsel Awg 2x10 (32m x 9tarikan) | I106: 288 | J106: meter | K106: 35000 | L106: =+I106*K106 -> 10080000 | M106: 46176 | N106: 46230 | O106: 034-DR-BAN 0726
B107: CMI-RLC-Nasional | C107: R5100118 | D107: PENYARINGAN RELOC | E107: 46128 | F107: 007/TSA-SPH-CMI/IV/2026 | G107: Relocation Equipment | H107: Tagihan Listrik April 2026 | I107: 1 | J107: bulan | K107: 1508284 | L107: =+I107*K107 -> 1508284 | N107: 46147 | O107: 024/DR-BAN/0526
B108: CMI-RLC-Nasional | C108: R5100118 | D108: PENYARINGAN RELOC | E108: 46128 | F108: 007/TSA-SPH-CMI/IV/2026 | G108: Relocation Equipment | H108: BPUJL | I108: 1 | J108: unit | K108: 4542700 | L108: =+I108*K108 -> 4542700 | N108: 46147 | O108: 024/DR-BAN/0526
B109: CMI-RLC-Nasional | C109: R5100118 | D109: PENYARINGAN RELOC | E109: 46128 | F109: 007/TSA-SPH-CMI/IV/2026 | G109: Relocation Equipment | H109: NIDI + SLO | I109: 1 | J109: unit | K109: 1500000 | L109: =+I109*K109 -> 1500000 | N109: 46147 | O109: 024/DR-BAN/0526
B110: CMI-RLC-Nasional | C110: R5100118 | D110: PENYARINGAN RELOC | E110: 46128 | F110: 007/TSA-SPH-CMI/IV/2026 | G110: Relocation Equipment | H110: Jasa AKLI | I110: 1 | J110: unit | K110: 3300000 | L110: =+I110*K110 -> 3300000 | N110: 46147 | O110: 024/DR-BAN/0526
B111: CMI-RLC-Nasional | C111: E5300006 | D111: V_LEMBOR | E111: 46128 | F111: 008/TSA-SPH-CMI/IV/2026 | G111: Dismantle Tower | H111: Ticket Surabaya - Labuan Bajo | I111: 5 | J111: orang | K111: 2240140 | L111: =+I111*K111 -> 11200700 | M111: 46142 | N111: 46147 | O111: 019/DR-BAN/0526
B112: CMI-RLC-Nasional | C112: E5300006 | D112: V_LEMBOR | E112: 46128 | F112: 008/TSA-SPH-CMI/IV/2026 | G112: Dismantle Tower | H112: Ticket Labuan Bajo - Surabaya | I112: 5 | J112: unit | K112: 2150414 | L112: =+I112*K112 -> 10752070 | M112: 46142 | N112: 46147 | O112: 019/DR-BAN/0526
B113: CMI-RLC-Nasional | C113: R7200006 | D113: NALU | E113: 46133 | F113: 009/TSA-SPH-CMI/IV/2026 | G113: Dismantle Tower | H113: Ticket Pesawat Team Makassar - Palu | I113: 6 | J113: orang | K113: 1590044 | L113: =+I113*K113 -> 9540264 | M113: 46176 | P113: Pending
B114: CMI-RLC-Nasional | C114: R7200006 | D114: NALU | E114: 46133 | F114: 009/TSA-SPH-CMI/IV/2026 | G114: Dismantle Tower | H114: Ticket Pesawat Team Palu - Makassar | I114: 6 | J114: orang | K114: 1383200 | L114: =+I114*K114 -> 8299200 | M114: 46176
B115: CMI-RLC-Nasional | C115: E3100485 | D115: PEDONGKELAN | E115: 46140 | F115: 010/TSA-SPH-CMI/IV/2026 | G115: Relocation Equipment | H115: Cable Power RRU Awg 2x10 untuk Telkomsel | I115: 30 | J115: meter | K115: 35000 | L115: =+I115*K115 -> 1050000 | N115: 46147 | O115: 023/DR-BAN/0526
B116: CMI-RLC-Nasional | C116: E7100037 | D116: ROAD TO TAMAKO | E116: 46146 | F116: 001/TSA-SPH-CMI/V/2026 | G116: Dismantle Tower | H116: Ticket Makassar - Manado | I116: 6 | J116: orang | K116: 1667400 | L116: =+I116*K116 -> 10004400 | M116: 46176 | P116: cancel karena team langsung ke V_Tahuna
B117: CMI-RLC-Nasional | C117: E7100037 | D117: ROAD TO TAMAKO | E117: 46146 | F117: 001/TSA-SPH-CMI/V/2026 | G117: Dismantle Tower | H117: Ticket Manado - Makassar | I117: 6 | J117: orang | K117: 1667400 | L117: =+I117*K117 -> 10004400 | M117: 46176 | P117: cancel karena team langsung ke V_Tahuna
B118: CMI-RLC-Nasional | C118: R1200302 | D118: BANGUN PURBA | E118: 46163 | F118: 002/TSA-SPH-CMI/V/2026 | G118: Relocation Equipment | H118: Delivery Cabinet recty | I118: 1 | J118: set | K118: 9500000 | L118: =+I118*K118 -> 9500000 | M118: 46176
B119: CMI-RLC-Nasional | C119: R1200302 | D119: BANGUN PURBA | E119: 46163 | F119: 002/TSA-SPH-CMI/V/2026 | G119: Relocation Equipment | H119: Additional Team Reloc untuk 3 hari | I119: 4 | J119: orang | K119: 1000000 | L119: =+I119*K119 -> 4000000 | M119: 46176
B120: CMI-RLC-Nasional | C120: E9400005 | D120: TVRI BIAK | E120: 46150 | F120: 003/TSA-SPH-CMI/V/2026 | G120: Dismantle Tower | H120: Scrap Material onsite | I120: 22270.78 | J120: kg | K120: -1500 | L120: =+I120*K120 -> -33406170 | M120: 46157 | N120: 46183 | O120: 028/DR-BAN/0626
B121: CMI-RLC-Nasional | C121: E7400036 | D121: V_WANCI | E121: 46154 | F121: 004/TSA-SPH-CMI/V/2026 | G121: Dismantle Tower | H121: Scrap Material onsite | I121: 18868.812 | J121: kg | K121: -1500 | L121: =+I121*K121 -> -28303218 | M121: 46157 | N121: 46183 | O121: 027/DR-BAN/0626
B122: CMI-RLC-Nasional | C122: E7100037 | D122: ROAD TO TAMAKO | E122: 46154 | F122: 005/TSA-SPH-CMI/V/2026 | G122: Dismantle Tower | H122: Scrap Material onsite | I122: 57349.8 | J122: kg | K122: -1200 | L122: =+I122*K122 -> -68819760 | M122: 46157 | N122: 46183 | O122: 026/DR-BAN/0626
B123: CMI-RLC-Nasional | C123: E1200119 | D123: TELADAN | E123: 46155 | F123: 006/TSA-SPH-CMI/V/2026 | G123: Dismantle Tower | H123: Sewa Crane | I123: 1 | J123: hari | K123: 5000000 | L123: =+I123*K123 -> 5000000 | M123: 46176
B124: CMI-RLC-Nasional | C124: E7100038 | D124: V_TAHUNA | E124: 46154 | F124: 007/TSA-SPH-CMI/V/2026 | G124: Dismantle Tower | H124: Scrap Material onsite | I124: 18868.812 | J124: kg | K124: 1200 | L124: =+I124*K124 -> 22642574
B125: CMI-RLC-Nasional | C125: E1200337 | D125: BUKIT_BALADA | E125: 46163 | F125: 008/TSA-SPH-CMI/V/2026 | G125: Dismantle Tower | H125: Scrap Material onsite | I125: 16910.318 | J125: kg | K125: 1500 | L125: =+I125*K125 -> 25365477
B126: CMI-RLC-Nasional | C126: E1200424 | D126: DAPUR_DUA_BELAS / DAPUR 12 | E126: 46170 | F126: 009/TSA-SPH-CMI/V/2026 | G126: Dismantle Tower | H126: Scrap Material onsite (Tower + Mounting RF & MW) | I126: 13517.71 | J126: kg | K126: 1500 | L126: =+I126*K126 -> 20276565
B127: CMI-RLC-Nasional | C127: R5100118 | D127: PENYARINGAN RELOC | E127: 46193 | G127: Relocation Equipment | H127: Tagihan Listrik Juni 2026 551400883538 | I127: 1 | J127: bulan | K127: 1660915 | L127: =+I127*K127 -> 1660915 | P127: akan dimasukkan ke site lain
B128: CMI-RLC-Nasional | C128: R5100055 | D128: T_COW TEUKU UMAR | E128: 46196 | F128: 002/TSA-SPH-CMI/VI/2026 | G128: Dismantle Tower | H128: Sewa Crane + Mobilisasi | I128: 1 | J128: Ls | K128: 7000000 | L128: =+I128*K128 -> 7000000
...

Sheet oret2
D3: Site ID | E3: Site Name | F3: Tower Provider | G3: LATITUDE | H3: LONGITUDE | I3: Height proposed | J3: Azimuth
C4: Near End (Site Acceptor) | D4: JAW-JB-KNG-1359 | E4: JAPARA KUNINGAN | F4: EMA | G4: -6.89649 | H4: 108.51681 | I4: 44
C5: Far End | D5: JAW-JB-KNG-1353 | E5: KUNINGAN BANGUN | F5: DMT | G5: -6.88686 | H5: 108.502806 | I5: existing
D7: E3200649 | E7: JAPARA

Sheet Update Boram
A1: Update BORAM
R2: ID Pelanggan PLN | S2: Nama Pelanggan PLN | T2: Nama Site | U2: Alamat | V2: Keterangan
A3: No | B3: Site ID CMI | C3: Site Name CMI | D3: Tenant | E3: Site ID Tenant | F3: Site Name Tenant | G3: ID Pel | H3: Daya (VA) | I3: SPBR Submit CMI | J3: SPBR Release | K3: SPBR Submit PLN | L3: BA Boram | M3: Progress | N3: Remark | O3: BOT PLN | R3: 152001107489 | S3: PT. INDOSAT | T3: PINTU4_MUKA_KUNING_EP | U3: JL. TANJUNG RAYA , MUKA KUNING
A4: 1 | B4: R35780005 | C4: WONOKESUMO | D4: IOH | E4: 16SBY0363 | F4: WONOSARILOR_CM | G4: 511040607208 | H4: 10600 | I4: 46125 | L4: 45596 | M4: =+IF(L4<>"","Done Boram",IF(K4<>"","SPBR submit to PLN",IF(J4<>"","SPBR Release",IF(I4<>"","Submit App SPBR","")))) -> Done Boram | N4: IOH tidak mengeluarkan SPBR karena id pel tersebut sudah boram
A5: 2 | B5: R35780005 | C5: WONOKESUMO | D5: TSEL | E5: SBY098 | F5: PEGIRIANCMI | G5: 511040502273 | H5: 10600 | K5: 46125 | L5: 46136 | M5: =+IF(L5<>"","Done Boram",IF(K5<>"","SPBR submit to PLN",IF(J5<>"","SPBR Release",IF(I5<>"","Submit App SPBR","")))) -> Done Boram | N5: SPBR edit sendiri
A6: 3 | B6: E3300061 | C6: RSMARGONO | D6: IOH | E6: 14PWT0167 | F6: RSMARGONO_EP | G6: 522011266252 | I6: 45721 | J6: 45804 | K6: 45805 | L6: 45957 | M6: =+IF(L6<>"","Done Boram",IF(K6<>"","SPBR submit to PLN",IF(J6<>"","SPBR Release",IF(I6<>"","Submit App SPBR","")))) -> Done Boram
A7: 4 | B7: E6400044 | C7: MARKONI | D7: IOH | E7: 22BPP0085 | F7: MARKONI_EP | G7: 232000283760 | I7: 45888 | J7: 45894 | K7: 45895 | L7: 45922 | M7: =+IF(L7<>"","Done Boram",IF(K7<>"","SPBR submit to PLN",IF(J7<>"","SPBR Release",IF(I7<>"","Submit App SPBR","")))) -> Done Boram
A8: 5 | B8: R3350400 | C8: SUMBER LAWANG | D8: XLS | E8: JAW-JT-SGN-1855 | F8: SUMBER LAWANG | G8: 520591331135 | I8: 45844 | J8: 45845 | K8: 45846 | L8: 45858 | M8: =+IF(L8<>"","Done Boram",IF(K8<>"","SPBR submit to PLN",IF(J8<>"","SPBR Release",IF(I8<>"","Submit App SPBR","")))) -> Done Boram
A9: 6 | B9: E8200008 | C9: JAILOLO | D9: IOH | E9: 32HBR0001 | F9: JAILOLO_EP | G9: 412500929541 | I9: 46014 | J9: 46029 | K9: 46029 | L9: 46072 | M9: =+IF(L9<>"","Done Boram",IF(K9<>"","SPBR submit to PLN",IF(J9<>"","SPBR Release",IF(I9<>"","Submit App SPBR","")))) -> Done Boram
A10: 7 | B10: R5100120 | C10: PANTAI PANDAWA | D10: IOH | E10: 17DPR0188 | F10: PANTAIPANDAWA_CM | G10: 551201457578 | I10: 45802 | J10: 45803 | K10: 45804 | L10: 45826 | M10: =+IF(L10<>"","Done Boram",IF(K10<>"","SPBR submit to PLN",IF(J10<>"","SPBR Release",IF(I10<>"","Submit App SPBR","")))) -> Done Boram
A11: 8 | B11: R3580411 | C11: PEGANTENAN | D11: XLS | E11: JAW-JI-PMK-2000 | F11: PEGANTENAN PAMEKASAN | G11: 517800793803 | I11: 46002 | J11: 46008 | K11: 46008 | L11: 46013 | M11: =+IF(L11<>"","Done Boram",IF(K11<>"","SPBR submit to PLN",IF(J11<>"","SPBR Release",IF(I11<>"","Submit App SPBR","")))) -> Done Boram
A12: 9 | B12: E3500148 | C12: KEDUNGPRING | D12: IOH | E12: 16LMG0033 | F12: KEDUNGPRING_EP | G12: 518041036694 | I12: 45922 | J12: 45922 | K12: 45923 | L12: 45948 | M12: =+IF(L12<>"","Done Boram",IF(K12<>"","SPBR submit to PLN",IF(J12<>"","SPBR Release",IF(I12<>"","Submit App SPBR","")))) -> Done Boram
A13: 10 | B13: E3500148 | C13: KEDUNGPRING | D13: XLS | E13: JAW-JI-LMG-4290 | F13: KEDUNGPRING TLANAK | G13: 518041755248 | I13: 45921 | J13: 45922 | K13: 45923 | L13: 45940 | M13: =+IF(L13<>"","Done Boram",IF(K13<>"","SPBR submit to PLN",IF(J13<>"","SPBR Release",IF(I13<>"","Submit App SPBR","")))) -> Done Boram
A14: 11 | B14: R6300019 | C14: JL. KELAPA BJM | D14: XLS | E14: KAL-KS-BJM-0197 | F14: JL. KELAPA BJM | G14: 221103103075 | I14: 46153 | J14: 46153 | K14: 46153 | L14: 46164 | M14: =+IF(L14<>"","Done Boram",IF(K14<>"","SPBR submit to PLN",IF(J14<>"","SPBR Release",IF(I14<>"","Submit App SPBR","")))) -> Done Boram | N14: 19.05.26 Boram done
A15: 12 | B15: R6300019 | C15: JL. KELAPA BJM | D15: TSEL | E15: BJM179 | F15: JL. KELAPA BJM | G15: 221103114978 | H15: 10600 | I15: 46153 | J15: 46175 | K15: 46175 | L15: 46206 | M15: =+IF(L15<>"","Done Boram",IF(K15<>"","SPBR submit to PLN",IF(J15<>"","SPBR Release",IF(I15<>"","Submit App SPBR","")))) -> Done Boram
A16: 13 | B16: E5100119 | C16: NUSALEMBONGAN | D16: IOH | E16: 17SPR0033 | F16: NUSALEMBONGAN_EP | G16: 551320015922 | I16: 45929 | J16: 45931 | K16: 45935 | L16: 45940 | M16: =+IF(L16<>"","Done Boram",IF(K16<>"","SPBR submit to PLN",IF(J16<>"","SPBR Release",IF(I16<>"","Submit App SPBR","")))) -> Done Boram
A17: 14 | B17: R3350113 | C17: PLIKEN | D17: IOH | E17: 14PWT0194 | F17: PLIKEN_CM | G17: 522020867980 | M17: =+IF(L17<>"","Done Boram",IF(K17<>"","SPBR submit to PLN",IF(J17<>"","SPBR Release",IF(I17<>"","Submit App SPBR",""))))
A18: 15 | B18: R3350113 | C18: PLIKEN | D18: TSEL | G18: 522020914363 | H18: 7700 | M18: =+IF(L18<>"","Done Boram",IF(K18<>"","SPBR submit to PLN",IF(J18<>"","SPBR Release",IF(I18<>"","Submit App SPBR",""))))
A19: 16 | B19: E1200347 | C19: JODOH | D19: IOH | E19: 05BTM0110 | F19: JODOH_EP | G19: 151001044556 | I19: 45936 | J19: 45930 | K19: 45931 | L19: 45957 | M19: =+IF(L19<>"","Done Boram",IF(K19<>"","SPBR submit to PLN",IF(J19<>"","SPBR Release",IF(I19<>"","Submit App SPBR","")))) -> Done Boram
A20: 17 | B20: R6300038 | C20: TRANS KALIMANTAN | D20: IOH | E20: 23MRB0023 | F20: TRANSKALIMANTAN_CM | G20: 221500493526 | H20: 5500 | I20: 46030 | J20: 46030 | K20: 46041 | L20: 46042 | M20: =+IF(L20<>"","Done Boram",IF(K20<>"","SPBR submit to PLN",IF(J20<>"","SPBR Release",IF(I20<>"","Submit App SPBR","")))) -> Done Boram
A21: 18 | B21: R6300038 | C21: TRANS KALIMANTAN | D21: XLS | E21: KAL-KS-MRH-0386 | F21: TRANS KALIMANTAN | G21: 221500137257 | H21: 13200 | I21: 46030 | J21: 46030 | K21: 46041 | L21: 46042 | M21: =+IF(L21<>"","Done Boram",IF(K21<>"","SPBR submit to PLN",IF(J21<>"","SPBR Release",IF(I21<>"","Submit App SPBR","")))) -> Done Boram
A22: 19 | B22: E1200343 | C22: TEMIANG_BATAM / BUKIT MATA KUCING 2 | D22: IOH | E22: 05BTM0074 | F22: TEMIANG_BATAM_EP | G22: 152001110528 | H22: 13200 | I22: 45996 | J22: 46001 | K22: 46001 | L22: 46010 | M22: =+IF(L22<>"","Done Boram",IF(K22<>"","SPBR submit to PLN",IF(J22<>"","SPBR Release",IF(I22<>"","Submit App SPBR","")))) -> Done Boram
A23: 20 | B23: E1200343 | C23: TEMIANG_BATAM / BUKIT MATA KUCING 2 | D23: XLS | E23: SUM-KR-BTM-0604 | F23: BULIANG | G23: 152002075724 | H23: 6600 | I23: 45996 | J23: 46001 | K23: 46001 | L23: 46010 | M23: =+IF(L23<>"","Done Boram",IF(K23<>"","SPBR submit to PLN",IF(J23<>"","SPBR Release",IF(I23<>"","Submit App SPBR","")))) -> Done Boram
A24: 21 | B24: E1200343 | C24: TEMIANG_BATAM / BUKIT MATA KUCING 2 | D24: TSEL | E24: BTM147 | F24: TEMIANG_BATAM BUKIT MATA KUCING 2 | G24: 152001757921 | H24: 10600 | I24: 45996 | J24: 46006 | K24: 46006 | L24: 46010 | M24: =+IF(L24<>"","Done Boram",IF(K24<>"","SPBR submit to PLN",IF(J24<>"","SPBR Release",IF(I24<>"","Submit App SPBR","")))) -> Done Boram
A25: 22 | B25: E3600061 | C25: PARUNGSARI | D25: IOH | E25: 11RKB0143 | F25: PARUNGSARI_RKB1_EP | G25: 539211120671 | I25: 45871 | J25: 45877 | K25: 45878 | L25: 45926 | M25: =+IF(L25<>"","Done Boram",IF(K25<>"","SPBR submit to PLN",IF(J25<>"","SPBR Release",IF(I25<>"","Submit App SPBR","")))) -> Done Boram
A26: 23 | B26: E3600061 | C26: PARUNGSARI | D26: XLS | E26: NJKT_1717 | F26: PARUNGSARI | G26: 562100172529 | I26: 45935 | J26: 45936 | K26: 45937 | L26: 45941 | M26: =+IF(L26<>"","Done Boram",IF(K26<>"","SPBR submit to PLN",IF(J26<>"","SPBR Release",IF(I26<>"","Submit App SPBR","")))) -> Done Boram
A27: 24 | B27: E3600061 | C27: PARUNGSARI | D27: TSEL | G27: 562101444860 | I27: 45904 | J27: 45974 | K27: 45974 | L27: 45982 | M27: =+IF(L27<>"","Done Boram",IF(K27<>"","SPBR submit to PLN",IF(J27<>"","SPBR Release",IF(I27<>"","Submit App SPBR","")))) -> Done Boram
A28: 25 | B28: E3200644 | C28: JALAKSANA | D28: IOH | E28: 13KNG0046 | F28: JALAKSANA_EP | G28: 533710563089 | I28: 45975 | J28: 45989 | K28: 45989 | L28: No Boram | M28: =+IF(L28<>"","Done Boram",IF(K28<>"","SPBR submit to PLN",IF(J28<>"","SPBR Release",IF(I28<>"","Submit App SPBR","")))) -> Done Boram
A29: 26 | B29: E3200269 | C29: CILEUNGSIKIDUL | D29: IOH | E29: 13CBN1024 | F29: CIELUNGSIKIDUL_EP | G29: 538654954208 | H29: 23000 | I29: 46120 | J29: 46128 | K29: 46129 | L29: 46133 | M29: =+IF(L29<>"","Done Boram",IF(K29<>"","SPBR submit to PLN",IF(J29<>"","SPBR Release",IF(I29<>"","Submit App SPBR","")))) -> Done Boram
A30: 27 | B30: E3200644 | C30: JALAKSANA | D30: XLS | E30: ZCRB_4188 | F30: JALAKSANA | G30: 533711051862 | I30: 45975 | J30: 45988 | K30: 45988 | L30: 46000 | M30: =+IF(L30<>"","Done Boram",IF(K30<>"","SPBR submit to PLN",IF(J30<>"","SPBR Release",IF(I30<>"","Submit App SPBR","")))) -> Done Boram
A31: 28 | B31: E3200269 | C31: CILEUNGSIKIDUL | D31: XLS | E31: NBGR_0125 | F31: CILEUNGSIKIDUL | G31: 538655662867 | H31: 10600 | I31: 46120 | J31: 46127 | K31: 46127 | L31: 46133 | M31: =+IF(L31<>"","Done Boram",IF(K31<>"","SPBR submit to PLN",IF(J31<>"","SPBR Release",IF(I31<>"","Submit App SPBR","")))) -> Done Boram
A32: 29 | B32: E3500300 | C32: DUKUH_KUPANG | D32: IOH | E32: 16SBY0152 | F32: DUKUH_KUPANG_EP | G32: 511413067240 | I32: 45869 | J32: 45869 | K32: 45870 | L32: 45883 | M32: =+IF(L32<>"","Done Boram",IF(K32<>"","SPBR submit to PLN",IF(J32<>"","SPBR Release",IF(I32<>"","Submit App SPBR","")))) -> Done Boram
A33: 30 | B33: E3500300 | C33: DUKUH_KUPANG | D33: XLS | E33: JAW-JI-SBY-2359 | F33: PUTAT GEDE | G33: 511413182597 | I33: 45869 | J33: 45870 | K33: 45871 | L33: 45878 | M33: =+IF(L33<>"","Done Boram",IF(K33<>"","SPBR submit to PLN",IF(J33<>"","SPBR Release",IF(I33<>"","Submit App SPBR","")))) -> Done Boram
A34: 31 | B34: E3300323 | C34: WIROSARI | D34: IOH | E34: 14GRO0118 | F34: WIROSARI_EP | G34: 523073092633 | I34: 45881 | M34: =+IF(L34<>"","Done Boram",IF(K34<>"","SPBR submit to PLN",IF(J34<>"","SPBR Release",IF(I34<>"","Submit App SPBR","")))) -> Submit App SPBR
A35: 32 | B35: E3200297 | C35: CILOTO | D35: IOH | E35: 13CJR0017 | F35: CILOTO_EP | G35: 536712081435 | M35: =+IF(L35<>"","Done Boram",IF(K35<>"","SPBR submit to PLN",IF(J35<>"","SPBR Release",IF(I35<>"","Submit App SPBR",""))))
A36: 33 | B36: E3600042 | C36: TOL_CILEGON_SERANG | D36: IOH | E36: 11CLG0103 | F36: TOL_CLGN_SRANG_EP | G36: 539411151940 | I36: 45915 | J36: 45915 | K36: 45947 | L36: 45957 | M36: =+IF(L36<>"","Done Boram",IF(K36<>"","SPBR submit to PLN",IF(J36<>"","SPBR Release",IF(I36<>"","Submit App SPBR","")))) -> Done Boram
A37: 34 | B37: E3600042 | C37: TOL_CILEGON_SERANG | D37: XLS | E37: JAW-BT-SRG-1198 | F37: BOJONEGARA_SERDANG | G37: 561200596663 | I37: 45931 | J37: 45932 | K37: 45933 | L37: 45957 | M37: =+IF(L37<>"","Done Boram",IF(K37<>"","SPBR submit to PLN",IF(J37<>"","SPBR Release",IF(I37<>"","Submit App SPBR","")))) -> Done Boram
A38: 35 | B38: E3600042 | C38: TOL_CILEGON_SERANG | D38: TSEL | G38: 539411611457 | I38: 45908 | J38: 45974 | K38: 45974 | L38: 45985 | M38: =+IF(L38<>"","Done Boram",IF(K38<>"","SPBR submit to PLN",IF(J38<>"","SPBR Release",IF(I38<>"","Submit App SPBR","")))) -> Done Boram
A39: 36 | B39: E3100485 | C39: PEDONGKELAN | D39: IOH | E39: 12JKU0476 | F39: PEDONGKELAN_EP | G39: 545200594263 | I39: 46132 | J39: 46146 | M39: =+IF(L39<>"","Done Boram",IF(K39<>"","SPBR submit to PLN",IF(J39<>"","SPBR Release",IF(I39<>"","Submit App SPBR","")))) -> SPBR Release | N39: waiting penyambungan inbuilding di new site
A40: 37 | B40: E3100485 | C40: PEDONGKELAN | D40: TSEL | E40: JUX617 | F40: MEDAN MARUNDA | G40: 545303131129 | I40: 46132 | J40: 46146 | M40: =+IF(L40<>"","Done Boram",IF(K40<>"","SPBR submit to PLN",IF(J40<>"","SPBR Release",IF(I40<>"","Submit App SPBR","")))) -> SPBR Release | N40: waiting penyambungan inbuilding di new site
A41: 38 | B41: R5100062 | C41: SMPK_THOMAS_AQUINO | D41: XLS | E41: BAL-BA-MGW-0604 | F41: SMPK THOMAS AQUINO | G41: 551103534720 | I41: 45958 | J41: 45964 | K41: 45965 | L41: 45987 | M41: =+IF(L41<>"","Done Boram",IF(K41<>"","SPBR submit to PLN",IF(J41<>"","SPBR Release",IF(I41<>"","Submit App SPBR","")))) -> Done Boram
A42: 39 | B42: E3300214 | C42: SALATIGA_SLT | D42: IOH | E42: 14STG0029 | F42: SALATIGA_SLT_EP | G42: 523511005416 | H42: 23000 | M42: =+IF(L42<>"","Done Boram",IF(K42<>"","SPBR submit to PLN",IF(J42<>"","SPBR Release",IF(I42<>"","Submit App SPBR",""))))
A43: 40 | B43: E3300214 | C43: SALATIGA_SLT | D43: XLS | E43: JAW-JT-SLT-2167 | F43: SALATIGA SELATAN | G43: 523511496062 | H43: 17600 | M43: =+IF(L43<>"","Done Boram",IF(K43<>"","SPBR submit to PLN",IF(J43<>"","SPBR Release",IF(I43<>"","Submit App SPBR",""))))
A44: 41 | B44: E3300288 | C44: PR KUDUS | D44: IOH | E44: 14KDS0024 | F44: PRKUDUS_EP | G44: 520013759025 | I44: 45924 | J44: 45924 | K44: 45925 | L44: 45930 | M44: =+IF(L44<>"","Done Boram",IF(K44<>"","SPBR submit to PLN",IF(J44<>"","SPBR Release",IF(I44<>"","Submit App SPBR","")))) -> Done Boram
A45: 42 | B45: E1200351 | C45: DANAGRAHA_BUILDING1 / DANA GRAHA | D45: IOH | E45: 05BTM0128 | F45: DANAGRAHA_BUILDING_EP | G45: 151001829409 | I45: 45961 | J45: 45961 | K45: 45967 | L45: 45993 | M45: =+IF(L45<>"","Done Boram",IF(K45<>"","SPBR submit to PLN",IF(J45<>"","SPBR Release",IF(I45<>"","Submit App SPBR","")))) -> Done Boram
A46: 43 | B46: E1200372 | C46: NONGSA_RESORT_1 | D46: IOH | E46: 05BTM0283 | F46: NONGSA_RESORT_EP | G46: 151000866377 | H46: 13200 | I46: 45951 | J46: 45988 | K46: 45988 | L46: 46009 | M46: =+IF(L46<>"","Done Boram",IF(K46<>"","SPBR submit to PLN",IF(J46<>"","SPBR Release",IF(I46<>"","Submit App SPBR","")))) -> Done Boram
A47: 44 | B47: E1200372 | C47: NONGSA_RESORT_1 | D47: XLS | E47: SUM-KR-BTM-0492 | F47: NONGSA_RESORT_1 | G47: 154000398840 | H47: 6600 | I47: 45971 | J47: 45972 | K47: 45973 | L47: 46000 | M47: =+IF(L47<>"","Done Boram",IF(K47<>"","SPBR submit to PLN",IF(J47<>"","SPBR Release",IF(I47<>"","Submit App SPBR","")))) -> Done Boram
A48: 45 | B48: E1200372 | C48: NONGSA_RESORT_1 | D48: TSEL | E48: BTM429 | F48: NONGSA_RESORT | G48: 154000200962 | H48: 7700 | I48: 45957 | J48: 45968 | K48: 45973 | L48: 46000 | M48: =+IF(L48<>"","Done Boram",IF(K48<>"","SPBR submit to PLN",IF(J48<>"","SPBR Release",IF(I48<>"","Submit App SPBR","")))) -> Done Boram
A49: 46 | B49: R5100118 | C49: PENYARINGAN RELOC | D49: IOH | E49: 17DPS0255 | F49: PENYARINGAN_CM | G49: 551004242550 | H49: 6600 | I49: 46030 | J49: 46031 | K49: 46065 | L49: 46080 | M49: =+IF(L49<>"","Done Boram",IF(K49<>"","SPBR submit to PLN",IF(J49<>"","SPBR Release",IF(I49<>"","Submit App SPBR","")))) -> Done Boram
A50: 47 | B50: R5100118 | C50: PENYARINGAN RELOC | D50: XLS | E50: BAL-BA-DPR-0349 | F50: PENYARINGAN BALI Relocation | G50: 551004153092 | H50: 16500 | I50: 46030 | J50: 46030 | K50: 46065 | L50: 46080 | M50: =+IF(L50<>"","Done Boram",IF(K50<>"","SPBR submit to PLN",IF(J50<>"","SPBR Release",IF(I50<>"","Submit App SPBR","")))) -> Done Boram
A51: 48 | B51: R5100118 | C51: PENYARINGAN RELOC | D51: TSEL | E51: DPR134 | F51: PENYARINGAN RELOC | G51: 551004164236 | H51: 10600 | I51: 46030 | J51: 46045 | K51: 46065 | L51: 46080 | M51: =+IF(L51<>"","Done Boram",IF(K51<>"","SPBR submit to PLN",IF(J51<>"","SPBR Release",IF(I51<>"","Submit App SPBR","")))) -> Done Boram
A52: 49 | B52: R6400134 | C52: BATUAH KM.45 | D52: XLS | E52: KAL-KI-TRG-0464 | F52: BATUAH KM.45 | G52: 231047000599 | H52: 6600 | I52: 46030 | J52: 46030 | K52: 46036 | L52: 46073 | M52: =+IF(L52<>"","Done Boram",IF(K52<>"","SPBR submit to PLN",IF(J52<>"","SPBR Release",IF(I52<>"","Submit App SPBR","")))) -> Done Boram
A53: 50 | B53: E3500389 | C53: BURNEH | D53: IOH | E53: 16BKN0064 | F53: BURNEH_EP | G53: 517300513859 | H53: 16500 | I53: 46062 | J53: 46076 | K53: 46076 | L53: 46114 | M53: =+IF(L53<>"","Done Boram",IF(K53<>"","SPBR submit to PLN",IF(J53<>"","SPBR Release",IF(I53<>"","Submit App SPBR","")))) -> Done Boram
A54: 51 | B54: R7300461 | C54: Nuri Rajawali | D54: XLS | E54: SUL-SN-MKS-0125 | F54: RAJAWALI | G54: 321401616005 | I54: 45958 | J54: 45964 | K54: 45964 | L54: 45981 | M54: =+IF(L54<>"","Done Boram",IF(K54<>"","SPBR submit to PLN",IF(J54<>"","SPBR Release",IF(I54<>"","Submit App SPBR","")))) -> Done Boram
A55: 52 | B55: E3500389 | C55: BURNEH | D55: TSEL | E55: BKN109 | F55: BURNEH | G55: 517300843005 | H55: 10600 | I55: 46062 | J55: 46084 | K55: 46085 | L55: 46114 | M55: =+IF(L55<>"","Done Boram",IF(K55<>"","SPBR submit to PLN",IF(J55<>"","SPBR Release",IF(I55<>"","Submit App SPBR","")))) -> Done Boram
A56: 53 | B56: R3100496 | C56: KELAPA DUA WETAN | D56: XLS | E56: JAW-JK-CKG-0221 | F56: KELAPA DUA WETAN | G56: 547200633598 | I56: 45974 | J56: 46002 | K56: 46002 | L56: 46003 | M56: =+IF(L56<>"","Done Boram",IF(K56<>"","SPBR submit to PLN",IF(J56<>"","SPBR Release",IF(I56<>"","Submit App SPBR","")))) -> Done Boram
A57: 54 | B57: E1600040 | C57: MUARA_BELITI | D57: IOH | E57: 07LLG0030 | F57: MUARA_BELITI_EP | G57: 147800047966 | H57: 13200 | I57: 46199 | J57: 46205 | K57: 46205 | L57: 46216 | M57: =+IF(L57<>"","Done Boram",IF(K57<>"","SPBR submit to PLN",IF(J57<>"","SPBR Release",IF(I57<>"","Submit App SPBR","")))) -> Done Boram | N57: 07.07.26 done boram, waiting BA
A58: 55 | B58: R3350446 | C58: WURYANTORO | D58: XLS | E58: JAW-JT-WNG-2807 | F58: WURYANTORO | G58: 520601092420 | H58: 13900 | I58: 45974 | J58: 46007 | K58: 46007 | L58: 46032 | M58: =+IF(L58<>"","Done Boram",IF(K58<>"","SPBR submit to PLN",IF(J58<>"","SPBR Release",IF(I58<>"","Submit App SPBR","")))) -> Done Boram
A59: 56 | B59: E1600040 | C59: MUARA_BELITI | D59: TSEL | G59: 147800525248 | M59: =+IF(L59<>"","Done Boram",IF(K59<>"","SPBR submit to PLN",IF(J59<>"","SPBR Release",IF(I59<>"","Submit App SPBR",""))))
A60: 57 | B60: R3300369 | C60: NUSUKAN I | D60: IOH | E60: 14SKA0067 | F60: KAPTENPT_CM | G60: 520521333891 | H60: 11000 | M60: =+IF(L60<>"","Done Boram",IF(K60<>"","SPBR submit to PLN",IF(J60<>"","SPBR Release",IF(I60<>"","Submit App SPBR",""))))
A61: 58 | B61: R3300369 | C61: NUSUKAN I | D61: XLS | E61: JAW-JT-SKT-2056 | F61: NUSUKAN RELOCATION 2 | G61: 520521374285 | H61: 13900 | M61: =+IF(L61<>"","Done Boram",IF(K61<>"","SPBR submit to PLN",IF(J61<>"","SPBR Release",IF(I61<>"","Submit App SPBR",""))))
A62: 59 | B62: R7300203 | C62: KIMA 2 | D62: IOH | E62: 29UPD0326 | F62: IRSUTAMI_BIRA_CM | G62: 321302090948 | H62: 7700 | I62: 46044 | J62: 46078 | K62: 46078 | L62: 46087 | M62: =+IF(L62<>"","Done Boram",IF(K62<>"","SPBR submit to PLN",IF(J62<>"","SPBR Release",IF(I62<>"","Submit App SPBR","")))) -> Done Boram
A63: 60 | B63: R7200006 | C63: NALU | D63: IOH | E63: 27TLI0023 | F63: NALU | G63: 315010498239 | H63: 10600 | I63: 46128 | J63: 46132 | K63: 46133 | L63: 46141 | M63: =+IF(L63<>"","Done Boram",IF(K63<>"","SPBR submit to PLN",IF(J63<>"","SPBR Release",IF(I63<>"","Submit App SPBR","")))) -> Done Boram
A64: 61 | B64: R3270659 | C64: PERUMNAS CIJERAH | D64: XLS | E64: JAW-JB-BDG-0733 | F64: PERUMNAS CIJERAH | G64: 535555667882 | I64: 45974 | J64: 45986 | K64: 45986 | L64: 45989 | M64: =+IF(L64<>"","Done Boram",IF(K64<>"","SPBR submit to PLN",IF(J64<>"","SPBR Release",IF(I64<>"","Submit App SPBR","")))) -> Done Boram
A65: 62 | B65: R7300203 | C65: KIMA 2 | D65: XLS | E65: SUL-SN-MKS-0278 | F65: KIMA DUA | G65: 321300601220 | H65: 23000 | I65: 46044 | J65: 46071 | K65: 46071 | L65: 46087 | M65: =+IF(L65<>"","Done Boram",IF(K65<>"","SPBR submit to PLN",IF(J65<>"","SPBR Release",IF(I65<>"","Submit App SPBR","")))) -> Done Boram
A66: 63 | B66: R7200006 | C66: NALU | D66: XLS | E66: SUL-ST-TLI-0176 | F66: NALU HANYALAH | G66: 315010360795 | H66: 6600 | I66: 46128 | J66: 46132 | K66: 46133 | L66: 46141 | M66: =+IF(L66<>"","Done Boram",IF(K66<>"","SPBR submit to PLN",IF(J66<>"","SPBR Release",IF(I66<>"","Submit App SPBR","")))) -> Done Boram
A67: 64 | B67: E3100424 | C67: SUNTER_B | D67: IOH | E67: 12JKU0296 | F67: SUNTER_JKU1_EP | G67: 545103061273 | I67: 45971 | M67: =+IF(L67<>"","Done Boram",IF(K67<>"","SPBR submit to PLN",IF(J67<>"","SPBR Release",IF(I67<>"","Submit App SPBR","")))) -> Submit App SPBR
A68: 65 | B68: R3100533 | C68: PELEPAH INDAH | D68: XLS | E68: JAW-JK-TJP-2426 | F68: PELEPAH INDAH | G68: 545102776942 | H68: 16500 | I68: 46029 | J68: 46030 | K68: 46034 | L68: 46037 | M68: =+IF(L68<>"","Done Boram",IF(K68<>"","SPBR submit to PLN",IF(J68<>"","SPBR Release",IF(I68<>"","Submit App SPBR","")))) -> Done Boram
A69: 66 | B69: E1200395 | C69: KM 6 TG.PINANG / SUNGAI JANG SEAFOOD | D69: IOH | E69: 05TJG0026 | F69: KM6PINANG_EP | G69: 183090278172 | I69: 46150 | J69: 46153 | K69: 46153 | L69: 46184 | M69: =+IF(L69<>"","Done Boram",IF(K69<>"","SPBR submit to PLN",IF(J69<>"","SPBR Release",IF(I69<>"","Submit App SPBR","")))) -> Done Boram | N69: 15.05.26 Boram done (waiting BA Boram)
A70: 67 | B70: R3580695 | C70: 3G_Kupang Krajan Sawahan | D70: XLS | E70: JAW-JI-SBY-2377 | F70: KUPANGKRAJAN SAWAHAN | G70: 511063165327 | H70: 13200 | I70: 46083 | J70: 46086 | K70: 46086 | L70: 46099 | M70: =+IF(L70<>"","Done Boram",IF(K70<>"","SPBR submit to PLN",IF(J70<>"","SPBR Release",IF(I70<>"","Submit App SPBR","")))) -> Done Boram
A71: 68 | B71: E3100287 | C71: KAMPUNG_SAWAH | D71: IOH | E71: 12JKS0715 | F71: KAMPUNG_SAWAH_EP | G71: 547500442841 | H71: 33000 | I71: 46112 | J71: 46119 | K71: 46119 | L71: 46127 | M71: =+IF(L71<>"","Done Boram",IF(K71<>"","SPBR submit to PLN",IF(J71<>"","SPBR Release",IF(I71<>"","Submit App SPBR","")))) -> Done Boram
A72: 69 | B72: E6400049 | C72: WADUK MANGGAR | D72: XLS | E72: ZBLK_0069 | F72: WADUK MANGGAR | G72: 232011576146 | I72: 45973 | J72: 46007 | K72: 46007 | M72: =+IF(L72<>"","Done Boram",IF(K72<>"","SPBR submit to PLN",IF(J72<>"","SPBR Release",IF(I72<>"","Submit App SPBR","")))) -> SPBR submit to PLN | N72: TSA tidak jadi boram, diminta KTP penanggung jawab dari XL sama PLN. XL tidak mau ngasih
A73: 70 | B73: E3100287 | C73: KAMPUNG_SAWAH | D73: XLS | E73: JAW-JK-KYB-0175 | F73: RAYA LENTENG AGUNG RELOC | G73: 547401310502 | H73: 16500 | I73: 46112 | J73: 46114 | K73: 46119 | L73: 46127 | M73: =+IF(L73<>"","Done Boram",IF(K73<>"","SPBR submit to PLN",IF(J73<>"","SPBR Release",IF(I73<>"","Submit App SPBR","")))) -> Done Boram
A74: 71 | B74: E6400049 | C74: WADUK MANGGAR | D74: TSEL | G74: 232011396690 | I74: 45974 | M74: =+IF(L74<>"","Done Boram",IF(K74<>"","SPBR submit to PLN",IF(J74<>"","SPBR Release",IF(I74<>"","Submit App SPBR","")))) -> Submit App SPBR | N74: TSA tidak jadi boram, diminta KTP penanggung jawab dari telkomsel sama PLN. Tsel tidak mau ngasih
A75: 72 | B75: R1200302 | C75: BANGUN PURBA | D75: XLS | E75: SUM-SU-LBP-0405 | F75: BANGUN PURBA | G75: 126170452098 | H75: 13200 | I75: 46163 | J75: 46168 | K75: 46171 | L75: 46190 | M75: =+IF(L75<>"","Done Boram",IF(K75<>"","SPBR submit to PLN",IF(J75<>"","SPBR Release",IF(I75<>"","Submit App SPBR","")))) -> Done Boram
A76: 73 | B76: E1200357 | C76: BENGKONG_HARAPAN | D76: IOH | E76: 07BTM059 | F76: BENGKONGHARAPAN_EP | G76: 151000434988 | H76: 10600 | I76: 46085 | J76: 46090 | K76: 46090 | L76: 46155 | M76: =+IF(L76<>"","Done Boram",IF(K76<>"","SPBR submit to PLN",IF(J76<>"","SPBR Release",IF(I76<>"","Submit App SPBR","")))) -> Done Boram | N76: KWH Stolen Done payment, waiting BA putus langganan
A77: 74 | B77: R3350436 | C77: CIMANGGU CILACAP | D77: XLS | E77: JAW-JT-CLP-0423 | F77: CIMANGGU CILACAP | G77: 525020470615 | M77: =+IF(L77<>"","Done Boram",IF(K77<>"","SPBR submit to PLN",IF(J77<>"","SPBR Release",IF(I77<>"","Submit App SPBR",""))))
A78: 75 | B78: R3350421 | C78: KARANGJUNTI | D78: IOH | E78: 14BRS0006 | F78: KARANGJUNTI_CM | G78: 522550779277 | H78: 7700 | I78: 46154 | J78: 46178 | K78: 46181 | L78: 46196 | M78: =+IF(L78<>"","Done Boram",IF(K78<>"","SPBR submit to PLN",IF(J78<>"","SPBR Release",IF(I78<>"","Submit App SPBR","")))) -> Done Boram
A79: 76 | B79: R3350421 | C79: KARANGJUNTI | D79: XLS | E79: JAW-JT-BBS-0007 | F79: KARANGJUNTI | G79: 522550705294 | H79: 16500 | I79: 46154 | J79: 46155 | K79: 46195 | L79: 46217 | M79: =+IF(L79<>"","Done Boram",IF(K79<>"","SPBR submit to PLN",IF(J79<>"","SPBR Release",IF(I79<>"","Submit App SPBR","")))) -> Done Boram | N79: 13.07.26 Plan boram by PLN
A80: 77 | B80: E7300112 | C80: BANTAENG | D80: IOH | E80: 29BTN0012 | F80: BANTAENG_EP | G80: 327400105660 | H80: 16500 | M80: =+IF(L80<>"","Done Boram",IF(K80<>"","SPBR submit to PLN",IF(J80<>"","SPBR Release",IF(I80<>"","Submit App SPBR",""))))
A81: 78 | B81: R3270184 | C81: SETRAINDAH BARAT | D81: IOH | E81: 13BDG0084 | F81: SETRAINDAHBARAT_CM | G81: 535596541629 | H81: 13200 | I81: 46233 | M81: =+IF(L81<>"","Done Boram",IF(K81<>"","SPBR submit to PLN",IF(J81<>"","SPBR Release",IF(I81<>"","Submit App SPBR","")))) -> Submit App SPBR
A82: 79 | B82: R3270184 | C82: SETRAINDAH BARAT | D82: XLS | E82: JAW-JB-BDG-0045 | F82: SETRA INDAH BARAT | G82: 535596533200 | H82: 13200 | I82: 46233 | J82: 46237 | M82: =+IF(L82<>"","Done Boram",IF(K82<>"","SPBR submit to PLN",IF(J82<>"","SPBR Release",IF(I82<>"","Submit App SPBR","")))) -> SPBR Release
A83: 80 | B83: E3500307 | C83: MOROKREMBANGAN | D83: IOH | E83: 20SBY108 | F83: MOROKREMBANGAN_EP | G83: 511040478991 | H83: 13200 | I83: 46181 | J83: 46188 | K83: 46189 | L83: 42568 | M83: =+IF(L83<>"","Done Boram",IF(K83<>"","SPBR submit to PLN",IF(J83<>"","SPBR Release",IF(I83<>"","Submit App SPBR","")))) -> Done Boram
A84: 81 | B84: E3500307 | C84: MOROKREMBANGAN | D84: XLS | E84: BJM179 | F84: PERAK BARAT KREMBANGAN BARU | G84: 511040594261 | H84: 23000 | I84: 46181 | J84: 46185 | K84: 46189 | L84: 42568 | M84: =+IF(L84<>"","Done Boram",IF(K84<>"","SPBR submit to PLN",IF(J84<>"","SPBR Release",IF(I84<>"","Submit App SPBR","")))) -> Done Boram
A85: 82 | B85: E3500307 | C85: MOROKREMBANGAN | D85: TSEL | E85: SBY374 | F85: MOROKREMBANGAN | G85: 511040545712 | H85: 10600 | I85: 46181 | J85: 46185 | K85: 46189 | L85: 42568 | M85: =+IF(L85<>"","Done Boram",IF(K85<>"","SPBR submit to PLN",IF(J85<>"","SPBR Release",IF(I85<>"","Submit App SPBR","")))) -> Done Boram
A86: 83 | B86: E1200337 | C86: BUKIT_BALADA | D86: IOH | E86: 05BTM0018 | F86: BUKIT_BALADA_EP | G86: 152000372414 | H86: 13200 | M86: =+IF(L86<>"","Done Boram",IF(K86<>"","SPBR submit to PLN",IF(J86<>"","SPBR Release",IF(I86<>"","Submit App SPBR",""))))
A87: 84 | B87: E1200337 | C87: BUKIT_BALADA | D87: TSEL | M87: =+IF(L87<>"","Done Boram",IF(K87<>"","SPBR submit to PLN",IF(J87<>"","SPBR Release",IF(I87<>"","Submit App SPBR","")))) | N87: need ID Pel PLN (No ID Pel di box KWH)
A88: 85 | B88: E1200119 | C88: TELADAN | D88: IOH | E88: 02MDN0444 | F88: TELADAN_MDN_EP | G88: 120030477253 | M88: =+IF(L88<>"","Done Boram",IF(K88<>"","SPBR submit to PLN",IF(J88<>"","SPBR Release",IF(I88<>"","Submit App SPBR",""))))
A89: 86 | B89: E1200424 | C89: DAPUR_DUA_BELAS / DAPUR 12 | D89: IOH | E89: 05BTM0054 | F89: DAPUR_DUA_BELAS_EP | G89: 152001107489 | H89: 13200 | I89: 46198 | M89: =+IF(L89<>"","Done Boram",IF(K89<>"","SPBR submit to PLN",IF(J89<>"","SPBR Release",IF(I89<>"","Submit App SPBR","")))) -> Submit App SPBR | N89: SPBR NY release
A90: 87 | B90: E1200424 | C90: DAPUR_DUA_BELAS / DAPUR 12 | D90: TSEL | G90: 153000082661 | H90: 10600 | M90: =+IF(L90<>"","Done Boram",IF(K90<>"","SPBR submit to PLN",IF(J90<>"","SPBR Release",IF(I90<>"","Submit App SPBR","")))) | N90: need confirmation ID Pel PLN
A91: 88 | B91: E1200363 | C91: PINTU 4 MUKA KUNING | D91: IOH | E91: 05BTM0207 | F91: PINTU4_MUKA_KUNING_EP | G91: 151000857894 | H91: 16500 | I91: 46181 | M91: =+IF(L91<>"","Done Boram",IF(K91<>"","SPBR submit to PLN",IF(J91<>"","SPBR Release",IF(I91<>"","Submit App SPBR","")))) -> Submit App SPBR | N91: SPBR NY release
A92: 89 | B92: R7300149 | C92: KDI AEROPPALA | D92: TSEL | E92: UPD832 | G92: 321203251026 | H92: 13200 | I92: 46178 | J92: 46178 | K92: 46185 | L92: 46234 | M92: =+IF(L92<>"","Done Boram",IF(K92<>"","SPBR submit to PLN",IF(J92<>"","SPBR Release",IF(I92<>"","Submit App SPBR","")))) -> Done Boram
A93: 90 | B93: E3200034 | C93: CIPANGAUR | D93: IOH | E93: 13CBN0069 | F93: CIPANGAUR_EP | G93: 538530316568 | H93: 16500 | M93: =+IF(L93<>"","Done Boram",IF(K93<>"","SPBR submit to PLN",IF(J93<>"","SPBR Release",IF(I93<>"","Submit App SPBR",""))))
A94: 91 | B94: E3200269 | C94: CILEUNGSIKIDUL | D94: XLS | E94: NBGR_0125 | F94: CILEUNGSIKIDUL | G94: 538656796899 | H94: 13200 | I94: 46120 | J94: 46127 | K94: 46127 | L94: 46133 | M94: =+IF(L94<>"","Done Boram",IF(K94<>"","SPBR submit to PLN",IF(J94<>"","SPBR Release",IF(I94<>"","Submit App SPBR","")))) -> Done Boram
A95: 92 | B95: R3350451 | C95: BANYUURIP | D95: IOH | E95: 14PWR0054 | F95: BANYUURIP_CM | G95: 521520857598 | H95: 7700 | M95: =+IF(L95<>"","Done Boram",IF(K95<>"","SPBR submit to PLN",IF(J95<>"","SPBR Release",IF(I95<>"","Submit App SPBR",""))))
A96: 93 | B96: R3350451 | C96: BANYUURIP | D96: XLS | E96: JAW-JT-PWR-1640 | F96: BANYUURIP PURWOREJO | G96: 521520810681 | H96: 11000 | M96: =+IF(L96<>"","Done Boram",IF(K96<>"","SPBR submit to PLN",IF(J96<>"","SPBR Release",IF(I96<>"","Submit App SPBR",""))))
A97: 94 | B97: E9400005 | C97: TVRI BIAK | D97: IOH | E97: 33BIA0006 | G97: 422100182082 | H97: 10600 | I97: 46205 | M97: =+IF(L97<>"","Done Boram",IF(K97<>"","SPBR submit to PLN",IF(J97<>"","SPBR Release",IF(I97<>"","Submit App SPBR","")))) -> Submit App SPBR | N97: Waiting SPBR release
A98: 95 | B98: E3600214 | C98: SUPERMAL | D98: IOH | E98: 11TGN0458 | F98: SUPERMAL_EP | G98: In Building | H98: - | L98: 46098 | M98: =+IF(L98<>"","Done Boram",IF(K98<>"","SPBR submit to PLN",IF(J98<>"","SPBR Release",IF(I98<>"","Submit App SPBR","")))) -> Done Boram | N98: BA Switch Off
A99: 96 | B99: E3500375 | C99: MERPATI | D99: All Tenant | H99: 82500 | L99: 46092 | M99: =+IF(L99<>"","Done Boram",IF(K99<>"","SPBR submit to PLN",IF(J99<>"","SPBR Release",IF(I99<>"","Submit App SPBR","")))) -> Done Boram | N99: BA Switch Off
A100: 97 | B100: R3100450 | C100: KEBON SIRIH | D100: XLS | E100: ZJKT_4697 | F100: KEBON SIRIH | G100: In Building | L100: 46029 | M100: =+IF(L100<>"","Done Boram",IF(K100<>"","SPBR submit to PLN",IF(J100<>"","SPBR Release",IF(I100<>"","Submit App SPBR","")))) -> Done Boram | N100: BA Switch Off
...

Sheet CMI-RLC-Nasional
A1: Plan
A2: OG
A3: Pending | G3: {=COUNTA(_xlfn.UNIQUE(_xlfn._xlws.FILTER(G6:G995,SUBTOTAL(3,OFFSET(G6,ROW(G6:G995)-ROW(G6),0)))))} -> 1 | I3: =+SUBTOTAL(3,I6:I1002) -> 356 | AH3: =+SUBTOTAL(3,AH6:AH1002) -> 61 | BK3: =+SUBTOTAL(3,BK6:BK1002) -> 152 | BP3: =SUBTOTAL(3,BP6:BP296) -> 291
A4: Prayudi | W4: Aghnia | AD4: Prayudi | AQ4: Prayudi | BF4: Prabowo | BP4: Prayudi | CE4: New Site / FE MW
A5: NO | B5: Vendor Code | C5: Project Code | D5: Scope Of Area | E5: Unique ID | F5: Assignment | G5: Site ID Old | H5: Site ID New | I5: Site Name | J5: Zone | K5: Entity | L5: Provinsi | M5: Kota/Kabupaten | N5: Site Address | O5: LATITUDE | P5: LONGITUDE | Q5: Tower Weight - Original (kg) | R5: Tower Height (Eng) (m) | S5: Tenant | T5: Site Type | U5: Tower Type | V5: SOW Detail | W5: PIC | X5: Kontak | Y5: SOW Permit | Z5: Start | AA5: Expired | AB5: Validitas Permit | AC5: Remark Permit | AD5: Survey | AE5: Survey Report Submit | AF5: End Lease / Drop | AG5: RFD Approved | AH5: Dismantle Perangkat | AI5: Dismantle CME | AJ5: Inbound | AK5: Install | AL5: OA/RFS | AM5: ATP Approve MS | AN5: BAST | AO5: Update Progress | AP5: Remark Progress | AQ5: 1st BOQ Submit | AR5: 1st BOQ Pass TI | AS5: Engineering Structural Manager App | AT5: SPH 1 / BAN 1 App | AU5: Upload 1st BOQ & BAN Isaac | AV5: App 1st BOQ & BAN Isaac | AW5: 1st BOQ | AX5: 2nd BOQ Submit | AY5: 2nd BOQ Pass TI | AZ5: Engineering Structural Manager App | BA5: SPH 2 / BAN 2 App | BB5: Upload 2nd BOQ & BAN Isaac | BC5: App 2nd BOQ & BAN Isaac | BD5: 2nd BOQ | BE5: Remark BOQ | BF5: HSE Plan & JSA Submit | BG5: Isaac HSE Plan & JSA App | BH5: JSA Doc No. | BI5: SWP Submit | BJ5: SWP App | BK5: SWP Doc No | BL5: HSE & JSA | BM5: SWP | BN5: BA Dism / BA OA / BAST Submit | BO5: BA Dism / BA OA / BAST App | BP5: SOW | BQ5: PO Number | BR5: PO Release | BS5: Aging PO | BT5: PO Variation 1 | BU5: PO Variation 1 Release | BV5: Aging PO Variation 1 | BW5: PO Variation 2 | BX5: PO Variation 2 Release | BY5: Aging PO Variation 2 | BZ5: Blocking Issue | CA5: PIC Responsible | CB5: Company | CC5: Target Submit Date | CE5: Site ID | CF5: Site Name | CG5: LATITUDE | CH5: LONGITUDE | CI5: CR IOH | CJ5: XLWO | CK5: CRQ Tsel | CL5: Remark Reloc
A6: 1 | B6: CMI | C6: RLC | D6: Nasional | E6: =+_xlfn.CONCAT(G6,"-",B6,"_",C6,"_",_xlfn.XLOOKUP(BP6,Account!M:M,Account!N:N)) -> #NAME? | F6: 45670 | G6: E3300061 | H6: ID-JT-05773 | I6: RSMARGONO | J6: 11 | K6: EMA | L6: JAWA TENGAH | M6: Kab. Banyumas | N6: KOMPLEK RS. MARGONO JL. JEND. SUDIRMAN PURWOKERTO | O6: -7.43475 | P6: 109.2674 | Q6: 13067.712 | R6: 55 | S6: IOH (hwei) | T6: Greenfield | U6: SST 4 Legs | V6: Dismantle Tower | W6: Joko Dedoyo Kecil Liyanto | X6: 87861095209 | Y6: Dismantle | Z6: 45713 | AA6: 45720 | AB6: =IF(AA6="ds","Submit",IF(AA6="","NY Submit",IF(AA6<TODAY(),"Expired",IFERROR(DATEDIF(TODAY(),AA6,"d"),"")))) -> Expired | AD6: 45681 | AE6: 45686 | AG6: 45716 | AI6: 45722 | AN6: 45727 | AO6: =+IF(AN6<>"","BAST",IF(AI6<>"","Dismantle",IF(AG6<>"","RFD App",IF(AF6="Drop","Drop",IF(AE6<>"","Survey Report",IF(AD6<>"","Survey","NY Survey")))))) -> BAST | AQ6: 45719 | AR6: 45719 | AS6: 45719 | AT6: 45765 | AU6: 45735 | AV6: 45735 | AW6: =+IF(AV6<>"","1st BOQ App on ISAAC",IF(AU6<>"","Upload 1st BOQ & BAN Isaac",IF(AT6="DRM","need DRM",IF(AT6<>"","BAN App",IF(AR6<>"","1st BOQ Pass TI",IF(AS6<>"","Engineering Structural Manager App",IF(AQ6<>"","1st BOQ Submit","NY Submit"))))))) -> 1st BOQ App on ISAAC | BD6: =+IF(BC6<>"","2nd BOQ App on ISAAC",IF(BB6<>"","Upload 2nd BOQ & BAN Isaac",IF(BA6="DRM","need DRM",IF(BA6<>"","BAN App",IF(AZ6<>"","Engineering Structural Manager App",IF(AY6<>"","2nd BOQ Pass TI",IF(AX6<>"","2nd BOQ Submit","NY Submit"))))))) -> NY Submit | BF6: 45689 | BG6: 45695 | BH6: JSA No.02/TSA/HSE/02/2025 | BI6: 45689 | BJ6: 45695 | BK6: SWP-HSE-09 | BL6: =+IF(BG6<>"","Approved",IF(BF6<>"","Submit","NY Submit")) -> Approved | BM6: =+IF(BJ6<>"","Approved",IF(BI6<>"","Submit","NY Submit")) -> Approved | BN6: 45727 | BO6: 45727 | BP6: Dismantle Tower | BQ6: EMAPO25-000807 | BR6: 45791 | BS6: =IF(AO6="Drop", "Drop", IF(ISBLANK(AV6), 0, IF(ISBLANK(BR6), DATEDIF(AV6,TODAY(),"d"), DATEDIF(AV6,BR6,"d") ) ) ) -> 56 | BV6: =IF(AO6="Drop", "Drop", IF(ISBLANK(BC6), 0, IF(ISBLANK(BU6), DATEDIF(BC6,TODAY(),"d"), DATEDIF(BC6,BU6,"d") ) ) ) -> 0 | BZ6: Complete | CE6: ID-JT-14614 | CF6: PAMIJEN SOKARAJA | CG6: -7.43527 | CH6: 109.27026 | CI6: CR-20250226-00000275
A7: 2 | B7: CMI | C7: RLC | D7: Nasional | E7: =+_xlfn.CONCAT(G7,"-",B7,"_",C7,"_",_xlfn.XLOOKUP(BP7,Account!M:M,Account!N:N)) -> #NAME? | F7: 45670 | G7: E3300061 | H7: ID-JT-05773 | I7: RSMARGONO | J7: 11 | K7: EMA | L7: JAWA TENGAH | M7: Kab. Banyumas | N7: KOMPLEK RS. MARGONO JL. JEND. SUDIRMAN PURWOKERTO | O7: -7.43475 | P7: 109.2674 | Q7: 13067.712 | R7: 55 | S7: IOH (hwei) | T7: Greenfield | U7: SST 4 Legs | V7: Dismantle Equipment | W7: Joko Dedoyo Kecil Liyanto | X7: 87861095209 | Y7: Dismantle | Z7: 45713 | AA7: 45720 | AB7: =IF(AA7="ds","Submit",IF(AA7="","NY Submit",IF(AA7<TODAY(),"Expired",IFERROR(DATEDIF(TODAY(),AA7,"d"),"")))) -> Expired | AD7: 45681 | AE7: 45686 | AH7: 45717 | AM7: 45727 | AO7: =+IF(AM7<>"","ATP App MS",IF(AJ7<>"","Inbound",IF(AH7<>"","Dismantle Perangkat",IF(AF7="Drop","Drop",IF(AE7<>"","Survey Report",IF(AD7<>"","Survey","NY Survey")))))) -> ATP App MS | AQ7: 45719 | AR7: 45719 | AS7: 45719 | AT7: 45765 | AU7: 45735 | AV7: 45735 | AW7: =+IF(AV7<>"","1st BOQ App on ISAAC",IF(AU7<>"","Upload 1st BOQ & BAN Isaac",IF(AT7="DRM","need DRM",IF(AT7<>"","BAN App",IF(AR7<>"","1st BOQ Pass TI",IF(AS7<>"","Engineering Structural Manager App",IF(AQ7<>"","1st BOQ Submit","NY Submit"))))))) -> 1st BOQ App on ISAAC | BD7: =+IF(BC7<>"","2nd BOQ App on ISAAC",IF(BB7<>"","Upload 2nd BOQ & BAN Isaac",IF(BA7="DRM","need DRM",IF(BA7<>"","BAN App",IF(AZ7<>"","Engineering Structural Manager App",IF(AY7<>"","2nd BOQ Pass TI",IF(AX7<>"","2nd BOQ Submit","NY Submit"))))))) -> NY Submit | BF7: 45689 | BG7: 45695 | BH7: JSA No.02/TSA/HSE/02/2025 | BI7: 45689 | BJ7: 45708 | BL7: =+IF(BG7<>"","Approved",IF(BF7<>"","Submit","NY Submit")) -> Approved | BM7: =+IF(BJ7<>"","Approved",IF(BI7<>"","Submit","NY Submit")) -> Approved | BN7: 45727 | BO7: 45803 | BP7: Dismantle Equipment | BQ7: EMAPO25-000808 | BR7: 45791 | BS7: =IF(AO7="Drop", "Drop", IF(ISBLANK(AV7), 0, IF(ISBLANK(BR7), DATEDIF(AV7,TODAY(),"d"), DATEDIF(AV7,BR7,"d") ) ) ) -> 56 | BV7: =IF(AO7="Drop", "Drop", IF(ISBLANK(BC7), 0, IF(ISBLANK(BU7), DATEDIF(BC7,TODAY(),"d"), DATEDIF(BC7,BU7,"d") ) ) ) -> 0 | BZ7: Complete | CE7: ID-JT-14614 | CF7: PAMIJEN SOKARAJA | CG7: -7.43527 | CH7: 109.27026 | CI7: CR-20250226-00000275
A8: 3 | B8: CMI | C8: RLC | D8: Nasional | E8: =+_xlfn.CONCAT(G8,"-",B8,"_",C8,"_",_xlfn.XLOOKUP(BP8,Account!M:M,Account!N:N)) -> #NAME? | F8: 45670 | G8: E3300061 | H8: ID-JT-05773 | I8: RSMARGONO | J8: 11 | K8: EMA | L8: JAWA TENGAH | M8: Kab. Banyumas | N8: KOMPLEK RS. MARGONO JL. JEND. SUDIRMAN PURWOKERTO | O8: -7.43475 | P8: 109.2674 | Q8: 13067.712 | R8: 55 | S8: IOH (hwei) | T8: Greenfield | U8: SST 4 Legs | V8: Relocation Equipment | W8: Joko Dedoyo Kecil Liyanto | X8: 87861095209 | Y8: Dismantle | Z8: 45713 | AA8: 45720 | AB8: =IF(AA8="ds","Submit",IF(AA8="","NY Submit",IF(AA8<TODAY(),"Expired",IFERROR(DATEDIF(TODAY(),AA8,"d"),"")))) -> Expired | AD8: 45681 | AE8: 45686 | AK8: 45719 | AL8: 45719 | AM8: 45727 | AO8: =+IF(AM8<>"","ATP App MS",IF(AL8<>"","OA/RFS",IF(AK8<>"","Install",IF(AH8<>"","Dismantle Perangkat",IF(AF8="Drop","Drop",IF(AE8<>"","Survey Report",IF(AD8<>"","Survey","NY Survey"))))))) -> ATP App MS | AQ8: 45719 | AR8: 45719 | AS8: 45719 | AT8: 45765 | AU8: 45735 | AV8: 45735 | AW8: =+IF(AV8<>"","1st BOQ App on ISAAC",IF(AU8<>"","Upload 1st BOQ & BAN Isaac",IF(AT8="DRM","need DRM",IF(AT8<>"","BAN App",IF(AR8<>"","1st BOQ Pass TI",IF(AS8<>"","Engineering Structural Manager App",IF(AQ8<>"","1st BOQ Submit","NY Submit"))))))) -> 1st BOQ App on ISAAC | BD8: =+IF(BC8<>"","2nd BOQ App on ISAAC",IF(BB8<>"","Upload 2nd BOQ & BAN Isaac",IF(BA8="DRM","need DRM",IF(BA8<>"","BAN App",IF(AZ8<>"","Engineering Structural Manager App",IF(AY8<>"","2nd BOQ Pass TI",IF(AX8<>"","2nd BOQ Submit","NY Submit"))))))) -> NY Submit | BF8: 45689 | BG8: 45695 | BH8: JSA No.02/TSA/HSE/02/2025 | BI8: 45689 | BJ8: 45708 | BL8: =+IF(BG8<>"","Approved",IF(BF8<>"","Submit","NY Submit")) -> Approved | BM8: =+IF(BJ8<>"","Approved",IF(BI8<>"","Submit","NY Submit")) -> Approved | BN8: 45727 | BO8: 45803 | BP8: Relocation Equipment | BQ8: EMAPO25-000809 | BR8: 45791 | BS8: =IF(AO8="Drop", "Drop", IF(ISBLANK(AV8), 0, IF(ISBLANK(BR8), DATEDIF(AV8,TODAY(),"d"), DATEDIF(AV8,BR8,"d") ) ) ) -> 56 | BV8: =IF(AO8="Drop", "Drop", IF(ISBLANK(BC8), 0, IF(ISBLANK(BU8), DATEDIF(BC8,TODAY(),"d"), DATEDIF(BC8,BU8,"d") ) ) ) -> 0 | BZ8: Complete | CE8: ID-JT-14614 | CF8: PAMIJEN SOKARAJA | CG8: -7.43527 | CH8: 109.27026 | CI8: CR-20250226-00000275
A9: 4 | B9: CMI | C9: RLC | D9: Nasional | E9: =+_xlfn.CONCAT(G9,"-",B9,"_",C9,"_",_xlfn.XLOOKUP(BP9,Account!M:M,Account!N:N)) -> #NAME? | F9: 45670 | G9: E3300061 | H9: ID-JT-05773 | I9: RSMARGONO | J9: 11 | K9: EMA | L9: JAWA TENGAH | M9: Kab. Banyumas | N9: KOMPLEK RS. MARGONO JL. JEND. SUDIRMAN PURWOKERTO | O9: -7.43475 | P9: 109.2674 | Q9: 13067.712 | R9: 55 | S9: IOH (hwei) | T9: Greenfield | U9: SST 4 Legs | V9: Rebuild_LOS Survey 14PWT0167_RSMARGONO to 14PWT0200_Purwadadi MT | W9: Joko Dedoyo Kecil Liyanto | X9: 87861095209 | Y9: Dismantle | Z9: 45713 | AA9: 45720 | AB9: =IF(AA9="ds","Submit",IF(AA9="","NY Submit",IF(AA9<TODAY(),"Expired",IFERROR(DATEDIF(TODAY(),AA9,"d"),"")))) -> Expired | AD9: 45737 | AE9: 45737 | AM9: 45737 | AO9: =+IF(AM9<>"","Survey LOS App",IF(AF9="Drop","Drop",IF(AE9<>"","Survey Report",IF(AD9<>"","Survey","NY Survey")))) -> Survey LOS App | AW9: =+IF(AV9<>"","1st BOQ App on ISAAC",IF(AU9<>"","Upload 1st BOQ & BAN Isaac",IF(AT9="DRM","need DRM",IF(AT9<>"","BAN App",IF(AR9<>"","1st BOQ Pass TI",IF(AS9<>"","Engineering Structural Manager App",IF(AQ9<>"","1st BOQ Submit","NY Submit"))))))) -> NY Submit | BD9: =+IF(BC9<>"","2nd BOQ App on ISAAC",IF(BB9<>"","Upload 2nd BOQ & BAN Isaac",IF(BA9="DRM","need DRM",IF(BA9<>"","BAN App",IF(AZ9<>"","Engineering Structural Manager App",IF(AY9<>"","2nd BOQ Pass TI",IF(AX9<>"","2nd BOQ Submit","NY Submit"))))))) -> NY Submit | BL9: =+IF(BG9<>"","Approved",IF(BF9<>"","Submit","NY Submit")) -> NY Submit | BM9: =+IF(BJ9<>"","Approved",IF(BI9<>"","Submit","NY Submit")) -> NY Submit | BP9: Rebuild_LOS Survey | BQ9: EMAPO25-000367 | BR9: 45726 | BS9: =IF(AO9="Drop", "Drop", IF(ISBLANK(AV9), 0, IF(ISBLANK(BR9), DATEDIF(AV9,TODAY(),"d"), DATEDIF(AV9,BR9,"d") ) ) ) -> 0 | BV9: =IF(AO9="Drop", "Drop", IF(ISBLANK(BC9), 0, IF(ISBLANK(BU9), DATEDIF(BC9,TODAY(),"d"), DATEDIF(BC9,BU9,"d") ) ) ) -> 0 | BZ9: Complete | CE9: 14PWT0200 | CF9: Purwadadi MT | CG9: -7.43527 | CH9: 109.27026
A10: 5 | B10: CMI | C10: RLC | D10: Nasional | E10: =+_xlfn.CONCAT(G10,"-",B10,"_",C10,"_",_xlfn.XLOOKUP(BP10,Account!M:M,Account!N:N)) -> #NAME? | F10: 45670 | G10: E3300287 | H10: ID-JT-05997 | I10: SINGOSAREN_NEW | J10: 11 | K10: EMA | L10: JAWA TENGAH | M10: Kota Surakarta | N10: Jl. Gatot Subroto No.27 - 28, Kemlayan, Kec. Serengan, Kota Surakarta | O10: -7.57308 | P10: 110.82058 | Q10: 2490.696 | R10: 20 | S10: IOH (hwei) | T10: Rooftop | U10: MT 4 Legs | V10: Dismantle Tower | Y10: Survey | Z10: 45692 | AA10: 45700 | AB10: =IF(AA10="ds","Submit",IF(AA10="","NY Submit",IF(AA10<TODAY(),"Expired",IFERROR(DATEDIF(TODAY(),AA10,"d"),"")))) -> Expired | AD10: 45695 | AE10: 45698 | AG10: 46034 | AI10: 46058 | AN10: 46058 | AO10: =+IF(AN10<>"","BAST",IF(AI10<>"","Dismantle",IF(AG10<>"","RFD App",IF(AF10="Drop","Drop",IF(AE10<>"","Survey Report",IF(AD10<>"","Survey","NY Survey")))))) -> BAST | AP10: 03.02.26 Start dismantle | AQ10: 45999 | AR10: 46034 | AS10: 46006 | AU10: 46034 | AV10: 46034 | AW10: =+IF(AV10<>"","1st BOQ App on ISAAC",IF(AU10<>"","Upload 1st BOQ & BAN Isaac",IF(AT10="DRM","need DRM",IF(AT10<>"","BAN App",IF(AR10<>"","1st BOQ Pass TI",IF(AS10<>"","Engineering Structural Manager App",IF(AQ10<>"","1st BOQ Submit","NY Submit"))))))) -> 1st BOQ App on ISAAC | BD10: =+IF(BC10<>"","2nd BOQ App on ISAAC",IF(BB10<>"","Upload 2nd BOQ & BAN Isaac",IF(BA10="DRM","need DRM",IF(BA10<>"","BAN App",IF(AZ10<>"","Engineering Structural Manager App",IF(AY10<>"","2nd BOQ Pass TI",IF(AX10<>"","2nd BOQ Submit","NY Submit"))))))) -> NY Submit | BF10: 45699 | BG10: 45705 | BH10: JSA No.10/TSA/HSE/02/2025 | BI10: 45699 | BJ10: 45705 | BK10: SWP-HSE-16 | BL10: =+IF(BG10<>"","Approved",IF(BF10<>"","Submit","NY Submit")) -> Approved | BM10: =+IF(BJ10<>"","Approved",IF(BI10<>"","Submit","NY Submit")) -> Approved | BN10: 46059 | BO10: 46059 | BP10: Dismantle Tower | BQ10: EMAPO26-000073 | BR10: 46052 | BS10: =IF(AO10="Drop", "Drop", IF(ISBLANK(AV10), 0, IF(ISBLANK(BR10), DATEDIF(AV10,TODAY(),"d"), DATEDIF(AV10,BR10,"d") ) ) ) -> 18 | BV10: =IF(AO10="Drop", "Drop", IF(ISBLANK(BC10), 0, IF(ISBLANK(BU10), DATEDIF(BC10,TODAY(),"d"), DATEDIF(BC10,BU10,"d") ) ) ) -> 0 | BZ10: Complete | CE10: ID-JT-14679 | CF10: KEMLAYAN SURAKARTA | CG10: -7.57291 | CH10: 110.8208
A11: 6 | B11: CMI | C11: RLC | D11: Nasional | E11: =+_xlfn.CONCAT(G11,"-",B11,"_",C11,"_",_xlfn.XLOOKUP(BP11,Account!M:M,Account!N:N)) -> #NAME? | F11: 45670 | G11: E3300287 | H11: ID-JT-05997 | I11: SINGOSAREN_NEW | J11: 11 | K11: EMA | L11: JAWA TENGAH | M11: Kota Surakarta | N11: Jl. Gatot Subroto No.27 - 28, Kemlayan, Kec. Serengan, Kota Surakarta | O11: -7.57308 | P11: 110.82058 | Q11: 2490.696 | R11: 20 | S11: IOH (hwei) | T11: Rooftop | U11: MT 4 Legs | V11: Dismantle Equipment | Y11: Survey | Z11: 45692 | AA11: 45700 | AB11: =IF(AA11="ds","Submit",IF(AA11="","NY Submit",IF(AA11<TODAY(),"Expired",IFERROR(DATEDIF(TODAY(),AA11,"d"),"")))) -> Expired | AD11: 45695 | AE11: 45698 | AF11: Drop | AO11: =+IF(AM11<>"","ATP App MS",IF(AJ11<>"","Inbound",IF(AH11<>"","Dismantle Perangkat",IF(AF11="Drop","Drop",IF(AE11<>"","Survey Report",IF(AD11<>"","Survey","NY Survey")))))) -> Drop | AP11: Dismantle Equipment by MNO | AQ11: 45999 | AR11: 46034 | AS11: 46006 | AU11: 46034 | AV11: 46034 | AW11: =+IF(AV11<>"","1st BOQ App on ISAAC",IF(AU11<>"","Upload 1st BOQ & BAN Isaac",IF(AT11="DRM","need DRM",IF(AT11<>"","BAN App",IF(AR11<>"","1st BOQ Pass TI",IF(AS11<>"","Engineering Structural Manager App",IF(AQ11<>"","1st BOQ Submit","NY Submit"))))))) -> 1st BOQ App on ISAAC | BD11: =+IF(BC11<>"","2nd BOQ App on ISAAC",IF(BB11<>"","Upload 2nd BOQ & BAN Isaac",IF(BA11="DRM","need DRM",IF(BA11<>"","BAN App",IF(AZ11<>"","Engineering Structural Manager App",IF(AY11<>"","2nd BOQ Pass TI",IF(AX11<>"","2nd BOQ Submit","NY Submit"))))))) -> NY Submit | BF11: 45699 | BG11: 45705 | BH11: JSA No.10/TSA/HSE/02/2025 | BI11: 45699 | BJ11: 45705 | BL11: =+IF(BG11<>"","Approved",IF(BF11<>"","Submit","NY Submit")) -> Approved | BM11: =+IF(BJ11<>"","Approved",IF(BI11<>"","Submit","NY Submit")) -> Approved | BP11: Dismantle Equipment | BQ11: Drop | BS11: =IF(AO11="Drop", "Drop", IF(ISBLANK(AV11), 0, IF(ISBLANK(BR11), DATEDIF(AV11,TODAY(),"d"), DATEDIF(AV11,BR11,"d") ) ) ) -> Drop | BV11: =IF(AO11="Drop", "Drop", IF(ISBLANK(BC11), 0, IF(ISBLANK(BU11), DATEDIF(BC11,TODAY(),"d"), DATEDIF(BC11,BU11,"d") ) ) ) -> Drop | BZ11: Dismantle Equipment by MNO | CE11: ID-JT-14679 | CF11: KEMLAYAN SURAKARTA | CG11: -7.57291 | CH11: 110.8208
A12: 7 | B12: CMI | C12: RLC | D12: Nasional | E12: =+_xlfn.CONCAT(G12,"-",B12,"_",C12,"_",_xlfn.XLOOKUP(BP12,Account!M:M,Account!N:N)) -> #NAME? | F12: 45670 | G12: E3300287 | H12: ID-JT-05997 | I12: SINGOSAREN_NEW | J12: 11 | K12: EMA | L12: JAWA TENGAH | M12: Kota Surakarta | O12: -7.57308 | P12: 110.82058 | Q12: 2490.696 | R12: 20 | S12: IOH (hwei) | T12: Rooftop | U12: MT 4 Legs | V12: Relocation Equipment | Y12: Survey | Z12: 45692 | AA12: 45700 | AB12: =IF(AA12="ds","Submit",IF(AA12="","NY Submit",IF(AA12<TODAY(),"Expired",IFERROR(DATEDIF(TODAY(),AA12,"d"),"")))) -> Expired | AD12: 45695 | AE12: 45698 | AF12: Drop | AO12: =+IF(AM12<>"","ATP App MS",IF(AL12<>"","OA/RFS",IF(AK12<>"","Install",IF(AH12<>"","Dismantle Perangkat",IF(AF12="Drop","Drop",IF(AE12<>"","Survey Report",IF(AD12<>"","Survey","NY Survey"))))))) -> Drop | AW12: =+IF(AV12<>"","1st BOQ App on ISAAC",IF(AU12<>"","Upload 1st BOQ & BAN Isaac",IF(AT12="DRM","need DRM",IF(AT12<>"","BAN App",IF(AR12<>"","1st BOQ Pass TI",IF(AS12<>"","Engineering Structural Manager App",IF(AQ12<>"","1st BOQ Submit","NY Submit"))))))) -> NY Submit | BD12: =+IF(BC12<>"","2nd BOQ App on ISAAC",IF(BB12<>"","Upload 2nd BOQ & BAN Isaac",IF(BA12="DRM","need DRM",IF(BA12<>"","BAN App",IF(AZ12<>"","Engineering Structural Manager App",IF(AY12<>"","2nd BOQ Pass TI",IF(AX12<>"","2nd BOQ Submit","NY Submit"))))))) -> NY Submit | BF12: 45699 | BG12: 45705 | BH12: JSA No.10/TSA/HSE/02/2025 | BI12: 45699 | BJ12: 45705 | BL12: =+IF(BG12<>"","Approved",IF(BF12<>"","Submit","NY Submit")) -> Approved | BM12: =+IF(BJ12<>"","Approved",IF(BI12<>"","Submit","NY Submit")) -> Approved | BP12: Relocation Equipment | BQ12: Drop | BS12: =IF(AO12="Drop", "Drop", IF(ISBLANK(AV12), 0, IF(ISBLANK(BR12), DATEDIF(AV12,TODAY(),"d"), DATEDIF(AV12,BR12,"d") ) ) ) -> Drop | BV12: =IF(AO12="Drop", "Drop", IF(ISBLANK(BC12), 0, IF(ISBLANK(BU12), DATEDIF(BC12,TODAY(),"d"), DATEDIF(BC12,BU12,"d") ) ) ) -> Drop | BZ12: Dismantle Equipment by MNO | CE12: ID-JT-14679 | CF12: KEMLAYAN SURAKARTA | CG12: -7.57291 | CH12: 110.8208
A13: 8 | B13: CMI | C13: RLC | D13: Nasional | E13: =+_xlfn.CONCAT(G13,"-",B13,"_",C13,"_",_xlfn.XLOOKUP(BP13,Account!M:M,Account!N:N)) -> #NAME? | F13: 45670 | G13: R3350400 | H13: ID-JT-02664 | I13: SUMBER LAWANG | J13: 11 | K13: CMI | L13: JAWA TENGAH | M13: Kab. Sragen | O13: -7.32809 | P13: 110.86232 | Q13: 13212.913 | R13: 70 | S13: XL | T13: Greenfield | U13: SST 4 Legs | V13: Dismantle Tower | Y13: Survey | Z13: 45692 | AA13: 45700 | AB13: =IF(AA13="ds","Submit",IF(AA13="","NY Submit",IF(AA13<TODAY(),"Expired",IFERROR(DATEDIF(TODAY(),AA13,"d"),"")))) -> Expired | AD13: 45695 | AE13: 45698 | AG13: 45784 | AI13: 45793 | AN13: 45793 | AO13: =+IF(AN13<>"","BAST",IF(AI13<>"","Dismantle",IF(AG13<>"","RFD App",IF(AF13="Drop","Drop",IF(AE13<>"","Survey Report",IF(AD13<>"","Survey","NY Survey")))))) -> BAST | AQ13: 45775 | AR13: 45796 | AS13: 45796 | AU13: 45800 | AV13: 45799 | AW13: =+IF(AV13<>"","1st BOQ App on ISAAC",IF(AU13<>"","Upload 1st BOQ & BAN Isaac",IF(AT13="DRM","need DRM",IF(AT13<>"","BAN App",IF(AR13<>"","1st BOQ Pass TI",IF(AS13<>"","Engineering Structural Manager App",IF(AQ13<>"","1st BOQ Submit","NY Submit"))))))) -> 1st BOQ App on ISAAC | BD13: =+IF(BC13<>"","2nd BOQ App on ISAAC",IF(BB13<>"","Upload 2nd BOQ & BAN Isaac",IF(BA13="DRM","need DRM",IF(BA13<>"","BAN App",IF(AZ13<>"","Engineering Structural Manager App",IF(AY13<>"","2nd BOQ Pass TI",IF(AX13<>"","2nd BOQ Submit","NY Submit"))))))) -> NY Submit | BF13: 45699 | BG13: 45701 | BH13: JSA No.09/TSA/HSE/02/2025 | BI13: 45699 | BJ13: 45701 | BK13: SWP-HSE-17 | BL13: =+IF(BG13<>"","Approved",IF(BF13<>"","Submit","NY Submit")) -> Approved | BM13: =+IF(BJ13<>"","Approved",IF(BI13<>"","Submit","NY Submit")) -> Approved | BN13: 45793 | BO13: 45799 | BP13: Dismantle Tower | BQ13: CMIPO25-002455 | BR13: 45834 | BS13: =IF(AO13="Drop", "Drop", IF(ISBLANK(AV13), 0, IF(ISBLANK(BR13), DATEDIF(AV13,TODAY(),"d"), DATEDIF(AV13,BR13,"d") ) ) ) -> 35 | BV13: =IF(AO13="Drop", "Drop", IF(ISBLANK(BC13), 0, IF(ISBLANK(BU13), DATEDIF(BC13,TODAY(),"d"), DATEDIF(BC13,BU13,"d") ) ) ) -> 0 | BZ13: Complete | CE13: ID-JT-15609 | CF13: KEBAYAN SRAGEN | CG13: -7.32726 | CH13: 110.86249
A14: 9 | B14: CMI | C14: RLC | D14: Nasional | E14: =+_xlfn.CONCAT(G14,"-",B14,"_",C14,"_",_xlfn.XLOOKUP(BP14,Account!M:M,Account!N:N)) -> #NAME? | F14: 45670 | G14: R3350400 | H14: ID-JT-02664 | I14: SUMBER LAWANG | J14: 11 | K14: CMI | L14: JAWA TENGAH | M14: Kab. Sragen | O14: -7.32809 | P14: 110.86232 | Q14: 13212.913 | R14: 70 | S14: XL | T14: Greenfield | U14: SST 4 Legs | V14: Dismantle Equipment | Y14: Survey | Z14: 45692 | AA14: 45700 | AB14: =IF(AA14="ds","Submit",IF(AA14="","NY Submit",IF(AA14<TODAY(),"Expired",IFERROR(DATEDIF(TODAY(),AA14,"d"),"")))) -> Expired | AD14: 45695 | AE14: 45698 | AH14: 45787 | AM14: 45889 | AN14: 45889 | AO14: =+IF(AM14<>"","ATP App MS",IF(AJ14<>"","Inbound",IF(AH14<>"","Dismantle Perangkat",IF(AF14="Drop","Drop",IF(AE14<>"","Survey Report",IF(AD14<>"","Survey","NY Survey")))))) -> ATP App MS | AQ14: 45775 | AR14: 45796 | AS14: 45796 | AU14: 45800 | AV14: 45799 | AW14: =+IF(AV14<>"","1st BOQ App on ISAAC",IF(AU14<>"","Upload 1st BOQ & BAN Isaac",IF(AT14="DRM","need DRM",IF(AT14<>"","BAN App",IF(AR14<>"","1st BOQ Pass TI",IF(AS14<>"","Engineering Structural Manager App",IF(AQ14<>"","1st BOQ Submit","NY Submit"))))))) -> 1st BOQ App on ISAAC | BD14: =+IF(BC14<>"","2nd BOQ App on ISAAC",IF(BB14<>"","Upload 2nd BOQ & BAN Isaac",IF(BA14="DRM","need DRM",IF(BA14<>"","BAN App",IF(AZ14<>"","Engineering Structural Manager App",IF(AY14<>"","2nd BOQ Pass TI",IF(AX14<>"","2nd BOQ Submit","NY Submit"))))))) -> NY Submit | BF14: 45699 | BG14: 45701 | BH14: JSA No.09/TSA/HSE/02/2025 | BI14: 45699 | BJ14: 45779 | BL14: =+IF(BG14<>"","Approved",IF(BF14<>"","Submit","NY Submit")) -> Approved | BM14: =+IF(BJ14<>"","Approved",IF(BI14<>"","Submit","NY Submit")) -> Approved | BP14: Dismantle Equipment | BQ14: CMIPO25-002456 | BR14: 45834 | BS14: =IF(AO14="Drop", "Drop", IF(ISBLANK(AV14), 0, IF(ISBLANK(BR14), DATEDIF(AV14,TODAY(),"d"), DATEDIF(AV14,BR14,"d") ) ) ) -> 35 | BV14: =IF(AO14="Drop", "Drop", IF(ISBLANK(BC14), 0, IF(ISBLANK(BU14), DATEDIF(BC14,TODAY(),"d"), DATEDIF(BC14,BU14,"d") ) ) ) -> 0 | BZ14: Complete | CE14: ID-JT-15609 | CF14: KEBAYAN SRAGEN | CG14: -7.32726 | CH14: 110.86249
A15: 10 | B15: CMI | C15: RLC | D15: Nasional | E15: =+_xlfn.CONCAT(G15,"-",B15,"_",C15,"_",_xlfn.XLOOKUP(BP15,Account!M:M,Account!N:N)) -> #NAME? | F15: 45670 | G15: R3350400 | H15: ID-JT-02664 | I15: SUMBER LAWANG | J15: 11 | K15: CMI | L15: JAWA TENGAH | M15: Kab. Sragen | O15: -7.32809 | P15: 110.86232 | Q15: 13212.913 | R15: 70 | S15: XL | T15: Greenfield | U15: SST 4 Legs | V15: Relocation Equipment | Y15: Survey | Z15: 45692 | AA15: 45700 | AB15: =IF(AA15="ds","Submit",IF(AA15="","NY Submit",IF(AA15<TODAY(),"Expired",IFERROR(DATEDIF(TODAY(),AA15,"d"),"")))) -> Expired | AD15: 45695 | AE15: 45698 | AK15: 45792 | AL15: 45792 | AM15: 45889 | AN15: 45889 | AO15: =+IF(AM15<>"","ATP App MS",IF(AL15<>"","OA/RFS",IF(AK15<>"","Install",IF(AH15<>"","Dismantle Perangkat",IF(AF15="Drop","Drop",IF(AE15<>"","Survey Report",IF(AD15<>"","Survey","NY Survey"))))))) -> ATP App MS | AQ15: 45775 | AR15: 45796 | AS15: 45796 | AT15: 45807 | AU15: 45800 | AV15: 45799 | AW15: =+IF(AV15<>"","1st BOQ App on ISAAC",IF(AU15<>"","Upload 1st BOQ & BAN Isaac",IF(AT15="DRM","need DRM",IF(AT15<>"","BAN App",IF(AR15<>"","1st BOQ Pass TI",IF(AS15<>"","Engineering Structural Manager App",IF(AQ15<>"","1st BOQ Submit","NY Submit"))))))) -> 1st BOQ App on ISAAC | BD15: =+IF(BC15<>"","2nd BOQ App on ISAAC",IF(BB15<>"","Upload 2nd BOQ & BAN Isaac",IF(BA15="DRM","need DRM",IF(BA15<>"","BAN App",IF(AZ15<>"","Engineering Structural Manager App",IF(AY15<>"","2nd BOQ Pass TI",IF(AX15<>"","2nd BOQ Submit","NY Submit"))))))) -> NY Submit | BF15: 45699 | BG15: 45701 | BH15: JSA No.09/TSA/HSE/02/2025 | BI15: 45699 | BJ15: 45779 | BL15: =+IF(BG15<>"","Approved",IF(BF15<>"","Submit","NY Submit")) -> Approved | BM15: =+IF(BJ15<>"","Approved",IF(BI15<>"","Submit","NY Submit")) -> Approved | BP15: Relocation Equipment | BQ15: CMIPO25-002457 | BR15: 45834 | BS15: =IF(AO15="Drop", "Drop", IF(ISBLANK(AV15), 0, IF(ISBLANK(BR15), DATEDIF(AV15,TODAY(),"d"), DATEDIF(AV15,BR15,"d") ) ) ) -> 35 | BV15: =IF(AO15="Drop", "Drop", IF(ISBLANK(BC15), 0, IF(ISBLANK(BU15), DATEDIF(BC15,TODAY(),"d"), DATEDIF(BC15,BU15,"d") ) ) ) -> 0 | BZ15: Complete | CE15: ID-JT-15609 | CF15: KEBAYAN SRAGEN | CG15: -7.32726 | CH15: 110.86249
A16: 11 | B16: CMI | C16: RLC | D16: Nasional | E16: =+_xlfn.CONCAT(G16,"-",B16,"_",C16,"_",_xlfn.XLOOKUP(BP16,Account!M:M,Account!N:N)) -> #NAME? | F16: 45670 | G16: R3350400 | H16: ID-JT-02664 | I16: SUMBER LAWANG | J16: 11 | K16: CMI | L16: JAWA TENGAH | O16: -7.32809 | P16: 110.86232 | Q16: 13212.913 | R16: 70 | S16: XL | T16: Greenfield | U16: SST 4 Legs | V16: Rebuild_LOS Survey JAW-JT-SGN-1855_LTE_SUMBER_LAWANG to JAW-JT-PWD-1573_SOBO_GEYER | Y16: Survey | Z16: 45692 | AA16: 45700 | AB16: =IF(AA16="ds","Submit",IF(AA16="","NY Submit",IF(AA16<TODAY(),"Expired",IFERROR(DATEDIF(TODAY(),AA16,"d"),"")))) -> Expired | AD16: 45763 | AE16: 45785 | AM16: 45804 | AO16: =+IF(AM16<>"","Survey LOS App",IF(AF16="Drop","Drop",IF(AE16<>"","Survey Report",IF(AD16<>"","Survey","NY Survey")))) -> Survey LOS App | AW16: =+IF(AV16<>"","1st BOQ App on ISAAC",IF(AU16<>"","Upload 1st BOQ & BAN Isaac",IF(AT16="DRM","need DRM",IF(AT16<>"","BAN App",IF(AR16<>"","1st BOQ Pass TI",IF(AS16<>"","Engineering Structural Manager App",IF(AQ16<>"","1st BOQ Submit","NY Submit"))))))) -> NY Submit | BD16: =+IF(BC16<>"","2nd BOQ App on ISAAC",IF(BB16<>"","Upload 2nd BOQ & BAN Isaac",IF(BA16="DRM","need DRM",IF(BA16<>"","BAN App",IF(AZ16<>"","Engineering Structural Manager App",IF(AY16<>"","2nd BOQ Pass TI",IF(AX16<>"","2nd BOQ Submit","NY Submit"))))))) -> NY Submit | BL16: =+IF(BG16<>"","Approved",IF(BF16<>"","Submit","NY Submit")) -> NY Submit | BM16: =+IF(BJ16<>"","Approved",IF(BI16<>"","Submit","NY Submit")) -> NY Submit | BP16: Rebuild_LOS Survey | BQ16: CMIPO25-002162 | BR16: 45807 | BS16: =IF(AO16="Drop", "Drop", IF(ISBLANK(AV16), 0, IF(ISBLANK(BR16), DATEDIF(AV16,TODAY(),"d"), DATEDIF(AV16,BR16,"d") ) ) ) -> 0 | BV16: =IF(AO16="Drop", "Drop", IF(ISBLANK(BC16), 0, IF(ISBLANK(BU16), DATEDIF(BC16,TODAY(),"d"), DATEDIF(BC16,BU16,"d") ) ) ) -> 0 | BZ16: Complete | CE16: JAW-JT-PWD-1573 | CF16: SOBO_GEYER | CG16: -7.32726 | CH16: 110.86249
A17: 12 | B17: CMI | C17: RLC | D17: Nasional | E17: =+_xlfn.CONCAT(G17,"-",B17,"_",C17,"_",_xlfn.XLOOKUP(BP17,Account!M:M,Account!N:N)) -> #NAME? | F17: 45670 | G17: E6400044 | H17: ID-KI-07431 | I17: MARKONI | J17: 18 | K17: EMA | L17: KALIMANTAN TIMUR | M17: Kota Balikpapan | N17: Damai, Kota Balikpapan, Kalimantan Timur | O17: -1.27367 | P17: 116.85109 | Q17: 5076.24 | R17: 25 | S17: IOH (nokia) | T17: Rooftop | U17: MT 4 Legs | V17: Dismantle Tower | Y17: Survey | Z17: 45686 | AA17: 45693 | AB17: =IF(AA17="ds","Submit",IF(AA17="","NY Submit",IF(AA17<TODAY(),"Expired",IFERROR(DATEDIF(TODAY(),AA17,"d"),"")))) -> Expired | AD17: 45698 | AE17: 45701 | AG17: 45877 | AI17: 45901 | AM17: 45925 | AN17: 45925 | AO17: =+IF(AN17<>"","BAST",IF(AI17<>"","Dismantle",IF(AG17<>"","RFD App",IF(AF17="Drop","Drop",IF(AE17<>"","Survey Report",IF(AD17<>"","Survey","NY Survey")))))) -> BAST | AQ17: 45909 | AR17: 45890 | AS17: 45890 | AT17: 45910 | AU17: 45922 | AV17: 45922 | AW17: =+IF(AV17<>"","1st BOQ App on ISAAC",IF(AU17<>"","Upload 1st BOQ & BAN Isaac",IF(AT17="DRM","need DRM",IF(AT17<>"","BAN App",IF(AR17<>"","1st BOQ Pass TI",IF(AS17<>"","Engineering Structural Manager App",IF(AQ17<>"","1st BOQ Submit","NY Submit"))))))) -> 1st BOQ App on ISAAC | BD17: =+IF(BC17<>"","2nd BOQ App on ISAAC",IF(BB17<>"","Upload 2nd BOQ & BAN Isaac",IF(BA17="DRM","need DRM",IF(BA17<>"","BAN App",IF(AZ17<>"","Engineering Structural Manager App",IF(AY17<>"","2nd BOQ Pass TI",IF(AX17<>"","2nd BOQ Submit","NY Submit"))))))) -> NY Submit | BF17: 45701 | BG17: 45705 | BH17: JSA No.13/TSA/HSE/02/2025 | BI17: 45701 | BJ17: 45705 | BK17: SWP-HSE-18 | BL17: =+IF(BG17<>"","Approved",IF(BF17<>"","Submit","NY Submit")) -> Approved | BM17: =+IF(BJ17<>"","Approved",IF(BI17<>"","Submit","NY Submit")) -> Approved | BN17: 45925 | BO17: 45929 | BP17: Dismantle Tower | BQ17: EMAPO25-002009 | BR17: 45938 | BS17: =IF(AO17="Drop", "Drop", IF(ISBLANK(AV17), 0, IF(ISBLANK(BR17), DATEDIF(AV17,TODAY(),"d"), DATEDIF(AV17,BR17,"d") ) ) ) -> 16 | BV17: =IF(AO17="Drop", "Drop", IF(ISBLANK(BC17), 0, IF(ISBLANK(BU17), DATEDIF(BC17,TODAY(),"d"), DATEDIF(BC17,BU17,"d") ) ) ) -> 0 | BZ17: Complete | CE17: ID-KI-15616 | CF17: DAMAI BALIKPAPAN | CG17: -1.27076 | CH17: 116.85149
A18: 13 | B18: CMI | C18: RLC | D18: Nasional | E18: =+_xlfn.CONCAT(G18,"-",B18,"_",C18,"_",_xlfn.XLOOKUP(BP18,Account!M:M,Account!N:N)) -> #NAME? | F18: 45670 | G18: E6400044 | H18: ID-KI-07431 | I18: MARKONI | J18: 18 | K18: EMA | L18: KALIMANTAN TIMUR | M18: Kota Balikpapan | N18: Damai, Kota Balikpapan, Kalimantan Timur | O18: -1.27367 | P18: 116.85109 | Q18: 5076.24 | R18: 25 | S18: IOH (nokia) | T18: Rooftop | U18: MT 4 Legs | V18: Dismantle Equipment | Y18: Survey | Z18: 45686 | AA18: 45693 | AB18: =IF(AA18="ds","Submit",IF(AA18="","NY Submit",IF(AA18<TODAY(),"Expired",IFERROR(DATEDIF(TODAY(),AA18,"d"),"")))) -> Expired | AD18: 45698 | AE18: 45701 | AG18: 45877 | AH18: 45880 | AM18: 46078 | AN18: 46078 | AO18: =+IF(AM18<>"","ATP App MS",IF(AJ18<>"","Inbound",IF(AH18<>"","Dismantle Perangkat",IF(AF18="Drop","Drop",IF(AE18<>"","Survey Report",IF(AD18<>"","Survey","NY Survey")))))) -> ATP App MS | AQ18: 45909 | AR18: 45890 | AS18: 45890 | AU18: 45922 | AV18: 45922 | AW18: =+IF(AV18<>"","1st BOQ App on ISAAC",IF(AU18<>"","Upload 1st BOQ & BAN Isaac",IF(AT18="DRM","need DRM",IF(AT18<>"","BAN App",IF(AR18<>"","1st BOQ Pass TI",IF(AS18<>"","Engineering Structural Manager App",IF(AQ18<>"","1st BOQ Submit","NY Submit"))))))) -> 1st BOQ App on ISAAC | BD18: =+IF(BC18<>"","2nd BOQ App on ISAAC",IF(BB18<>"","Upload 2nd BOQ & BAN Isaac",IF(BA18="DRM","need DRM",IF(BA18<>"","BAN App",IF(AZ18<>"","Engineering Structural Manager App",IF(AY18<>"","2nd BOQ Pass TI",IF(AX18<>"","2nd BOQ Submit","NY Submit"))))))) -> NY Submit | BF18: 45701 | BG18: 45705 | BH18: JSA No.13/TSA/HSE/02/2025 | BI18: 45701 | BJ18: 45705 | BL18: =+IF(BG18<>"","Approved",IF(BF18<>"","Submit","NY Submit")) -> Approved | BM18: =+IF(BJ18<>"","Approved",IF(BI18<>"","Submit","NY Submit")) -> Approved | BP18: Dismantle Equipment | BQ18: EMAPO25-002010 | BR18: 45938 | BS18: =IF(AO18="Drop", "Drop", IF(ISBLANK(AV18), 0, IF(ISBLANK(BR18), DATEDIF(AV18,TODAY(),"d"), DATEDIF(AV18,BR18,"d") ) ) ) -> 16 | BV18: =IF(AO18="Drop", "Drop", IF(ISBLANK(BC18), 0, IF(ISBLANK(BU18), DATEDIF(BC18,TODAY(),"d"), DATEDIF(BC18,BU18,"d") ) ) ) -> 0 | BZ18: Complete | CA18: CMI Project | CB18: CMI
A19: 14 | B19: CMI | C19: RLC | D19: Nasional | E19: =+_xlfn.CONCAT(G19,"-",B19,"_",C19,"_",_xlfn.XLOOKUP(BP19,Account!M:M,Account!N:N)) -> #NAME? | F19: 45670 | G19: E6400044 | H19: ID-KI-07431 | I19: MARKONI | J19: 18 | K19: EMA | L19: KALIMANTAN TIMUR | M19: Kota Balikpapan | N19: Damai, Kota Balikpapan, Kalimantan Timur | O19: -1.27367 | P19: 116.85109 | Q19: 5076.24 | R19: 25 | S19: IOH (nokia) | T19: Rooftop | U19: MT 4 Legs | V19: Relocation Equipment | W19: Abe Rizal | Y19: Survey | Z19: 45686 | AA19: 45693 | AB19: =IF(AA19="ds","Submit",IF(AA19="","NY Submit",IF(AA19<TODAY(),"Expired",IFERROR(DATEDIF(TODAY(),AA19,"d"),"")))) -> Expired | AD19: 45698 | AE19: 45701 | AG19: 45877 | AL19: 45965 | AM19: 46078 | AN19: 46078 | AO19: =+IF(AM19<>"","ATP App MS",IF(AL19<>"","OA/RFS",IF(AK19<>"","Install",IF(AH19<>"","Dismantle Perangkat",IF(AF19="Drop","Drop",IF(AE19<>"","Survey Report",IF(AD19<>"","Survey","NY Survey"))))))) -> ATP App MS | AP19: 11.11.25 ATP MS done | AQ19: 45909 | AR19: 45890 | AS19: 45890 | AT19: 45910 | AU19: 45922 | AV19: 45922 | AW19: =+IF(AV19<>"","1st BOQ App on ISAAC",IF(AU19<>"","Upload 1st BOQ & BAN Isaac",IF(AT19="DRM","need DRM",IF(AT19<>"","BAN App",IF(AR19<>"","1st BOQ Pass TI",IF(AS19<>"","Engineering Structural Manager App",IF(AQ19<>"","1st BOQ Submit","NY Submit"))))))) -> 1st BOQ App on ISAAC | BD19: =+IF(BC19<>"","2nd BOQ App on ISAAC",IF(BB19<>"","Upload 2nd BOQ & BAN Isaac",IF(BA19="DRM","need DRM",IF(BA19<>"","BAN App",IF(AZ19<>"","Engineering Structural Manager App",IF(AY19<>"","2nd BOQ Pass TI",IF(AX19<>"","2nd BOQ Submit","NY Submit"))))))) -> NY Submit | BF19: 45701 | BG19: 45705 | BH19: JSA No.13/TSA/HSE/02/2025 | BI19: 45701 | BJ19: 45705 | BL19: =+IF(BG19<>"","Approved",IF(BF19<>"","Submit","NY Submit")) -> Approved | BM19: =+IF(BJ19<>"","Approved",IF(BI19<>"","Submit","NY Submit")) -> Approved | BP19: Relocation Equipment | BQ19: EMAPO25-002011 | BR19: 45938 | BS19: =IF(AO19="Drop", "Drop", IF(ISBLANK(AV19), 0, IF(ISBLANK(BR19), DATEDIF(AV19,TODAY(),"d"), DATEDIF(AV19,BR19,"d") ) ) ) -> 16 | BV19: =IF(AO19="Drop", "Drop", IF(ISBLANK(BC19), 0, IF(ISBLANK(BU19), DATEDIF(BC19,TODAY(),"d"), DATEDIF(BC19,BU19,"d") ) ) ) -> 0 | BZ19: Complete | CA19: CMI Project | CB19: CMI | CE19: ID-KI-15616 | CF19: DAMAI BALIKPAPAN
A20: 15 | B20: CMI | C20: RLC | D20: Nasional | E20: =+_xlfn.CONCAT(G20,"-",B20,"_",C20,"_",_xlfn.XLOOKUP(BP20,Account!M:M,Account!N:N)) -> #NAME? | F20: 45666 | G20: R5100123 | H20: ID-BA-09703 | I20: PALAPA BARAT | J20: 16 | K20: CMI | L20: BALI | M20: Kab. Badung | O20: -8.6806 | P20: 115.16718 | R20: 12 | S20: IOH | T20: Rooftop | U20: Pole | V20: Dismantle Tower | W20: Hoirul Anam | X20: +62 813-3368-2903 | Y20: Urgent Site | AB20: =IF(AA20="ds","Submit",IF(AA20="","NY Submit",IF(AA20<TODAY(),"Expired",IFERROR(DATEDIF(TODAY(),AA20,"d"),"")))) -> NY Submit | AD20: 45655 | AE20: 45680 | AG20: 45673 | AI20: 45673 | AN20: 45674 | AO20: =+IF(AN20<>"","BAST",IF(AI20<>"","Dismantle",IF(AG20<>"","RFD App",IF(AF20="Drop","Drop",IF(AE20<>"","Survey Report",IF(AD20<>"","Survey","NY Survey")))))) -> BAST | AQ20: 45677 | AR20: 45677 | AW20: =+IF(AV20<>"","1st BOQ App on ISAAC",IF(AU20<>"","Upload 1st BOQ & BAN Isaac",IF(AT20="DRM","need DRM",IF(AT20<>"","BAN App",IF(AR20<>"","1st BOQ Pass TI",IF(AS20<>"","Engineering Structural Manager App",IF(AQ20<>"","1st BOQ Submit","NY Submit"))))))) -> 1st BOQ Pass TI | BD20: =+IF(BC20<>"","2nd BOQ App on ISAAC",IF(BB20<>"","Upload 2nd BOQ & BAN Isaac",IF(BA20="DRM","need DRM",IF(BA20<>"","BAN App",IF(AZ20<>"","Engineering Structural Manager App",IF(AY20<>"","2nd BOQ Pass TI",IF(AX20<>"","2nd BOQ Submit","NY Submit"))))))) -> NY Submit | BF20: 45677 | BG20: 45680 | BH20: JSA No.04/TSA/HSE/01/2025 | BI20: 45677 | BJ20: 45680 | BK20: SWP-HSE-01 | BL20: =+IF(BG20<>"","Approved",IF(BF20<>"","Submit","NY Submit")) -> Approved | BM20: =+IF(BJ20<>"","Approved",IF(BI20<>"","Submit","NY Submit")) -> Approved | BN20: 45677 | BO20: 45693 | BP20: Dismantle Tower | BQ20: CMIPO25-000681 | BR20: 45699 | BS20: =IF(AO20="Drop", "Drop", IF(ISBLANK(AV20), 0, IF(ISBLANK(BR20), DATEDIF(AV20,TODAY(),"d"), DATEDIF(AV20,BR20,"d") ) ) ) -> 0 | BV20: =IF(AO20="Drop", "Drop", IF(ISBLANK(BC20), 0, IF(ISBLANK(BU20), DATEDIF(BC20,TODAY(),"d"), DATEDIF(BC20,BU20,"d") ) ) ) -> 0 | BZ20: Complete | CJ20: XLWO-20250110-0000009
A21: 16 | B21: CMI | C21: RLC | D21: Nasional | E21: =+_xlfn.CONCAT(G21,"-",B21,"_",C21,"_",_xlfn.XLOOKUP(BP21,Account!M:M,Account!N:N)) -> #NAME? | F21: 45666 | G21: R5100123 | H21: ID-BA-09703 | I21: PALAPA BARAT | J21: 16 | K21: CMI | L21: BALI | M21: Kab. Badung | O21: -8.6806 | P21: 115.16718 | R21: 12 | S21: IOH | T21: Rooftop | U21: Pole | V21: Dismantle Equipment | Y21: Urgent Site | AB21: =IF(AA21="ds","Submit",IF(AA21="","NY Submit",IF(AA21<TODAY(),"Expired",IFERROR(DATEDIF(TODAY(),AA21,"d"),"")))) -> NY Submit | AD21: 45655 | AE21: 45680 | AH21: 45671 | AM21: 45674 | AO21: =+IF(AM21<>"","ATP App MS",IF(AJ21<>"","Inbound",IF(AH21<>"","Dismantle Perangkat",IF(AF21="Drop","Drop",IF(AE21<>"","Survey Report",IF(AD21<>"","Survey","NY Survey")))))) -> ATP App MS | AQ21: 45677 | AR21: 45677 | AW21: =+IF(AV21<>"","1st BOQ App on ISAAC",IF(AU21<>"","Upload 1st BOQ & BAN Isaac",IF(AT21="DRM","need DRM",IF(AT21<>"","BAN App",IF(AR21<>"","1st BOQ Pass TI",IF(AS21<>"","Engineering Structural Manager App",IF(AQ21<>"","1st BOQ Submit","NY Submit"))))))) -> 1st BOQ Pass TI | BD21: =+IF(BC21<>"","2nd BOQ App on ISAAC",IF(BB21<>"","Upload 2nd BOQ & BAN Isaac",IF(BA21="DRM","need DRM",IF(BA21<>"","BAN App",IF(AZ21<>"","Engineering Structural Manager App",IF(AY21<>"","2nd BOQ Pass TI",IF(AX21<>"","2nd BOQ Submit","NY Submit"))))))) -> NY Submit | BF21: 45677 | BG21: 45680 | BH21: JSA No.04/TSA/HSE/01/2025 | BI21: 45677 | BJ21: 45667 | BL21: =+IF(BG21<>"","Approved",IF(BF21<>"","Submit","NY Submit")) -> Approved | BM21: =+IF(BJ21<>"","Approved",IF(BI21<>"","Submit","NY Submit")) -> Approved | BN21: 45677 | BO21: 45693 | BP21: Dismantle Equipment | BQ21: CMIPO25-000682 | BR21: 45699 | BS21: =IF(AO21="Drop", "Drop", IF(ISBLANK(AV21), 0, IF(ISBLANK(BR21), DATEDIF(AV21,TODAY(),"d"), DATEDIF(AV21,BR21,"d") ) ) ) -> 0 | BV21: =IF(AO21="Drop", "Drop", IF(ISBLANK(BC21), 0, IF(ISBLANK(BU21), DATEDIF(BC21,TODAY(),"d"), DATEDIF(BC21,BU21,"d") ) ) ) -> 0 | BZ21: Complete
A22: 17 | B22: CMI | C22: RLC | D22: Nasional | E22: =+_xlfn.CONCAT(G22,"-",B22,"_",C22,"_",_xlfn.XLOOKUP(BP22,Account!M:M,Account!N:N)) -> #NAME? | F22: 45666 | G22: R5100123 | H22: ID-BA-09703 | I22: PALAPA BARAT | J22: 16 | K22: CMI | L22: BALI | M22: Kab. Badung | O22: -8.6806 | P22: 115.16718 | R22: 12 | S22: IOH | T22: Rooftop | U22: Pole | V22: Relocation Equipment | W22: Prayudi | Y22: Urgent Site | AB22: =IF(AA22="ds","Submit",IF(AA22="","NY Submit",IF(AA22<TODAY(),"Expired",IFERROR(DATEDIF(TODAY(),AA22,"d"),"")))) -> NY Submit | AD22: 45655 | AE22: 45680 | AK22: 45672 | AL22: 45672 | AM22: 45674 | AO22: =+IF(AM22<>"","ATP App MS",IF(AL22<>"","OA/RFS",IF(AK22<>"","Install",IF(AH22<>"","Dismantle Perangkat",IF(AF22="Drop","Drop",IF(AE22<>"","Survey Report",IF(AD22<>"","Survey","NY Survey"))))))) -> ATP App MS | AQ22: 45677 | AR22: 45677 | AW22: =+IF(AV22<>"","1st BOQ App on ISAAC",IF(AU22<>"","Upload 1st BOQ & BAN Isaac",IF(AT22="DRM","need DRM",IF(AT22<>"","BAN App",IF(AR22<>"","1st BOQ Pass TI",IF(AS22<>"","Engineering Structural Manager App",IF(AQ22<>"","1st BOQ Submit","NY Submit"))))))) -> 1st BOQ Pass TI | BD22: =+IF(BC22<>"","2nd BOQ App on ISAAC",IF(BB22<>"","Upload 2nd BOQ & BAN Isaac",IF(BA22="DRM","need DRM",IF(BA22<>"","BAN App",IF(AZ22<>"","Engineering Structural Manager App",IF(AY22<>"","2nd BOQ Pass TI",IF(AX22<>"","2nd BOQ Submit","NY Submit"))))))) -> NY Submit | BF22: 45677 | BG22: 45680 | BH22: JSA No.04/TSA/HSE/01/2025 | BI22: 45677 | BJ22: 45667 | BL22: =+IF(BG22<>"","Approved",IF(BF22<>"","Submit","NY Submit")) -> Approved | BM22: =+IF(BJ22<>"","Approved",IF(BI22<>"","Submit","NY Submit")) -> Approved | BN22: 45677 | BO22: 45693 | BP22: Relocation Equipment | BQ22: CMIPO25-000683 | BR22: 45699 | BS22: =IF(AO22="Drop", "Drop", IF(ISBLANK(AV22), 0, IF(ISBLANK(BR22), DATEDIF(AV22,TODAY(),"d"), DATEDIF(AV22,BR22,"d") ) ) ) -> 0 | BV22: =IF(AO22="Drop", "Drop", IF(ISBLANK(BC22), 0, IF(ISBLANK(BU22), DATEDIF(BC22,TODAY(),"d"), DATEDIF(BC22,BU22,"d") ) ) ) -> 0 | BZ22: Complete
A23: 18 | B23: CMI | C23: RLC | D23: Nasional | E23: =+_xlfn.CONCAT(G23,"-",B23,"_",C23,"_",_xlfn.XLOOKUP(BP23,Account!M:M,Account!N:N)) -> #NAME? | F23: 45671 | G23: E3300170 | H23: ID-JT-05881 | I23: WATUGONG | J23: 11 | K23: EMA | L23: JAWA TENGAH | M23: Kota Semarang | N23: Banyumanik, Kec. Banyumanik, Kota Semarang, Jawa Tengah | O23: -7.0804 | P23: 110.412 | Q23: 1364.403 | T23: Rooftop | U23: Pole | V23: Dismantle Tower | Y23: Survey | Z23: 45701 | AA23: 45708 | AB23: =IF(AA23="ds","Submit",IF(AA23="","NY Submit",IF(AA23<TODAY(),"Expired",IFERROR(DATEDIF(TODAY(),AA23,"d"),"")))) -> Expired | AD23: 45672 | AE23: 45686 | AI23: 46157 | AM23: 46157 | AN23: 46157 | AO23: =+IF(AN23<>"","BAST",IF(AI23<>"","Dismantle",IF(AG23<>"","RFD App",IF(AF23="Drop","Drop",IF(AE23<>"","Survey Report",IF(AD23<>"","Survey","NY Survey")))))) -> BAST | AP23: 14.05.26 Start dismantle | AQ23: 45786 | AR23: 45796 | AS23: 45788 | AU23: 45967 | AV23: 45967 | AW23: =+IF(AV23<>"","1st BOQ App on ISAAC",IF(AU23<>"","Upload 1st BOQ & BAN Isaac",IF(AT23="DRM","need DRM",IF(AT23<>"","BAN App",IF(AR23<>"","1st BOQ Pass TI",IF(AS23<>"","Engineering Structural Manager App",IF(AQ23<>"","1st BOQ Submit","NY Submit"))))))) -> 1st BOQ App on ISAAC | AX23: 46162 | BC23: 46168 | BD23: =+IF(BC23<>"","2nd BOQ App on ISAAC",IF(BB23<>"","Upload 2nd BOQ & BAN Isaac",IF(BA23="DRM","need DRM",IF(BA23<>"","BAN App",IF(AZ23<>"","Engineering Structural Manager App",IF(AY23<>"","2nd BOQ Pass TI",IF(AX23<>"","2nd BOQ Submit","NY Submit"))))))) -> 2nd BOQ App on ISAAC | BE23: 06.11.25 BOQ survey app | BF23: 45706 | BG23: 45706 | BH23: JSA No.15/TSA/HSE/02/2025 | BI23: 45706 | BJ23: 45706 | BK23: SWP-HSE-22 | BL23: =+IF(BG23<>"","Approved",IF(BF23<>"","Submit","NY Submit")) -> Approved | BM23: =+IF(BJ23<>"","Approved",IF(BI23<>"","Submit","NY Submit")) -> Approved | BP23: Dismantle Tower | BQ23: EMAPO25-002203 | BR23: 45974 | BS23: =IF(AO23="Drop", "Drop", IF(ISBLANK(AV23), 0, IF(ISBLANK(BR23), DATEDIF(AV23,TODAY(),"d"), DATEDIF(AV23,BR23,"d") ) ) ) -> 7 | BT23: EMAPO26-000856 | BU23: 46206 | BV23: =IF(AO23="Drop", "Drop", IF(ISBLANK(BC23), 0, IF(ISBLANK(BU23), DATEDIF(BC23,TODAY(),"d"), DATEDIF(BC23,BU23,"d") ) ) ) -> 38 | BZ23: Complete | CA23: CMI Project
A24: 19 | B24: CMI | C24: RLC | D24: Nasional | E24: =+_xlfn.CONCAT(G24,"-",B24,"_",C24,"_",_xlfn.XLOOKUP(BP24,Account!M:M,Account!N:N)) -> #NAME? | F24: 45681 | G24: R5100015 | H24: ID-BA-00032 | I24: MERCURE KUTA | J24: 16 | K24: CMI | L24: BALI | M24: Kab. Badung | N24: MERCURE HOTEL,JL. PANTAI KUTA BR. PANDA MAS.KUTA,BADUNG,BALI,80361 | O24: -8.72108 | P24: 115.1704 | R24: 9 | T24: Rooftop | U24: Pole | V24: Dismantle Tower | Y24: Dismantle | Z24: 45700 | AA24: 45707 | AB24: =IF(AA24="ds","Submit",IF(AA24="","NY Submit",IF(AA24<TODAY(),"Expired",IFERROR(DATEDIF(TODAY(),AA24,"d"),"")))) -> Expired | AD24: 45691 | AE24: 45707 | AG24: 45723 | AI24: 45724 | AN24: 45724 | AO24: =+IF(AN24<>"","BAST",IF(AI24<>"","Dismantle",IF(AG24<>"","RFD App",IF(AF24="Drop","Drop",IF(AE24<>"","Survey Report",IF(AD24<>"","Survey","NY Survey")))))) -> BAST | AQ24: 45691 | AR24: 45691 | AS24: 45691 | AU24: 45721 | AV24: 45722 | AW24: =+IF(AV24<>"","1st BOQ App on ISAAC",IF(AU24<>"","Upload 1st BOQ & BAN Isaac",IF(AT24="DRM","need DRM",IF(AT24<>"","BAN App",IF(AR24<>"","1st BOQ Pass TI",IF(AS24<>"","Engineering Structural Manager App",IF(AQ24<>"","1st BOQ Submit","NY Submit"))))))) -> 1st BOQ App on ISAAC | BD24: =+IF(BC24<>"","2nd BOQ App on ISAAC",IF(BB24<>"","Upload 2nd BOQ & BAN Isaac",IF(BA24="DRM","need DRM",IF(BA24<>"","BAN App",IF(AZ24<>"","Engineering Structural Manager App",IF(AY24<>"","2nd BOQ Pass TI",IF(AX24<>"","2nd BOQ Submit","NY Submit"))))))) -> NY Submit | BF24: 45691 | BG24: 45708 | BH24: JSA No.04/TSA/HSE/02/2025 | BI24: 45691 | BJ24: 45708 | BK24: SWP-HSE-11 | BL24: =+IF(BG24<>"","Approved",IF(BF24<>"","Submit","NY Submit")) -> Approved | BM24: =+IF(BJ24<>"","Approved",IF(BI24<>"","Submit","NY Submit")) -> Approved | BN24: 45724 | BO24: 45726 | BP24: Dismantle Tower | BQ24: CMIPO25-001383 | BR24: 45737 | BS24: =IF(AO24="Drop", "Drop", IF(ISBLANK(AV24), 0, IF(ISBLANK(BR24), DATEDIF(AV24,TODAY(),"d"), DATEDIF(AV24,BR24,"d") ) ) ) -> 15 | BV24: =IF(AO24="Drop", "Drop", IF(ISBLANK(BC24), 0, IF(ISBLANK(BU24), DATEDIF(BC24,TODAY(),"d"), DATEDIF(BC24,BU24,"d") ) ) ) -> 0 | BZ24: Complete
A25: 20 | B25: CMI | C25: RLC | D25: Nasional | E25: =+_xlfn.CONCAT(G25,"-",B25,"_",C25,"_",_xlfn.XLOOKUP(BP25,Account!M:M,Account!N:N)) -> #NAME? | F25: 45681 | G25: R5100017 | H25: ID-BA-00042 | I25: BELO-PETANG | J25: 16 | K25: CMI | L25: BALI | M25: Kab. Badung | N25: HOUSE,JL. RAYA KINTAMANI PLAGA BR. BELO DESA BELO KEC. PETANG KAB. BADUNG.DESA BELO KEC. PETANG,BADUNG,BALI,80353 | O25: -8.27693 | P25: 115.23985 | R25: 12 | T25: Rooftop | U25: Pole | V25: Dismantle Tower | Y25: Dismantle | Z25: 45693 | AA25: 45700 | AB25: =IF(AA25="ds","Submit",IF(AA25="","NY Submit",IF(AA25<TODAY(),"Expired",IFERROR(DATEDIF(TODAY(),AA25,"d"),"")))) -> Expired | AD25: 45691 | AE25: 45707 | AG25: 45727 | AI25: 45729 | AN25: 45730 | AO25: =+IF(AN25<>"","BAST",IF(AI25<>"","Dismantle",IF(AG25<>"","RFD App",IF(AF25="Drop","Drop",IF(AE25<>"","Survey Report",IF(AD25<>"","Survey","NY Survey")))))) -> BAST | AQ25: 45691 | AR25: 45691 | AS25: 45691 | AU25: 45721 | AV25: 45722 | AW25: =+IF(AV25<>"","1st BOQ App on ISAAC",IF(AU25<>"","Upload 1st BOQ & BAN Isaac",IF(AT25="DRM","need DRM",IF(AT25<>"","BAN App",IF(AR25<>"","1st BOQ Pass TI",IF(AS25<>"","Engineering Structural Manager App",IF(AQ25<>"","1st BOQ Submit","NY Submit"))))))) -> 1st BOQ App on ISAAC | BD25: =+IF(BC25<>"","2nd BOQ App on ISAAC",IF(BB25<>"","Upload 2nd BOQ & BAN Isaac",IF(BA25="DRM","need DRM",IF(BA25<>"","BAN App",IF(AZ25<>"","Engineering Structural Manager App",IF(AY25<>"","2nd BOQ Pass TI",IF(AX25<>"","2nd BOQ Submit","NY Submit"))))))) -> NY Submit | BF25: 45691 | BG25: 45708 | BH25: JSA No.05/TSA/HSE/02/2025 | BI25: 45691 | BJ25: 45708 | BK25: SWP-HSE-12 | BL25: =+IF(BG25<>"","Approved",IF(BF25<>"","Submit","NY Submit")) -> Approved | BM25: =+IF(BJ25<>"","Approved",IF(BI25<>"","Submit","NY Submit")) -> Approved | BN25: 45730 | BO25: 45737 | BP25: Dismantle Tower | BQ25: CMIPO25-001384 | BR25: 45737 | BS25: =IF(AO25="Drop", "Drop", IF(ISBLANK(AV25), 0, IF(ISBLANK(BR25), DATEDIF(AV25,TODAY(),"d"), DATEDIF(AV25,BR25,"d") ) ) ) -> 15 | BV25: =IF(AO25="Drop", "Drop", IF(ISBLANK(BC25), 0, IF(ISBLANK(BU25), DATEDIF(BC25,TODAY(),"d"), DATEDIF(BC25,BU25,"d") ) ) ) -> 0 | BZ25: Complete
A26: 21 | B26: CMI | C26: RLC | D26: Nasional | E26: =+_xlfn.CONCAT(G26,"-",B26,"_",C26,"_",_xlfn.XLOOKUP(BP26,Account!M:M,Account!N:N)) -> #NAME? | F26: 45681 | G26: R5100005 | H26: ID-BA-00178 | I26: MENGWI / BUDUK | J26: 16 | K26: CMI | L26: BALI | M26: Kab. Badung | N26: BANJAR TENGAH DESA BUDUK KEC. MENGUI BADUNG BALI | O26: -8.606059 | P26: 115.16469 | R26: 6 | T26: Rooftop | U26: Pole | V26: Dismantle Tower | W26: Utut Wahyu Eka | X26: 8112345378 | Y26: Dismantle | Z26: 45693 | AA26: 45700 | AB26: =IF(AA26="ds","Submit",IF(AA26="","NY Submit",IF(AA26<TODAY(),"Expired",IFERROR(DATEDIF(TODAY(),AA26,"d"),"")))) -> Expired | AD26: 45686 | AE26: 45689 | AG26: 45692 | AI26: 45698 | AN26: 45707 | AO26: =+IF(AN26<>"","BAST",IF(AI26<>"","Dismantle",IF(AG26<>"","RFD App",IF(AF26="Drop","Drop",IF(AE26<>"","Survey Report",IF(AD26<>"","Survey","NY Survey")))))) -> BAST | AQ26: 45691 | AR26: 45691 | AS26: 45691 | AU26: 45692 | AV26: 45701 | AW26: =+IF(AV26<>"","1st BOQ App on ISAAC",IF(AU26<>"","Upload 1st BOQ & BAN Isaac",IF(AT26="DRM","need DRM",IF(AT26<>"","BAN App",IF(AR26<>"","1st BOQ Pass TI",IF(AS26<>"","Engineering Structural Manager App",IF(AQ26<>"","1st BOQ Submit","NY Submit"))))))) -> 1st BOQ App on ISAAC | BD26: =+IF(BC26<>"","2nd BOQ App on ISAAC",IF(BB26<>"","Upload 2nd BOQ & BAN Isaac",IF(BA26="DRM","need DRM",IF(BA26<>"","BAN App",IF(AZ26<>"","Engineering Structural Manager App",IF(AY26<>"","2nd BOQ Pass TI",IF(AX26<>"","2nd BOQ Submit","NY Submit"))))))) -> NY Submit | BF26: 45689 | BG26: 45691 | BH26: JSA No.01/TSA/HSE/02/2025 | BI26: 45689 | BJ26: 45691 | BK26: SWP-HSE-08 | BL26: =+IF(BG26<>"","Approved",IF(BF26<>"","Submit","NY Submit")) -> Approved | BM26: =+IF(BJ26<>"","Approved",IF(BI26<>"","Submit","NY Submit")) -> Approved | BN26: 45705 | BO26: 45722 | BP26: Dismantle Tower | BQ26: CMIPO25-001181 | BR26: 45730 | BS26: =IF(AO26="Drop", "Drop", IF(ISBLANK(AV26), 0, IF(ISBLANK(BR26), DATEDIF(AV26,TODAY(),"d"), DATEDIF(AV26,BR26,"d") ) ) ) -> 29 | BV26: =IF(AO26="Drop", "Drop", IF(ISBLANK(BC26), 0, IF(ISBLANK(BU26), DATEDIF(BC26,TODAY(),"d"), DATEDIF(BC26,BU26,"d") ) ) ) -> 0 | BZ26: Complete
A27: 22 | B27: CMI | C27: RLC | D27: Nasional | E27: =+_xlfn.CONCAT(G27,"-",B27,"_",C27,"_",_xlfn.XLOOKUP(BP27,Account!M:M,Account!N:N)) -> #NAME? | F27: 45681 | G27: E1200243 | H27: ID-SB-03997 | I27: RD TO PAINAN/BUKIT LANGKISAU | J27: 3 | K27: EMA | L27: SUMATERA BARAT | M27: Kab. Pesisir Selatan | N27: JL. RAYA PANTAI CAROCOK PAINAN KEC. 4 JURAI | O27: -1.34411 | P27: 100.57142 | Q27: 22120.78 | R27: 55 | T27: Greenfield | U27: SST 4 Legs | V27: Dismantle Tower | W27: Ismail | X27: 82168704736 | Y27: Dismantle | Z27: 45700 | AA27: 45707 | AB27: =IF(AA27="ds","Submit",IF(AA27="","NY Submit",IF(AA27<TODAY(),"Expired",IFERROR(DATEDIF(TODAY(),AA27,"d"),"")))) -> Expired | AD27: 45684 | AE27: 45687 | AG27: 45699 | AI27: 45705 | AN27: 45712 | AO27: =+IF(AN27<>"","BAST",IF(AI27<>"","Dismantle",IF(AG27<>"","RFD App",IF(AF27="Drop","Drop",IF(AE27<>"","Survey Report",IF(AD27<>"","Survey","NY Survey")))))) -> BAST | AQ27: 45689 | AR27: 45689 | AS27: 45714 | AT27: 45714 | AU27: 45721 | AV27: 45721 | AW27: =+IF(AV27<>"","1st BOQ App on ISAAC",IF(AU27<>"","Upload 1st BOQ & BAN Isaac",IF(AT27="DRM","need DRM",IF(AT27<>"","BAN App",IF(AR27<>"","1st BOQ Pass TI",IF(AS27<>"","Engineering Structural Manager App",IF(AQ27<>"","1st BOQ Submit","NY Submit"))))))) -> 1st BOQ App on ISAAC | BD27: =+IF(BC27<>"","2nd BOQ App on ISAAC",IF(BB27<>"","Upload 2nd BOQ & BAN Isaac",IF(BA27="DRM","need DRM",IF(BA27<>"","BAN App",IF(AZ27<>"","Engineering Structural Manager App",IF(AY27<>"","2nd BOQ Pass TI",IF(AX27<>"","2nd BOQ Submit","NY Submit"))))))) -> NY Submit | BF27: 45686 | BG27: 45687 | BH27: JSA No.01/TSA/HSE/01/2025 | BI27: 45686 | BJ27: 45687 | BK27: SWP-HSE-04 | BL27: =+IF(BG27<>"","Approved",IF(BF27<>"","Submit","NY Submit")) -> Approved | BM27: =+IF(BJ27<>"","Approved",IF(BI27<>"","Submit","NY Submit")) -> Approved | BN27: 45710 | BO27: 45712 | BP27: Dismantle Tower | BQ27: EMAPO25-000459 | BR27: 45736 | BS27: =IF(AO27="Drop", "Drop", IF(ISBLANK(AV27), 0, IF(ISBLANK(BR27), DATEDIF(AV27,TODAY(),"d"), DATEDIF(AV27,BR27,"d") ) ) ) -> 15 | BV27: =IF(AO27="Drop", "Drop", IF(ISBLANK(BC27), 0, IF(ISBLANK(BU27), DATEDIF(BC27,TODAY(),"d"), DATEDIF(BC27,BU27,"d") ) ) ) -> 0 | BZ27: Complete
A28: 23 | B28: CMI | C28: RLC | D28: Nasional | E28: =+_xlfn.CONCAT(G28,"-",B28,"_",C28,"_",_xlfn.XLOOKUP(BP28,Account!M:M,Account!N:N)) -> #NAME? | F28: 45681 | G28: E1200260 | H28: ID-SB-04014 | I28: SURIAN | J28: 3 | K28: EMA | L28: SUMATERA BARAT | M28: Kab. Solok | N28: JL. PASAR SURIAN, JORONG PASAR, KEC. PANTAI CERMIN, KAB. SOLOK | O28: -1.25231 | P28: 100.88605 | Q28: 22120.78 | R28: 70 | T28: Greenfield | U28: SST 4 Legs | V28: Dismantle Tower | W28: Ismail | X28: 82168704736 | Y28: Dismantle | Z28: 45700 | AA28: 45707 | AB28: =IF(AA28="ds","Submit",IF(AA28="","NY Submit",IF(AA28<TODAY(),"Expired",IFERROR(DATEDIF(TODAY(),AA28,"d"),"")))) -> Expired | AD28: 45684 | AE28: 45687 | AG28: 45696 | AI28: 45712 | AN28: 45713 | AO28: =+IF(AN28<>"","BAST",IF(AI28<>"","Dismantle",IF(AG28<>"","RFD App",IF(AF28="Drop","Drop",IF(AE28<>"","Survey Report",IF(AD28<>"","Survey","NY Survey")))))) -> BAST | AQ28: 45689 | AR28: 45689 | AS28: 45714 | AT28: 45714 | AU28: 45721 | AV28: 45721 | AW28: =+IF(AV28<>"","1st BOQ App on ISAAC",IF(AU28<>"","Upload 1st BOQ & BAN Isaac",IF(AT28="DRM","need DRM",IF(AT28<>"","BAN App",IF(AR28<>"","1st BOQ Pass TI",IF(AS28<>"","Engineering Structural Manager App",IF(AQ28<>"","1st BOQ Submit","NY Submit"))))))) -> 1st BOQ App on ISAAC | BD28: =+IF(BC28<>"","2nd BOQ App on ISAAC",IF(BB28<>"","Upload 2nd BOQ & BAN Isaac",IF(BA28="DRM","need DRM",IF(BA28<>"","BAN App",IF(AZ28<>"","Engineering Structural Manager App",IF(AY28<>"","2nd BOQ Pass TI",IF(AX28<>"","2nd BOQ Submit","NY Submit"))))))) -> NY Submit | BF28: 45685 | BG28: 45687 | BH28: JSA No.03/TSA/HSE/01/2025 | BI28: 45685 | BJ28: 45687 | BK28: SWP-HSE-03 | BL28: =+IF(BG28<>"","Approved",IF(BF28<>"","Submit","NY Submit")) -> Approved | BM28: =+IF(BJ28<>"","Approved",IF(BI28<>"","Submit","NY Submit")) -> Approved | BN28: 45713 | BO28: 45713 | BP28: Dismantle Tower | BQ28: EMAPO25-000460 | BR28: 45736 | BS28: =IF(AO28="Drop", "Drop", IF(ISBLANK(AV28), 0, IF(ISBLANK(BR28), DATEDIF(AV28,TODAY(),"d"), DATEDIF(AV28,BR28,"d") ) ) ) -> 15 | BV28: =IF(AO28="Drop", "Drop", IF(ISBLANK(BC28), 0, IF(ISBLANK(BU28), DATEDIF(BC28,TODAY(),"d"), DATEDIF(BC28,BU28,"d") ) ) ) -> 0 | BZ28: Complete
A29: 24 | B29: CMI | C29: RLC | D29: Nasional | E29: =+_xlfn.CONCAT(G29,"-",B29,"_",C29,"_",_xlfn.XLOOKUP(BP29,Account!M:M,Account!N:N)) -> #NAME? | F29: 45681 | G29: E7400037 | H29: ID-SG-07845 | I29: V_TOMIA | J29: 19 | K29: EMA | L29: SULAWESI TENGGARA | M29: Kab. Wakatobi | N29: LINGKUNGAN UNTU KEL. WAHA KEC. TOMIA KABUPATEN WAKATOBI, SULAWESI TENGGARA | O29: -5.7283 | P29: 123.89737 | Q29: 22120.78 | R29: 70 | T29: Greenfield | U29: SST 4 Legs | V29: Dismantle Tower | W29: Saiful S | X29: 82195397250 | Y29: Dismantle | Z29: 45700 | AA29: 45707 | AB29: =IF(AA29="ds","Submit",IF(AA29="","NY Submit",IF(AA29<TODAY(),"Expired",IFERROR(DATEDIF(TODAY(),AA29,"d"),"")))) -> Expired | AD29: 45687 | AE29: 45687 | AG29: 45699 | AI29: 45742 | AN29: 45742 | AO29: =+IF(AN29<>"","BAST",IF(AI29<>"","Dismantle",IF(AG29<>"","RFD App",IF(AF29="Drop","Drop",IF(AE29<>"","Survey Report",IF(AD29<>"","Survey","NY Survey")))))) -> BAST | AQ29: 45689 | AR29: 45689 | AS29: 45714 | AT29: 45714 | AU29: 45707 | AV29: 45707 | AW29: =+IF(AV29<>"","1st BOQ App on ISAAC",IF(AU29<>"","Upload 1st BOQ & BAN Isaac",IF(AT29="DRM","need DRM",IF(AT29<>"","BAN App",IF(AR29<>"","1st BOQ Pass TI",IF(AS29<>"","Engineering Structural Manager App",IF(AQ29<>"","1st BOQ Submit","NY Submit"))))))) -> 1st BOQ App on ISAAC | BD29: =+IF(BC29<>"","2nd BOQ App on ISAAC",IF(BB29<>"","Upload 2nd BOQ & BAN Isaac",IF(BA29="DRM","need DRM",IF(BA29<>"","BAN App",IF(AZ29<>"","Engineering Structural Manager App",IF(AY29<>"","2nd BOQ Pass TI",IF(AX29<>"","2nd BOQ Submit","NY Submit"))))))) -> NY Submit | BF29: 45687 | BG29: 45687 | BH29: JSA No.06/TSA/HSE/01/2025 | BI29: 45687 | BJ29: 45687 | BK29: SWP-HSE-06 | BL29: =+IF(BG29<>"","Approved",IF(BF29<>"","Submit","NY Submit")) -> Approved | BM29: =+IF(BJ29<>"","Approved",IF(BI29<>"","Submit","NY Submit")) -> Approved | BN29: 45761 | BO29: 45761 | BP29: Dismantle Tower | BQ29: EMAPO25-000463 | BR29: 45736 | BS29: =IF(AO29="Drop", "Drop", IF(ISBLANK(AV29), 0, IF(ISBLANK(BR29), DATEDIF(AV29,TODAY(),"d"), DATEDIF(AV29,BR29,"d") ) ) ) -> 29 | BV29: =IF(AO29="Drop", "Drop", IF(ISBLANK(BC29), 0, IF(ISBLANK(BU29), DATEDIF(BC29,TODAY(),"d"), DATEDIF(BC29,BU29,"d") ) ) ) -> 0 | BZ29: Complete
A30: 25 | B30: CMI | C30: RLC | D30: Nasional | E30: =+_xlfn.CONCAT(G30,"-",B30,"_",C30,"_",_xlfn.XLOOKUP(BP30,Account!M:M,Account!N:N)) -> #NAME? | F30: 45681 | G30: E7300173 | H30: ID-SN-07804 | I30: BIKERU | J30: 19 | K30: EMA | L30: SULAWESI SELATAN | M30: Kab. Sinjai | N30: JL. PERSATUAN RAYA, KEL. SANGIASERI, KEC. SINJAI SELATAN | O30: -5.2588 | P30: 120.15962 | Q30: 22120.78 | R30: 70 | T30: Greenfield | U30: SST 4 Legs | V30: Dismantle Tower | W30: Saiful S | X30: 82195397250 | Y30: Dismantle | Z30: 45700 | AA30: 45707 | AB30: =IF(AA30="ds","Submit",IF(AA30="","NY Submit",IF(AA30<TODAY(),"Expired",IFERROR(DATEDIF(TODAY(),AA30,"d"),"")))) -> Expired | AD30: 45683 | AE30: 45687 | AG30: 45699 | AI30: 45716 | AN30: 45727 | AO30: =+IF(AN30<>"","BAST",IF(AI30<>"","Dismantle",IF(AG30<>"","RFD App",IF(AF30="Drop","Drop",IF(AE30<>"","Survey Report",IF(AD30<>"","Survey","NY Survey")))))) -> BAST | AQ30: 45689 | AR30: 45689 | AS30: 45714 | AT30: 45714 | AU30: 45721 | AV30: 45721 | AW30: =+IF(AV30<>"","1st BOQ App on ISAAC",IF(AU30<>"","Upload 1st BOQ & BAN Isaac",IF(AT30="DRM","need DRM",IF(AT30<>"","BAN App",IF(AR30<>"","1st BOQ Pass TI",IF(AS30<>"","Engineering Structural Manager App",IF(AQ30<>"","1st BOQ Submit","NY Submit"))))))) -> 1st BOQ App on ISAAC | BD30: =+IF(BC30<>"","2nd BOQ App on ISAAC",IF(BB30<>"","Upload 2nd BOQ & BAN Isaac",IF(BA30="DRM","need DRM",IF(BA30<>"","BAN App",IF(AZ30<>"","Engineering Structural Manager App",IF(AY30<>"","2nd BOQ Pass TI",IF(AX30<>"","2nd BOQ Submit","NY Submit"))))))) -> NY Submit | BF30: 45686 | BG30: 45687 | BH30: JSA No.05/TSA/HSE/01/2025 | BI30: 45686 | BJ30: 45687 | BK30: SWP-HSE-05 | BL30: =+IF(BG30<>"","Approved",IF(BF30<>"","Submit","NY Submit")) -> Approved | BM30: =+IF(BJ30<>"","Approved",IF(BI30<>"","Submit","NY Submit")) -> Approved | BN30: 45727 | BO30: 45727 | BP30: Dismantle Tower | BQ30: EMAPO25-000462 | BR30: 45736 | BS30: =IF(AO30="Drop", "Drop", IF(ISBLANK(AV30), 0, IF(ISBLANK(BR30), DATEDIF(AV30,TODAY(),"d"), DATEDIF(AV30,BR30,"d") ) ) ) -> 15 | BV30: =IF(AO30="Drop", "Drop", IF(ISBLANK(BC30), 0, IF(ISBLANK(BU30), DATEDIF(BC30,TODAY(),"d"), DATEDIF(BC30,BU30,"d") ) ) ) -> 0 | BZ30: Complete
A31: 26 | B31: CMI | C31: RLC | D31: Nasional | E31: =+_xlfn.CONCAT(G31,"-",B31,"_",C31,"_",_xlfn.XLOOKUP(BP31,Account!M:M,Account!N:N)) -> #NAME? | F31: 45681 | G31: E7200035 | H31: ID-ST-07619 | I31: V_WAKAI | J31: 19 | K31: EMA | L31: SULAWESI TENGAH | M31: Kab. Tojo Una Una | N31: DS. WAKAI KEC. UNA-UNA, KAB. TOJO UNA-UNA, SULAWESI TENGAH | O31: -0.41265 | P31: 121.859 | Q31: 22120.78 | R31: 70 | T31: Greenfield | U31: SST 4 Legs | V31: Dismantle Tower | W31: Saiful S | X31: 82195397250 | Y31: Dismantle | Z31: 45700 | AA31: 45707 | AB31: =IF(AA31="ds","Submit",IF(AA31="","NY Submit",IF(AA31<TODAY(),"Expired",IFERROR(DATEDIF(TODAY(),AA31,"d"),"")))) -> Expired | AD31: 45687 | AE31: 45687 | AG31: 45699 | AI31: 45719 | AN31: 45719 | AO31: =+IF(AN31<>"","BAST",IF(AI31<>"","Dismantle",IF(AG31<>"","RFD App",IF(AF31="Drop","Drop",IF(AE31<>"","Survey Report",IF(AD31<>"","Survey","NY Survey")))))) -> BAST | AQ31: 45689 | AR31: 45689 | AS31: 45714 | AT31: 45714 | AU31: 45698 | AV31: 45698 | AW31: =+IF(AV31<>"","1st BOQ App on ISAAC",IF(AU31<>"","Upload 1st BOQ & BAN Isaac",IF(AT31="DRM","need DRM",IF(AT31<>"","BAN App",IF(AR31<>"","1st BOQ Pass TI",IF(AS31<>"","Engineering Structural Manager App",IF(AQ31<>"","1st BOQ Submit","NY Submit"))))))) -> 1st BOQ App on ISAAC | BD31: =+IF(BC31<>"","2nd BOQ App on ISAAC",IF(BB31<>"","Upload 2nd BOQ & BAN Isaac",IF(BA31="DRM","need DRM",IF(BA31<>"","BAN App",IF(AZ31<>"","Engineering Structural Manager App",IF(AY31<>"","2nd BOQ Pass TI",IF(AX31<>"","2nd BOQ Submit","NY Submit"))))))) -> NY Submit | BF31: 45687 | BG31: 45687 | BH31: JSA No.07/TSA/HSE/01/2025 | BI31: 45687 | BJ31: 45687 | BK31: SWP-HSE-07 | BL31: =+IF(BG31<>"","Approved",IF(BF31<>"","Submit","NY Submit")) -> Approved | BM31: =+IF(BJ31<>"","Approved",IF(BI31<>"","Submit","NY Submit")) -> Approved | BN31: 45719 | BO31: 45719 | BP31: Dismantle Tower | BQ31: EMAPO25-000461 | BR31: 45736 | BS31: =IF(AO31="Drop", "Drop", IF(ISBLANK(AV31), 0, IF(ISBLANK(BR31), DATEDIF(AV31,TODAY(),"d"), DATEDIF(AV31,BR31,"d") ) ) ) -> 38 | BV31: =IF(AO31="Drop", "Drop", IF(ISBLANK(BC31), 0, IF(ISBLANK(BU31), DATEDIF(BC31,TODAY(),"d"), DATEDIF(BC31,BU31,"d") ) ) ) -> 0 | BZ31: Complete
A32: 27 | B32: CMI | C32: RLC | D32: Nasional | E32: =+_xlfn.CONCAT(G32,"-",B32,"_",C32,"_",_xlfn.XLOOKUP(BP32,Account!M:M,Account!N:N)) -> #NAME? | F32: 45681 | G32: R5100027 | H32: ID-BA-00065 | I32: SULI | J32: 16 | K32: CMI | L32: BALI | M32: Kota Denpasar | N32: JL. SULI NO.91 BANJAR KERTHA BHUWANA KAJA KEL. DANGRI KANGIN KEC. DENPASAR UTARA - BALI | O32: -8.64226 | P32: 115.22391 | R32: 9 | T32: Rooftop | U32: Pole | V32: Dismantle Tower | Y32: Survey | Z32: 45700 | AA32: 45707 | AB32: =IF(AA32="ds","Submit",IF(AA32="","NY Submit",IF(AA32<TODAY(),"Expired",IFERROR(DATEDIF(TODAY(),AA32,"d"),"")))) -> Expired | AD32: 45688 | AE32: 45691 | AG32: 45915 | AI32: 45922 | AM32: 45965 | AN32: 45965 | AO32: =+IF(AN32<>"","BAST",IF(AI32<>"","Dismantle",IF(AG32<>"","RFD App",IF(AF32="Drop","Drop",IF(AE32<>"","Survey Report",IF(AD32<>"","Survey","NY Survey")))))) -> BAST | AQ32: 45691 | AR32: 45691 | AS32: 45691 | AU32: 45692 | AV32: 45699 | AW32: =+IF(AV32<>"","1st BOQ App on ISAAC",IF(AU32<>"","Upload 1st BOQ & BAN Isaac",IF(AT32="DRM","need DRM",IF(AT32<>"","BAN App",IF(AR32<>"","1st BOQ Pass TI",IF(AS32<>"","Engineering Structural Manager App",IF(AQ32<>"","1st BOQ Submit","NY Submit"))))))) -> 1st BOQ App on ISAAC | BD32: =+IF(BC32<>"","2nd BOQ App on ISAAC",IF(BB32<>"","Upload 2nd BOQ & BAN Isaac",IF(BA32="DRM","need DRM",IF(BA32<>"","BAN App",IF(AZ32<>"","Engineering Structural Manager App",IF(AY32<>"","2nd BOQ Pass TI",IF(AX32<>"","2nd BOQ Submit","NY Submit"))))))) -> NY Submit | BF32: 45691 | BG32: 45691 | BH32: JSA No.03/TSA/HSE/02/2025 | BI32: 45691 | BJ32: 45691 | BK32: SWP-HSE-10 | BL32: =+IF(BG32<>"","Approved",IF(BF32<>"","Submit","NY Submit")) -> Approved | BM32: =+IF(BJ32<>"","Approved",IF(BI32<>"","Submit","NY Submit")) -> Approved | BN32: 45966 | BO32: 45966 | BP32: Dismantle Tower | BQ32: CMIPO25-001182 | BR32: 45726 | BS32: =IF(AO32="Drop", "Drop", IF(ISBLANK(AV32), 0, IF(ISBLANK(BR32), DATEDIF(AV32,TODAY(),"d"), DATEDIF(AV32,BR32,"d") ) ) ) -> 27 | BV32: =IF(AO32="Drop", "Drop", IF(ISBLANK(BC32), 0, IF(ISBLANK(BU32), DATEDIF(BC32,TODAY(),"d"), DATEDIF(BC32,BU32,"d") ) ) ) -> 0 | BZ32: Complete
A33: 28 | B33: CMI | C33: RLC | D33: Nasional | E33: =+_xlfn.CONCAT(G33,"-",B33,"_",C33,"_",_xlfn.XLOOKUP(BP33,Account!M:M,Account!N:N)) -> #NAME? | F33: 45681 | G33: E3500317 | H33: ID-JI-06482 | I33: MIC_BUNGURASIH | J33: 15 | K33: EMA | L33: JAWA TIMUR | M33: Kab. Sidoarjo | N33: JL RAYA BUNGURASIH SIDOARJO, AT WALL OF RAMAYAN DEPT.STORE | O33: -7.35169 | P33: 112.72274 | Q33: 793 | R33: 6 | T33: Rooftop | U33: Pole | V33: Dismantle Tower | Y33: Dismantle | Z33: 45692 | AA33: 45700 | AB33: =IF(AA33="ds","Submit",IF(AA33="","NY Submit",IF(AA33<TODAY(),"Expired",IFERROR(DATEDIF(TODAY(),AA33,"d"),"")))) -> Expired | AD33: 45692 | AE33: 45693 | AG33: 45699 | AI33: 45709 | AN33: 45730 | AO33: =+IF(AN33<>"","BAST",IF(AI33<>"","Dismantle",IF(AG33<>"","RFD App",IF(AF33="Drop","Drop",IF(AE33<>"","Survey Report",IF(AD33<>"","Survey","NY Survey")))))) -> BAST | AQ33: 45693 | AR33: 45693 | AS33: 45708 | AU33: 45721 | AV33: 45722 | AW33: =+IF(AV33<>"","1st BOQ App on ISAAC",IF(AU33<>"","Upload 1st BOQ & BAN Isaac",IF(AT33="DRM","need DRM",IF(AT33<>"","BAN App",IF(AR33<>"","1st BOQ Pass TI",IF(AS33<>"","Engineering Structural Manager App",IF(AQ33<>"","1st BOQ Submit","NY Submit"))))))) -> 1st BOQ App on ISAAC | BD33: =+IF(BC33<>"","2nd BOQ App on ISAAC",IF(BB33<>"","Upload 2nd BOQ & BAN Isaac",IF(BA33="DRM","need DRM",IF(BA33<>"","BAN App",IF(AZ33<>"","Engineering Structural Manager App",IF(AY33<>"","2nd BOQ Pass TI",IF(AX33<>"","2nd BOQ Submit","NY Submit"))))))) -> NY Submit | BF33: 45693 | BG33: 45693 | BH33: JSA No.08/TSA/HSE/02/2025 | BI33: 45693 | BJ33: 45693 | BK33: SWP-HSE-13 | BL33: =+IF(BG33<>"","Approved",IF(BF33<>"","Submit","NY Submit")) -> Approved | BM33: =+IF(BJ33<>"","Approved",IF(BI33<>"","Submit","NY Submit")) -> Approved | BN33: 45712 | BO33: 45712 | BP33: Dismantle Tower | BQ33: EMAPO25-000478 | BR33: 45740 | BS33: =IF(AO33="Drop", "Drop", IF(ISBLANK(AV33), 0, IF(ISBLANK(BR33), DATEDIF(AV33,TODAY(),"d"), DATEDIF(AV33,BR33,"d") ) ) ) -> 18 | BV33: =IF(AO33="Drop", "Drop", IF(ISBLANK(BC33), 0, IF(ISBLANK(BU33), DATEDIF(BC33,TODAY(),"d"), DATEDIF(BC33,BU33,"d") ) ) ) -> 0 | BZ33: Complete
A34: 29 | B34: CMI | C34: RLC | D34: Nasional | E34: =+_xlfn.CONCAT(G34,"-",B34,"_",C34,"_",_xlfn.XLOOKUP(BP34,Account!M:M,Account!N:N)) -> #NAME? | F34: 45681 | G34: E3300111 | H34: ID-JT-05823 | I34: DCS_ONGKLOK | J34: 11 | K34: EMA | L34: JAWA TENGAH | M34: Kab. Wonosobo | N34: JL. DIENG NO. 60, RT.04/RW.05, KEL. KALIANGET, KEC WONOSOBO KAB. WONOSOBO, JAWA TENGAH | O34: -7.34716 | P34: 109.90704 | Q34: 1161 | R34: 6 | T34: Rooftop | U34: Pole | V34: Dismantle Tower | Y34: Dismantle | Z34: 45686 | AA34: 45693 | AB34: =IF(AA34="ds","Submit",IF(AA34="","NY Submit",IF(AA34<TODAY(),"Expired",IFERROR(DATEDIF(TODAY(),AA34,"d"),"")))) -> Expired | AD34: 45692 | AE34: 45693 | AG34: 45699 | AI34: 45705 | AN34: 45707 | AO34: =+IF(AN34<>"","BAST",IF(AI34<>"","Dismantle",IF(AG34<>"","RFD App",IF(AF34="Drop","Drop",IF(AE34<>"","Survey Report",IF(AD34<>"","Survey","NY Survey")))))) -> BAST | AQ34: 45712 | AR34: 45712 | AS34: 45712 | AU34: 45721 | AV34: 45722 | AW34: =+IF(AV34<>"","1st BOQ App on ISAAC",IF(AU34<>"","Upload 1st BOQ & BAN Isaac",IF(AT34="DRM","need DRM",IF(AT34<>"","BAN App",IF(AR34<>"","1st BOQ Pass TI",IF(AS34<>"","Engineering Structural Manager App",IF(AQ34<>"","1st BOQ Submit","NY Submit"))))))) -> 1st BOQ App on ISAAC | BD34: =+IF(BC34<>"","2nd BOQ App on ISAAC",IF(BB34<>"","Upload 2nd BOQ & BAN Isaac",IF(BA34="DRM","need DRM",IF(BA34<>"","BAN App",IF(AZ34<>"","Engineering Structural Manager App",IF(AY34<>"","2nd BOQ Pass TI",IF(AX34<>"","2nd BOQ Submit","NY Submit"))))))) -> NY Submit | BF34: 45693 | BG34: 45693 | BH34: JSA No.07/TSA/HSE/02/2025 | BI34: 45693 | BJ34: 45693 | BK34: SWP-HSE-14 | BL34: =+IF(BG34<>"","Approved",IF(BF34<>"","Submit","NY Submit")) -> Approved | BM34: =+IF(BJ34<>"","Approved",IF(BI34<>"","Submit","NY Submit")) -> Approved | BN34: 45707 | BO34: 45707 | BP34: Dismantle Tower | BQ34: EMAPO25-000458 | BR34: 45736 | BS34: =IF(AO34="Drop", "Drop", IF(ISBLANK(AV34), 0, IF(ISBLANK(BR34), DATEDIF(AV34,TODAY(),"d"), DATEDIF(AV34,BR34,"d") ) ) ) -> 14 | BV34: =IF(AO34="Drop", "Drop", IF(ISBLANK(BC34), 0, IF(ISBLANK(BU34), DATEDIF(BC34,TODAY(),"d"), DATEDIF(BC34,BU34,"d") ) ) ) -> 0 | BZ34: Complete
A35: 30 | B35: CMI | C35: RLC | D35: Nasional | E35: =+_xlfn.CONCAT(G35,"-",B35,"_",C35,"_",_xlfn.XLOOKUP(BP35,Account!M:M,Account!N:N)) -> #NAME? | F35: 45681 | G35: E3300302 | H35: ID-JT-06012 | I35: BHSPALUR | J35: 11 | K35: EMA | L35: JAWA TENGAH | M35: Kab. Karanganyar | N35: DESA NGRINGO, KEC. JATEN, KAB. KARANGANYAR, JAWA TENGAH | O35: -7.56703 | P35: 110.86775 | Q35: 3968.058 | R35: 34.7 | T35: Rooftop | U35: MT 4 Legs | V35: Dismantle Tower | Y35: Survey | Z35: 45713 | AA35: 45720 | AB35: =IF(AA35="ds","Submit",IF(AA35="","NY Submit",IF(AA35<TODAY(),"Expired",IFERROR(DATEDIF(TODAY(),AA35,"d"),"")))) -> Expired | AD35: 45699 | AE35: 45701 | AG35: 45762 | AI35: 45771 | AN35: 45772 | AO35: =+IF(AN35<>"","BAST",IF(AI35<>"","Dismantle",IF(AG35<>"","RFD App",IF(AF35="Drop","Drop",IF(AE35<>"","Survey Report",IF(AD35<>"","Survey","NY Survey")))))) -> BAST | AQ35: 45712 | AR35: 45712 | AS35: 45737 | AT35: 45737 | AU35: 45736 | AV35: 45736 | AW35: =+IF(AV35<>"","1st BOQ App on ISAAC",IF(AU35<>"","Upload 1st BOQ & BAN Isaac",IF(AT35="DRM","need DRM",IF(AT35<>"","BAN App",IF(AR35<>"","1st BOQ Pass TI",IF(AS35<>"","Engineering Structural Manager App",IF(AQ35<>"","1st BOQ Submit","NY Submit"))))))) -> 1st BOQ App on ISAAC | BD35: =+IF(BC35<>"","2nd BOQ App on ISAAC",IF(BB35<>"","Upload 2nd BOQ & BAN Isaac",IF(BA35="DRM","need DRM",IF(BA35<>"","BAN App",IF(AZ35<>"","Engineering Structural Manager App",IF(AY35<>"","2nd BOQ Pass TI",IF(AX35<>"","2nd BOQ Submit","NY Submit"))))))) -> NY Submit | BF35: 45701 | BG35: 45705 | BH35: JSA No.12/TSA/HSE/02/2025 | BI35: 45701 | BJ35: 45705 | BK35: SWP-HSE-20 | BL35: =+IF(BG35<>"","Approved",IF(BF35<>"","Submit","NY Submit")) -> Approved | BM35: =+IF(BJ35<>"","Approved",IF(BI35<>"","Submit","NY Submit")) -> Approved | BN35: 45772 | BO35: 45772 | BP35: Dismantle Tower | BQ35: EMAPO25-000669 | BR35: 45771 | BS35: =IF(AO35="Drop", "Drop", IF(ISBLANK(AV35), 0, IF(ISBLANK(BR35), DATEDIF(AV35,TODAY(),"d"), DATEDIF(AV35,BR35,"d") ) ) ) -> 35 | BV35: =IF(AO35="Drop", "Drop", IF(ISBLANK(BC35), 0, IF(ISBLANK(BU35), DATEDIF(BC35,TODAY(),"d"), DATEDIF(BC35,BU35,"d") ) ) ) -> 0 | BZ35: Complete
A36: 31 | B36: CMI | C36: RLC | D36: Nasional | E36: =+_xlfn.CONCAT(G36,"-",B36,"_",C36,"_",_xlfn.XLOOKUP(BP36,Account!M:M,Account!N:N)) -> #NAME? | F36: 45681 | G36: E7400027 | H36: ID-SG-07835 | I36: SWISSBELL_KENDARI | J36: 19 | K36: EMA | L36: SULAWESI TENGGARA | M36: Kota Kendari | N36: JL__EDI_SABARA_NO_88_BYPASS_93122 | O36: -3.96801 | P36: 122.53192 | Q36: 1861.482 | R36: 5.5 | T36: Rooftop | U36: Pole & Guyed Mast | V36: Dismantle Tower | Y36: Survey | AB36: =IF(AA36="ds","Submit",IF(AA36="","NY Submit",IF(AA36<TODAY(),"Expired",IFERROR(DATEDIF(TODAY(),AA36,"d"),"")))) -> NY Submit | AD36: 45692 | AE36: 45693 | AG36: 45829 | AI36: 45866 | AM36: 45867 | AN36: 45868 | AO36: =+IF(AN36<>"","BAST",IF(AI36<>"","Dismantle",IF(AG36<>"","RFD App",IF(AF36="Drop","Drop",IF(AE36<>"","Survey Report",IF(AD36<>"","Survey","NY Survey")))))) -> BAST | AQ36: 45712 | AR36: 45712 | AS36: 45720 | AT36: 45720 | AU36: 45693 | AV36: 45693 | AW36: =+IF(AV36<>"","1st BOQ App on ISAAC",IF(AU36<>"","Upload 1st BOQ & BAN Isaac",IF(AT36="DRM","need DRM",IF(AT36<>"","BAN App",IF(AR36<>"","1st BOQ Pass TI",IF(AS36<>"","Engineering Structural Manager App",IF(AQ36<>"","1st BOQ Submit","NY Submit"))))))) -> 1st BOQ App on ISAAC | BD36: =+IF(BC36<>"","2nd BOQ App on ISAAC",IF(BB36<>"","Upload 2nd BOQ & BAN Isaac",IF(BA36="DRM","need DRM",IF(BA36<>"","BAN App",IF(AZ36<>"","Engineering Structural Manager App",IF(AY36<>"","2nd BOQ Pass TI",IF(AX36<>"","2nd BOQ Submit","NY Submit"))))))) -> NY Submit | BF36: 45693 | BG36: 45693 | BH36: JSA No.06/TSA/HSE/02/2025 | BI36: 45693 | BJ36: 45693 | BK36: SWP-HSE-15 | BL36: =+IF(BG36<>"","Approved",IF(BF36<>"","Submit","NY Submit")) -> Approved | BM36: =+IF(BJ36<>"","Approved",IF(BI36<>"","Submit","NY Submit")) -> Approved | BN36: 45868 | BP36: Dismantle Tower | BQ36: EMAPO25-000479 | BR36: 45740 | BS36: =IF(AO36="Drop", "Drop", IF(ISBLANK(AV36), 0, IF(ISBLANK(BR36), DATEDIF(AV36,TODAY(),"d"), DATEDIF(AV36,BR36,"d") ) ) ) -> 47 | BV36: =IF(AO36="Drop", "Drop", IF(ISBLANK(BC36), 0, IF(ISBLANK(BU36), DATEDIF(BC36,TODAY(),"d"), DATEDIF(BC36,BU36,"d") ) ) ) -> 0 | BZ36: Complete
A37: 32 | B37: CMI | C37: RLC | D37: Nasional | E37: =+_xlfn.CONCAT(G37,"-",B37,"_",C37,"_",_xlfn.XLOOKUP(BP37,Account!M:M,Account!N:N)) -> #NAME? | F37: 45694 | G37: E8200008 | H37: ID-MU-07908 | I37: JAILOLO | J37: 20 | K37: EMA | L37: MALUKU UTARA | M37: Kab. Halmahera Barat | N37: DESA GUEAMADU, KEC. JAILOLO, KAB. HALMAHERA BARAT | O37: 1.06113 | P37: 127.46551 | Q37: 18868.812 | R37: 72 | S37: IOH (hwei) | T37: Greenfield | U37: SST 4 Legs | V37: Dismantle Tower | Y37: Survey | Z37: 45694 | AA37: 45701 | AB37: =IF(AA37="ds","Submit",IF(AA37="","NY Submit",IF(AA37<TODAY(),"Expired",IFERROR(DATEDIF(TODAY(),AA37,"d"),"")))) -> Expired | AD37: 45695 | AE37: 45737 | AG37: 45877 | AI37: 46017 | AN37: 46021 | AO37: =+IF(AN37<>"","BAST",IF(AI37<>"","Dismantle",IF(AG37<>"","RFD App",IF(AF37="Drop","Drop",IF(AE37<>"","Survey Report",IF(AD37<>"","Survey","NY Survey")))))) -> BAST | AQ37: 45915 | AR37: 46000 | AS37: 45916 | AT37: 46000 | AU37: 46002 | AV37: 46003 | AW37: =+IF(AV37<>"","1st BOQ App on ISAAC",IF(AU37<>"","Upload 1st BOQ & BAN Isaac",IF(AT37="DRM","need DRM",IF(AT37<>"","BAN App",IF(AR37<>"","1st BOQ Pass TI",IF(AS37<>"","Engineering Structural Manager App",IF(AQ37<>"","1st BOQ Submit","NY Submit"))))))) -> 1st BOQ App on ISAAC | BD37: =+IF(BC37<>"","2nd BOQ App on ISAAC",IF(BB37<>"","Upload 2nd BOQ & BAN Isaac",IF(BA37="DRM","need DRM",IF(BA37<>"","BAN App",IF(AZ37<>"","Engineering Structural Manager App",IF(AY37<>"","2nd BOQ Pass TI",IF(AX37<>"","2nd BOQ Submit","NY Submit"))))))) -> NY Submit | BE37: TSA ada hutang 1 cabinet untuk digunakan di site lain | BF37: 45701 | BG37: 45754 | BH37: JSA No.11/TSA/HSE/02/2025 | BI37: 45701 | BJ37: 45773 | BK37: SWP-HSE-19 | BL37: =+IF(BG37<>"","Approved",IF(BF37<>"","Submit","NY Submit")) -> Approved | BM37: =+IF(BJ37<>"","Approved",IF(BI37<>"","Submit","NY Submit")) -> Approved | BN37: 46021 | BO37: 46022 | BP37: Dismantle Tower | BQ37: EMAPO25-002375 | BR37: 46021 | BS37: =IF(AO37="Drop", "Drop", IF(ISBLANK(AV37), 0, IF(ISBLANK(BR37), DATEDIF(AV37,TODAY(),"d"), DATEDIF(AV37,BR37,"d") ) ) ) -> 18 | BV37: =IF(AO37="Drop", "Drop", IF(ISBLANK(BC37), 0, IF(ISBLANK(BU37), DATEDIF(BC37,TODAY(),"d"), DATEDIF(BC37,BU37,"d") ) ) ) -> 0 | BZ37: Complete | CE37: ID-MU-14641 | CF37: GUAEMAADU JAILOLO | CG37: 1.06156 | CH37: 127.46364
A38: 33 | B38: CMI | C38: RLC | D38: Nasional | E38: =+_xlfn.CONCAT(G38,"-",B38,"_",C38,"_",_xlfn.XLOOKUP(BP38,Account!M:M,Account!N:N)) -> #NAME? | F38: 45694 | G38: E8200008 | H38: ID-MU-07908 | I38: JAILOLO | J38: 20 | K38: EMA | L38: MALUKU UTARA | M38: Kab. Halmahera Barat | N38: DESA GUEAMADU, KEC. JAILOLO, KAB. HALMAHERA BARAT | O38: 1.06113 | P38: 127.46551 | Q38: 18868.812 | R38: 72 | S38: IOH (hwei) | T38: Greenfield | U38: SST 4 Legs | V38: Dismantle Equipment | Y38: Survey | Z38: 45694 | AA38: 45701 | AB38: =IF(AA38="ds","Submit",IF(AA38="","NY Submit",IF(AA38<TODAY(),"Expired",IFERROR(DATEDIF(TODAY(),AA38,"d"),"")))) -> Expired | AD38: 45695 | AE38: 45737 | AH38: 46009 | AM38: 46035 | AO38: =+IF(AM38<>"","ATP App MS",IF(AJ38<>"","Inbound",IF(AH38<>"","Dismantle Perangkat",IF(AF37="Drop","Drop",IF(AE38<>"","Survey Report",IF(AD38<>"","Survey","NY Survey")))))) -> ATP App MS | AP38: 01.12.25 Start dism equipment | AQ38: 45915 | AR38: 46000 | AT38: 46000 | AU38: 46002 | AW38: =+IF(AV38<>"","1st BOQ App on ISAAC",IF(AU38<>"","Upload 1st BOQ & BAN Isaac",IF(AT38="DRM","need DRM",IF(AT38<>"","BAN App",IF(AR38<>"","1st BOQ Pass TI",IF(AS38<>"","Engineering Structural Manager App",IF(AQ38<>"","1st BOQ Submit","NY Submit"))))))) -> Upload 1st BOQ & BAN Isaac | BD38: =+IF(BC38<>"","2nd BOQ App on ISAAC",IF(BB38<>"","Upload 2nd BOQ & BAN Isaac",IF(BA38="DRM","need DRM",IF(BA38<>"","BAN App",IF(AZ38<>"","Engineering Structural Manager App",IF(AY38<>"","2nd BOQ Pass TI",IF(AX38<>"","2nd BOQ Submit","NY Submit"))))))) -> NY Submit | BE38: TSA ada hutang 1 cabinet untuk digunakan di site lain | BF38: 45701 | BG38: 45754 | BH38: JSA No.11/TSA/HSE/02/2025 | BI38: 45701 | BJ38: 45773 | BL38: =+IF(BG38<>"","Approved",IF(BF38<>"","Submit","NY Submit")) -> Approved | BM38: =+IF(BJ38<>"","Approved",IF(BI38<>"","Submit","NY Submit")) -> Approved | BN38: 46079 | BO38: 46079 | BP38: Dismantle Equipment | BQ38: Include Reloc | BR38: 46021 | BS38: =IF(AO38="Drop", "Drop", IF(ISBLANK(AV38), 0, IF(ISBLANK(BR38), DATEDIF(AV38,TODAY(),"d"), DATEDIF(AV38,BR38,"d") ) ) ) -> 0 | BV38: =IF(AO38="Drop", "Drop", IF(ISBLANK(BC38), 0, IF(ISBLANK(BU38), DATEDIF(BC38,TODAY(),"d"), DATEDIF(BC38,BU38,"d") ) ) ) -> 0 | BZ38: Complete | CE38: ID-MU-14641 | CF38: GUAEMAADU JAILOLO | CG38: 1.06156 | CH38: 127.46364
A39: 34 | B39: CMI | C39: RLC | D39: Nasional | E39: =+_xlfn.CONCAT(G39,"-",B39,"_",C39,"_",_xlfn.XLOOKUP(BP39,Account!M:M,Account!N:N)) -> #NAME? | F39: 45694 | G39: E8200008 | H39: ID-MU-07908 | I39: JAILOLO | J39: 20 | K39: EMA | L39: MALUKU UTARA | M39: Kab. Halmahera Barat | N39: DESA GUEAMADU, KEC. JAILOLO, KAB. HALMAHERA BARAT | O39: 1.06113 | P39: 127.46551 | Q39: 18868.812 | R39: 72 | S39: IOH (hwei) | T39: Greenfield | U39: SST 4 Legs | V39: Relocation Equipment | Y39: Survey | Z39: 45694 | AA39: 45701 | AB39: =IF(AA39="ds","Submit",IF(AA39="","NY Submit",IF(AA39<TODAY(),"Expired",IFERROR(DATEDIF(TODAY(),AA39,"d"),"")))) -> Expired | AD39: 45695 | AE39: 45737 | AK39: 46012 | AL39: 46035 | AM39: 46035 | AO39: =+IF(AM39<>"","ATP App MS",IF(AL39<>"","OA/RFS",IF(AK39<>"","Install",IF(AH39<>"","Dismantle Perangkat",IF(AF39="Drop","Drop",IF(AE39<>"","Survey Report",IF(AD39<>"","Survey","NY Survey"))))))) -> ATP App MS | AP39: 21.12.25 partial OA | AQ39: 45915 | AR39: 46000 | AT39: 46000 | AU39: 46002 | AW39: =+IF(AV39<>"","1st BOQ App on ISAAC",IF(AU39<>"","Upload 1st BOQ & BAN Isaac",IF(AT39="DRM","need DRM",IF(AT39<>"","BAN App",IF(AR39<>"","1st BOQ Pass TI",IF(AS39<>"","Engineering Structural Manager App",IF(AQ39<>"","1st BOQ Submit","NY Submit"))))))) -> Upload 1st BOQ & BAN Isaac | AX39: 46021 | BA39: 46055 | BC39: 46055 | BD39: =+IF(BC39<>"","2nd BOQ App on ISAAC",IF(BB39<>"","Upload 2nd BOQ & BAN Isaac",IF(BA39="DRM","need DRM",IF(BA39<>"","BAN App",IF(AZ39<>"","Engineering Structural Manager App",IF(AY39<>"","2nd BOQ Pass TI",IF(AX39<>"","2nd BOQ Submit","NY Submit"))))))) -> 2nd BOQ App on ISAAC | BF39: 45701 | BG39: 45754 | BH39: JSA No.11/TSA/HSE/02/2025 | BI39: 45701 | BJ39: 45773 | BL39: =+IF(BG39<>"","Approved",IF(BF39<>"","Submit","NY Submit")) -> Approved | BM39: =+IF(BJ39<>"","Approved",IF(BI39<>"","Submit","NY Submit")) -> Approved | BN39: 46079 | BO39: 46079 | BP39: Relocation Equipment | BQ39: EMAPO25-002378 | BR39: 46063 | BS39: =IF(AO39="Drop", "Drop", IF(ISBLANK(AV39), 0, IF(ISBLANK(BR39), DATEDIF(AV39,TODAY(),"d"), DATEDIF(AV39,BR39,"d") ) ) ) -> 0 | BT39: EMAPO26-000137 | BU39: 46063 | BV39: =IF(AO39="Drop", "Drop", IF(ISBLANK(BC39), 0, IF(ISBLANK(BU39), DATEDIF(BC39,TODAY(),"d"), DATEDIF(BC39,BU39,"d") ) ) ) -> 8 | BZ39: Complete | CE39: ID-MU-14641 | CF39: GUAEMAADU JAILOLO | CG39: 1.06156 | CH39: 127.46364
A40: 35 | B40: CMI | C40: RLC | D40: Nasional | E40: =+_xlfn.CONCAT(G40,"-",B40,"_",C40,"_",_xlfn.XLOOKUP(BP40,Account!M:M,Account!N:N)) -> #NAME? | F40: 45699 | G40: R5300046 | H40: ID-NT-08458 | I40: N3T POMA | J40: 16 | K40: CMI | L40: NUSA TENGGARA TIMUR | M40: Kab. Sikka | N40: RATEGILI, RT 001/ RW 007 DUSUN RATEGILI , DESA POMA KECAMATAN TANA WAWO KAB SIKKA | O40: -8,663972222 | P40: 121,99636 | Q40: 9023.12 | R40: 52 | S40: XL | T40: Greenfield | U40: SST 4 Legs | V40: Dismantle Tower | Y40: Dismantle | Z40: 45700 | AA40: 45707 | AB40: =IF(AA40="ds","Submit",IF(AA40="","NY Submit",IF(AA40<TODAY(),"Expired",IFERROR(DATEDIF(TODAY(),AA40,"d"),"")))) -> Expired | AD40: 45702 | AE40: 45705 | AG40: 45727 | AI40: 45727 | AN40: 45771 | AO40: =+IF(AN40<>"","BAST",IF(AI40<>"","Dismantle",IF(AG40<>"","RFD App",IF(AF40="Drop","Drop",IF(AE40<>"","Survey Report",IF(AD40<>"","Survey","NY Survey")))))) -> BAST | AQ40: 45715 | AR40: 45771 | AS40: 45771 | AT40: 45825 | AU40: 45825 | AV40: 45825 | AW40: =+IF(AV40<>"","1st BOQ App on ISAAC",IF(AU40<>"","Upload 1st BOQ & BAN Isaac",IF(AT40="DRM","need DRM",IF(AT40<>"","BAN App",IF(AR40<>"","1st BOQ Pass TI",IF(AS40<>"","Engineering Structural Manager App",IF(AQ40<>"","1st BOQ Submit","NY Submit"))))))) -> 1st BOQ App on ISAAC | BD40: =+IF(BC40<>"","2nd BOQ App on ISAAC",IF(BB40<>"","Upload 2nd BOQ & BAN Isaac",IF(BA40="DRM","need DRM",IF(BA40<>"","BAN App",IF(AZ40<>"","Engineering Structural Manager App",IF(AY40<>"","2nd BOQ Pass TI",IF(AX40<>"","2nd BOQ Submit","NY Submit"))))))) -> NY Submit | BF40: 45704 | BG40: 45705 | BH40: JSA No.14/TSA/HSE/02/2025 | BI40: 45704 | BJ40: 45705 | BK40: SWP-HSE-21 | BL40: =+IF(BG40<>"","Approved",IF(BF40<>"","Submit","NY Submit")) -> Approved | BM40: =+IF(BJ40<>"","Approved",IF(BI40<>"","Submit","NY Submit")) -> Approved | BN40: 45771 | BO40: 45783 | BP40: Dismantle Tower | BQ40: CMIPO25-003409 | BR40: 45869 | BS40: =IF(AO40="Drop", "Drop", IF(ISBLANK(AV40), 0, IF(ISBLANK(BR40), DATEDIF(AV40,TODAY(),"d"), DATEDIF(AV40,BR40,"d") ) ) ) -> 44 | BV40: =IF(AO40="Drop", "Drop", IF(ISBLANK(BC40), 0, IF(ISBLANK(BU40), DATEDIF(BC40,TODAY(),"d"), DATEDIF(BC40,BU40,"d") ) ) ) -> 0 | BZ40: Complete
A41: 36 | B41: CMI | C41: RLC | D41: Nasional | E41: =+_xlfn.CONCAT(G41,"-",B41,"_",C41,"_",_xlfn.XLOOKUP(BP41,Account!M:M,Account!N:N)) -> #NAME? | F41: 45699 | G41: R5300046 | H41: ID-NT-08458 | I41: N3T POMA | J41: 16 | K41: CMI | L41: NUSA TENGGARA TIMUR | M41: Kab. Sikka | N41: RATEGILI, RT 001/ RW 007 DUSUN RATEGILI , DESA POMA KECAMATAN TANA WAWO KAB SIKKA | O41: -8,663972222 | P41: 121,99636 | Q41: 9023.12 | R41: 52 | S41: XL | T41: Greenfield | U41: SST 4 Legs | V41: Dismantle Equipment | Y41: Dismantle | Z41: 45700 | AA41: 45707 | AB41: =IF(AA41="ds","Submit",IF(AA41="","NY Submit",IF(AA41<TODAY(),"Expired",IFERROR(DATEDIF(TODAY(),AA41,"d"),"")))) -> Expired | AD41: 45702 | AE41: 45705 | AH41: 45711 | AM41: 45771 | AO41: =+IF(AM41<>"","ATP App MS",IF(AJ41<>"","Inbound",IF(AH41<>"","Dismantle Perangkat",IF(AF41="Drop","Drop",IF(AE41<>"","Survey Report",IF(AD41<>"","Survey","NY Survey")))))) -> ATP App MS | AQ41: 45715 | AR41: 45771 | AS41: 45771 | AT41: 45825 | AU41: 45825 | AV41: 45825 | AW41: =+IF(AV41<>"","1st BOQ App on ISAAC",IF(AU41<>"","Upload 1st BOQ & BAN Isaac",IF(AT41="DRM","need DRM",IF(AT41<>"","BAN App",IF(AR41<>"","1st BOQ Pass TI",IF(AS41<>"","Engineering Structural Manager App",IF(AQ41<>"","1st BOQ Submit","NY Submit"))))))) -> 1st BOQ App on ISAAC | BD41: =+IF(BC41<>"","2nd BOQ App on ISAAC",IF(BB41<>"","Upload 2nd BOQ & BAN Isaac",IF(BA41="DRM","need DRM",IF(BA41<>"","BAN App",IF(AZ41<>"","Engineering Structural Manager App",IF(AY41<>"","2nd BOQ Pass TI",IF(AX41<>"","2nd BOQ Submit","NY Submit"))))))) -> NY Submit | BF41: 45704 | BG41: 45705 | BH41: JSA No.14/TSA/HSE/02/2025 | BI41: 45704 | BJ41: No Need (site down) | BL41: =+IF(BG41<>"","Approved",IF(BF41<>"","Submit","NY Submit")) -> Approved | BM41: =+IF(BJ41<>"","Approved",IF(BI41<>"","Submit","NY Submit")) -> Approved | BP41: Dismantle Equipment | BQ41: CMIPO25-003410 | BR41: 45869 | BS41: =IF(AO41="Drop", "Drop", IF(ISBLANK(AV41), 0, IF(ISBLANK(BR41), DATEDIF(AV41,TODAY(),"d"), DATEDIF(AV41,BR41,"d") ) ) ) -> 44 | BV41: =IF(AO41="Drop", "Drop", IF(ISBLANK(BC41), 0, IF(ISBLANK(BU41), DATEDIF(BC41,TODAY(),"d"), DATEDIF(BC41,BU41,"d") ) ) ) -> 0 | BZ41: Complete
A42: 37 | B42: CMI | C42: RLC | D42: Nasional | E42: =+_xlfn.CONCAT(G42,"-",B42,"_",C42,"_",_xlfn.XLOOKUP(BP42,Account!M:M,Account!N:N)) -> #NAME? | F42: 45699 | G42: R5300046 | H42: ID-NT-08458 | I42: N3T POMA | J42: 16 | K42: CMI | L42: NUSA TENGGARA TIMUR | M42: Kab. Sikka | N42: RATEGILI, RT 001/ RW 007 DUSUN RATEGILI , DESA POMA KECAMATAN TANA WAWO KAB SIKKA | O42: -8,663972222 | P42: 121,99636 | Q42: 9023.12 | R42: 52 | S42: XL | T42: Greenfield | U42: SST 4 Legs | V42: Relocation Equipment | Y42: Dismantle | Z42: 45700 | AA42: 45707 | AB42: =IF(AA42="ds","Submit",IF(AA42="","NY Submit",IF(AA42<TODAY(),"Expired",IFERROR(DATEDIF(TODAY(),AA42,"d"),"")))) -> Expired | AD42: 45702 | AE42: 45705 | AK42: 45907 | AM42: 45771 | AO42: =+IF(AM42<>"","ATP App MS",IF(AL42<>"","OA/RFS",IF(AK42<>"","Install",IF(AH42<>"","Dismantle Perangkat",IF(AF42="Drop","Drop",IF(AE42<>"","Survey Report",IF(AD42<>"","Survey","NY Survey"))))))) -> ATP App MS | AQ42: 45715 | AR42: 45771 | AS42: 45771 | AT42: 45825 | AU42: 45825 | AV42: 45825 | AW42: =+IF(AV42<>"","1st BOQ App on ISAAC",IF(AU42<>"","Upload 1st BOQ & BAN Isaac",IF(AT42="DRM","need DRM",IF(AT42<>"","BAN App",IF(AR42<>"","1st BOQ Pass TI",IF(AS42<>"","Engineering Structural Manager App",IF(AQ42<>"","1st BOQ Submit","NY Submit"))))))) -> 1st BOQ App on ISAAC | BD42: =+IF(BC42<>"","2nd BOQ App on ISAAC",IF(BB42<>"","Upload 2nd BOQ & BAN Isaac",IF(BA42="DRM","need DRM",IF(BA42<>"","BAN App",IF(AZ42<>"","Engineering Structural Manager App",IF(AY42<>"","2nd BOQ Pass TI",IF(AX42<>"","2nd BOQ Submit","NY Submit"))))))) -> NY Submit | BF42: 45704 | BG42: 45705 | BH42: JSA No.14/TSA/HSE/02/2025 | BI42: 45704 | BJ42: No Need (site down) | BL42: =+IF(BG42<>"","Approved",IF(BF42<>"","Submit","NY Submit")) -> Approved | BM42: =+IF(BJ42<>"","Approved",IF(BI42<>"","Submit","NY Submit")) -> Approved | BP42: Relocation Equipment | BQ42: CMIPO25-003411 | BR42: 45869 | BS42: =IF(AO42="Drop", "Drop", IF(ISBLANK(AV42), 0, IF(ISBLANK(BR42), DATEDIF(AV42,TODAY(),"d"), DATEDIF(AV42,BR42,"d") ) ) ) -> 44 | BV42: =IF(AO42="Drop", "Drop", IF(ISBLANK(BC42), 0, IF(ISBLANK(BU42), DATEDIF(BC42,TODAY(),"d"), DATEDIF(BC42,BU42,"d") ) ) ) -> 0 | BZ42: Complete
A43: 38 | B43: CMI | C43: RLC | D43: Nasional | E43: =+_xlfn.CONCAT(G43,"-",B43,"_",C43,"_",_xlfn.XLOOKUP(BP43,Account!M:M,Account!N:N)) -> #NAME? | F43: 45705 | G43: E3500541 | H43: ID-JI-06705 | I43: GANDUSARI | J43: 15 | K43: EMA | L43: JAWA TIMUR | M43: Kab. Trenggalek | N43: Jl. Gandusari - Kampak | O43: -8.12748 | P43: 111.71111 | Q43: 22120 | R43: 70 | S43: IOH | T43: Greenfield | U43: SST 4 Legs | V43: Dismantle Tower | Y43: Survey | AB43: =IF(AA43="ds","Submit",IF(AA43="","NY Submit",IF(AA43<TODAY(),"Expired",IFERROR(DATEDIF(TODAY(),AA43,"d"),"")))) -> NY Submit | AD43: 45707 | AE43: 45708 | AF43: Drop | AO43: =+IF(AN43<>"","BAST",IF(AI43<>"","Dismantle",IF(AG43<>"","RFD App",IF(AF43="Drop","Drop",IF(AE43<>"","Survey Report",IF(AD43<>"","Survey","NY Survey")))))) -> Drop | AP43: Survey Only | AQ43: 45888 | AR43: 45960 | AV43: 45960 | AW43: =+IF(AV43<>"","1st BOQ App on ISAAC",IF(AU43<>"","Upload 1st BOQ & BAN Isaac",IF(AT43="DRM","need DRM",IF(AT43<>"","BAN App",IF(AR43<>"","1st BOQ Pass TI",IF(AS43<>"","Engineering Structural Manager App",IF(AQ43<>"","1st BOQ Submit","NY Submit"))))))) -> 1st BOQ App on ISAAC | BD43: =+IF(BC43<>"","2nd BOQ App on ISAAC",IF(BB43<>"","Upload 2nd BOQ & BAN Isaac",IF(BA43="DRM","need DRM",IF(BA43<>"","BAN App",IF(AZ43<>"","Engineering Structural Manager App",IF(AY43<>"","2nd BOQ Pass TI",IF(AX43<>"","2nd BOQ Submit","NY Submit"))))))) -> NY Submit | BF43: 45708 | BG43: 45712 | BH43: JSA No.16/TSA/HSE/02/2025 | BI43: 45708 | BJ43: 45712 | BK43: SWP-HSE-23 | BL43: =+IF(BG43<>"","Approved",IF(BF43<>"","Submit","NY Submit")) -> Approved | BM43: =+IF(BJ43<>"","Approved",IF(BI43<>"","Submit","NY Submit")) -> Approved | BP43: Dismantle Tower | BQ43: EMAPO25-002238 | BR43: 45982 | BS43: =IF(AO43="Drop", "Drop", IF(ISBLANK(AV43), 0, IF(ISBLANK(BR43), DATEDIF(AV43,TODAY(),"d"), DATEDIF(AV43,BR43,"d") ) ) ) -> Drop | BV43: =IF(AO43="Drop", "Drop", IF(ISBLANK(BC43), 0, IF(ISBLANK(BU43), DATEDIF(BC43,TODAY(),"d"), DATEDIF(BC43,BU43,"d") ) ) ) -> Drop | BZ43: Complete | CE43: ID-JI-16221 | CF43: DURENAN TRENGGALEK | CG43: -8.11192 | CH43: 111.80472
A44: 39 | B44: CMI | C44: RLC | D44: Nasional | E44: =+_xlfn.CONCAT(G44,"-",B44,"_",C44,"_",_xlfn.XLOOKUP(BP44,Account!M:M,Account!N:N)) -> #NAME? | F44: 45705 | G44: E3500541 | H44: ID-JI-06705 | I44: GANDUSARI | J44: 15 | K44: EMA | L44: JAWA TIMUR | M44: Kab. Trenggalek | N44: Jl. Gandusari - Kampak | O44: -8.12748 | P44: 111.71111 | Q44: 22120 | R44: 70 | S44: IOH | T44: Greenfield | U44: SST 4 Legs | V44: Dismantle Equipment | Y44: Survey | AB44: =IF(AA44="ds","Submit",IF(AA44="","NY Submit",IF(AA44<TODAY(),"Expired",IFERROR(DATEDIF(TODAY(),AA44,"d"),"")))) -> NY Submit | AD44: 45707 | AE44: 45708 | AF44: Drop | AO44: =+IF(AM44<>"","ATP App MS",IF(AJ44<>"","Inbound",IF(AH44<>"","Dismantle Perangkat",IF(AF44="Drop","Drop",IF(AE44<>"","Survey Report",IF(AD44<>"","Survey","NY Survey")))))) -> Drop | AW44: =+IF(AV44<>"","1st BOQ App on ISAAC",IF(AU44<>"","Upload 1st BOQ & BAN Isaac",IF(AT44="DRM","need DRM",IF(AT44<>"","BAN App",IF(AR44<>"","1st BOQ Pass TI",IF(AS44<>"","Engineering Structural Manager App",IF(AQ44<>"","1st BOQ Submit","NY Submit"))))))) -> NY Submit | BD44: =+IF(BC44<>"","2nd BOQ App on ISAAC",IF(BB44<>"","Upload 2nd BOQ & BAN Isaac",IF(BA44="DRM","need DRM",IF(BA44<>"","BAN App",IF(AZ44<>"","Engineering Structural Manager App",IF(AY44<>"","2nd BOQ Pass TI",IF(AX44<>"","2nd BOQ Submit","NY Submit"))))))) -> NY Submit | BF44: 45708 | BG44: 45712 | BH44: JSA No.16/TSA/HSE/02/2025 | BI44: 45708 | BJ44: 45712 | BL44: =+IF(BG44<>"","Approved",IF(BF44<>"","Submit","NY Submit")) -> Approved | BM44: =+IF(BJ44<>"","Approved",IF(BI44<>"","Submit","NY Submit")) -> Approved | BP44: Dismantle Equipment | BQ44: Drop | BS44: =IF(AO44="Drop", "Drop", IF(ISBLANK(AV44), 0, IF(ISBLANK(BR44), DATEDIF(AV44,TODAY(),"d"), DATEDIF(AV44,BR44,"d") ) ) ) -> Drop | BV44: =IF(AO44="Drop", "Drop", IF(ISBLANK(BC44), 0, IF(ISBLANK(BU44), DATEDIF(BC44,TODAY(),"d"), DATEDIF(BC44,BU44,"d") ) ) ) -> Drop | BZ44: Drop | CA44: Drop | CB44: Drop | CE44: ID-JI-16221 | CF44: DURENAN TRENGGALEK | CG44: -8.11192 | CH44: 111.80472
A45: 40 | B45: CMI | C45: RLC | D45: Nasional | E45: =+_xlfn.CONCAT(G45,"-",B45,"_",C45,"_",_xlfn.XLOOKUP(BP45,Account!M:M,Account!N:N)) -> #NAME? | F45: 45705 | G45: E3500541 | H45: ID-JI-06705 | I45: GANDUSARI | J45: 15 | K45: EMA | L45: JAWA TIMUR | M45: Kab. Trenggalek | N45: Jl. Gandusari - Kampak | O45: -8.12748 | P45: 111.71111 | Q45: 22120 | R45: 70 | S45: IOH | T45: Greenfield | U45: SST 4 Legs | V45: Relocation Equipment | Y45: Survey | AB45: =IF(AA45="ds","Submit",IF(AA45="","NY Submit",IF(AA45<TODAY(),"Expired",IFERROR(DATEDIF(TODAY(),AA45,"d"),"")))) -> NY Submit | AD45: 45707 | AE45: 45708 | AF45: Drop | AO45: =+IF(AM45<>"","ATP App MS",IF(AL45<>"","OA/RFS",IF(AK45<>"","Install",IF(AH45<>"","Dismantle Perangkat",IF(AF45="Drop","Drop",IF(AE45<>"","Survey Report",IF(AD45<>"","Survey","NY Survey"))))))) -> Drop | AW45: =+IF(AV45<>"","1st BOQ App on ISAAC",IF(AU45<>"","Upload 1st BOQ & BAN Isaac",IF(AT45="DRM","need DRM",IF(AT45<>"","BAN App",IF(AR45<>"","1st BOQ Pass TI",IF(AS45<>"","Engineering Structural Manager App",IF(AQ45<>"","1st BOQ Submit","NY Submit"))))))) -> NY Submit | BD45: =+IF(BC45<>"","2nd BOQ App on ISAAC",IF(BB45<>"","Upload 2nd BOQ & BAN Isaac",IF(BA45="DRM","need DRM",IF(BA45<>"","BAN App",IF(AZ45<>"","Engineering Structural Manager App",IF(AY45<>"","2nd BOQ Pass TI",IF(AX45<>"","2nd BOQ Submit","NY Submit"))))))) -> NY Submit | BF45: 45708 | BG45: 45712 | BH45: JSA No.16/TSA/HSE/02/2025 | BI45: 45708 | BJ45: 45712 | BL45: =+IF(BG45<>"","Approved",IF(BF45<>"","Submit","NY Submit")) -> Approved | BM45: =+IF(BJ45<>"","Approved",IF(BI45<>"","Submit","NY Submit")) -> Approved | BP45: Relocation Equipment | BQ45: Drop | BS45: =IF(AO45="Drop", "Drop", IF(ISBLANK(AV45), 0, IF(ISBLANK(BR45), DATEDIF(AV45,TODAY(),"d"), DATEDIF(AV45,BR45,"d") ) ) ) -> Drop | BV45: =IF(AO45="Drop", "Drop", IF(ISBLANK(BC45), 0, IF(ISBLANK(BU45), DATEDIF(BC45,TODAY(),"d"), DATEDIF(BC45,BU45,"d") ) ) ) -> Drop | BZ45: Drop | CA45: Drop | CB45: Drop | CE45: ID-JI-16221 | CF45: DURENAN TRENGGALEK | CG45: -8.11192 | CH45: 111.80472
A46: 41 | B46: CMI | C46: RLC | D46: Nasional | E46: =+_xlfn.CONCAT(G46,"-",B46,"_",C46,"_",_xlfn.XLOOKUP(BP46,Account!M:M,Account!N:N)) -> #NAME? | F46: 45713 | G46: E1200267 | H46: ID-RI-04021 | I46: AMIK_DURI | J46: 2 | K46: EMA | L46: RIAU | M46: Kab. Bengkalis | N46: JL. KAYANGAN RT 01 RW 07 KEL. BABUSSALAM MANDAU RIAU | O46: 1.27403 | P46: 101.17672 | Q46: 646.226 | R46: 5 | T46: Rooftop | U46: Pole | V46: Dismantle Tower | Y46: Survey | Z46: 45713 | AA46: 45720 | AB46: =IF(AA46="ds","Submit",IF(AA46="","NY Submit",IF(AA46<TODAY(),"Expired",IFERROR(DATEDIF(TODAY(),AA46,"d"),"")))) -> Expired | AD46: 45719 | AE46: 45692 | AG46: 45727 | AI46: 45738 | AN46: 45738 | AO46: =+IF(AN46<>"","BAST",IF(AI46<>"","Dismantle",IF(AG46<>"","RFD App",IF(AF46="Drop","Drop",IF(AE46<>"","Survey Report",IF(AD46<>"","Survey","NY Survey")))))) -> BAST | AQ46: 45735 | AR46: 45735 | AS46: 45735 | AU46: 45741 | AV46: 45741 | AW46: =+IF(AV46<>"","1st BOQ App on ISAAC",IF(AU46<>"","Upload 1st BOQ & BAN Isaac",IF(AT46="DRM","need DRM",IF(AT46<>"","BAN App",IF(AR46<>"","1st BOQ Pass TI",IF(AS46<>"","Engineering Structural Manager App",IF(AQ46<>"","1st BOQ Submit","NY Submit"))))))) -> 1st BOQ App on ISAAC | BD46: =+IF(BC46<>"","2nd BOQ App on ISAAC",IF(BB46<>"","Upload 2nd BOQ & BAN Isaac",IF(BA46="DRM","need DRM",IF(BA46<>"","BAN App",IF(AZ46<>"","Engineering Structural Manager App",IF(AY46<>"","2nd BOQ Pass TI",IF(AX46<>"","2nd BOQ Submit","NY Submit"))))))) -> NY Submit | BF46: 45720 | BG46: 45728 | BH46: JSA No.02/TSA/HSE/03/2025 | BI46: 45720 | BJ46: 45700 | BK46: SWP-HSE-25 | BL46: =+IF(BG46<>"","Approved",IF(BF46<>"","Submit","NY Submit")) -> Approved | BM46: =+IF(BJ46<>"","Approved",IF(BI46<>"","Submit","NY Submit")) -> Approved | BN46: 45741 | BO46: 45741 | BP46: Dismantle Tower | BQ46: EMAPO25-000667 | BR46: 45771 | BS46: =IF(AO46="Drop", "Drop", IF(ISBLANK(AV46), 0, IF(ISBLANK(BR46), DATEDIF(AV46,TODAY(),"d"), DATEDIF(AV46,BR46,"d") ) ) ) -> 30 | BV46: =IF(AO46="Drop", "Drop", IF(ISBLANK(BC46), 0, IF(ISBLANK(BU46), DATEDIF(BC46,TODAY(),"d"), DATEDIF(BC46,BU46,"d") ) ) ) -> 0 | BZ46: Complete
A47: 42 | B47: CMI | C47: RLC | D47: Nasional | E47: =+_xlfn.CONCAT(G47,"-",B47,"_",C47,"_",_xlfn.XLOOKUP(BP47,Account!M:M,Account!N:N)) -> #NAME? | F47: 45713 | G47: E1200268 | H47: ID-RI-04022 | I47: SUDIRMAN_DURI / SUDIRMAN DURI-4 | J47: 2 | K47: EMA | L47: RIAU | M47: Kab. Bengkalis | N47: JL. JEND. SUDIRMAN NO. 9 KEL. BABUSSALAM KEL. MANDAU KAB. BENGKALIS- RIAU | O47: 1.280917 | P47: 101.195194 | Q47: 4930.116 | R47: 25 | T47: Rooftop | U47: MT 4 Legs | V47: Dismantle Tower | Y47: Survey | Z47: 45713 | AA47: 45720 | AB47: =IF(AA47="ds","Submit",IF(AA47="","NY Submit",IF(AA47<TODAY(),"Expired",IFERROR(DATEDIF(TODAY(),AA47,"d"),"")))) -> Expired | AD47: 45717 | AE47: 45754 | AG47: 45769 | AI47: 45779 | AN47: 45797 | AO47: =+IF(AN47<>"","BAST",IF(AI47<>"","Dismantle",IF(AG47<>"","RFD App",IF(AF47="Drop","Drop",IF(AE47<>"","Survey Report",IF(AD47<>"","Survey","NY Survey")))))) -> BAST | AQ47: 45768 | AR47: 45793 | AS47: 45792 | AT47: 45792 | AU47: 45793 | AV47: 45793 | AW47: =+IF(AV47<>"","1st BOQ App on ISAAC",IF(AU47<>"","Upload 1st BOQ & BAN Isaac",IF(AT47="DRM","need DRM",IF(AT47<>"","BAN App",IF(AR47<>"","1st BOQ Pass TI",IF(AS47<>"","Engineering Structural Manager App",IF(AQ47<>"","1st BOQ Submit","NY Submit"))))))) -> 1st BOQ App on ISAAC | BD47: =+IF(BC47<>"","2nd BOQ App on ISAAC",IF(BB47<>"","Upload 2nd BOQ & BAN Isaac",IF(BA47="DRM","need DRM",IF(BA47<>"","BAN App",IF(AZ47<>"","Engineering Structural Manager App",IF(AY47<>"","2nd BOQ Pass TI",IF(AX47<>"","2nd BOQ Submit","NY Submit"))))))) -> NY Submit | BF47: 45758 | BG47: 45758 | BH47: JSA No.03/TSA/HSE/04/2025 | BI47: 45758 | BJ47: 45763 | BK47: SWP-HSE-29 | BL47: =+IF(BG47<>"","Approved",IF(BF47<>"","Submit","NY Submit")) -> Approved | BM47: =+IF(BJ47<>"","Approved",IF(BI47<>"","Submit","NY Submit")) -> Approved | BO47: 45797 | BP47: Dismantle Tower | BQ47: EMAPO25-000993 | BR47: 45813 | BS47: =IF(AO47="Drop", "Drop", IF(ISBLANK(AV47), 0, IF(ISBLANK(BR47), DATEDIF(AV47,TODAY(),"d"), DATEDIF(AV47,BR47,"d") ) ) ) -> 20 | BV47: =IF(AO47="Drop", "Drop", IF(ISBLANK(BC47), 0, IF(ISBLANK(BU47), DATEDIF(BC47,TODAY(),"d"), DATEDIF(BC47,BU47,"d") ) ) ) -> 0 | BZ47: Complete
A48: 43 | B48: CMI | C48: RLC | D48: Nasional | E48: =+_xlfn.CONCAT(G48,"-",B48,"_",C48,"_",_xlfn.XLOOKUP(BP48,Account!M:M,Account!N:N)) -> #NAME? | F48: 45713 | G48: E1200270 | H48: ID-RI-04023 | I48: HOTEL_FAJAR | J48: 2 | K48: EMA | L48: RIAU | M48: Kab. Bengkalis | N48: JALAN JEND. SUDIRMAN DESA GAJAH SAKTI KECAMATAN MANDAU KABUPATEN BENGKALIS PROVINSI RIAU | O48: 1.27047 | P48: 101.20196 | Q48: 1577.217 | R48: 12 | T48: Rooftop | U48: Pole | V48: Dismantle Tower | Y48: Survey | Z48: 45713 | AA48: 45720 | AB48: =IF(AA48="ds","Submit",IF(AA48="","NY Submit",IF(AA48<TODAY(),"Expired",IFERROR(DATEDIF(TODAY(),AA48,"d"),"")))) -> Expired | AD48: 45719 | AE48: 45692 | AG48: 45762 | AI48: 45771 | AN48: 45772 | AO48: =+IF(AN48<>"","BAST",IF(AI48<>"","Dismantle",IF(AG48<>"","RFD App",IF(AF48="Drop","Drop",IF(AE48<>"","Survey Report",IF(AD48<>"","Survey","NY Survey")))))) -> BAST | AQ48: 45735 | AR48: 45735 | AS48: 45735 | AU48: 45741 | AV48: 45741 | AW48: =+IF(AV48<>"","1st BOQ App on ISAAC",IF(AU48<>"","Upload 1st BOQ & BAN Isaac",IF(AT48="DRM","need DRM",IF(AT48<>"","BAN App",IF(AR48<>"","1st BOQ Pass TI",IF(AS48<>"","Engineering Structural Manager App",IF(AQ48<>"","1st BOQ Submit","NY Submit"))))))) -> 1st BOQ App on ISAAC | BD48: =+IF(BC48<>"","2nd BOQ App on ISAAC",IF(BB48<>"","Upload 2nd BOQ & BAN Isaac",IF(BA48="DRM","need DRM",IF(BA48<>"","BAN App",IF(AZ48<>"","Engineering Structural Manager App",IF(AY48<>"","2nd BOQ Pass TI",IF(AX48<>"","2nd BOQ Submit","NY Submit"))))))) -> NY Submit | BF48: 45722 | BG48: 45741 | BH48: JSA No.03/TSA/HSE/03/2025 | BI48: 45722 | BJ48: 45736 | BK48: SWP-HSE-26 | BL48: =+IF(BG48<>"","Approved",IF(BF48<>"","Submit","NY Submit")) -> Approved | BM48: =+IF(BJ48<>"","Approved",IF(BI48<>"","Submit","NY Submit")) -> Approved | BN48: 45772 | BO48: 45775 | BP48: Dismantle Tower | BQ48: EMAPO25-000668 | BR48: 45771 | BS48: =IF(AO48="Drop", "Drop", IF(ISBLANK(AV48), 0, IF(ISBLANK(BR48), DATEDIF(AV48,TODAY(),"d"), DATEDIF(AV48,BR48,"d") ) ) ) -> 30 | BV48: =IF(AO48="Drop", "Drop", IF(ISBLANK(BC48), 0, IF(ISBLANK(BU48), DATEDIF(BC48,TODAY(),"d"), DATEDIF(BC48,BU48,"d") ) ) ) -> 0 | BZ48: Complete
A49: 44 | B49: CMI | C49: RLC | D49: Nasional | E49: =+_xlfn.CONCAT(G49,"-",B49,"_",C49,"_",_xlfn.XLOOKUP(BP49,Account!M:M,Account!N:N)) -> #NAME? | F49: 45713 | G49: E1200417 | H49: ID-KR-04167 | I49: V_SERASAN / SERASAN | J49: 2 | K49: EMA | L49: KEPULAUAN RIAU | M49: Natuna | N49: JL.DATUK BONE KEC.SARASAN, KAB.NATUNA | O49: 2.50902 | P49: 109.02495 | Q49: 22120.78 | R49: 70 | T49: Greenfield | U49: SST 4 Legs | V49: Dismantle Tower | Y49: Survey | Z49: 45713 | AA49: 45720 | AB49: =IF(AA49="ds","Submit",IF(AA49="","NY Submit",IF(AA49<TODAY(),"Expired",IFERROR(DATEDIF(TODAY(),AA49,"d"),"")))) -> Expired | AD49: 45719 | AE49: 45719 | AG49: 45762 | AI49: 45775 | AN49: 45776 | AO49: =+IF(AN49<>"","BAST",IF(AI49<>"","Dismantle",IF(AG49<>"","RFD App",IF(AF49="Drop","Drop",IF(AE49<>"","Survey Report",IF(AD49<>"","Survey","NY Survey")))))) -> BAST | AQ49: 45757 | AR49: 45757 | AS49: 45765 | AT49: 45765 | AU49: 45769 | AV49: 45769 | AW49: =+IF(AV49<>"","1st BOQ App on ISAAC",IF(AU49<>"","Upload 1st BOQ & BAN Isaac",IF(AT49="DRM","need DRM",IF(AT49<>"","BAN App",IF(AR49<>"","1st BOQ Pass TI",IF(AS49<>"","Engineering Structural Manager App",IF(AQ49<>"","1st BOQ Submit","NY Submit"))))))) -> 1st BOQ App on ISAAC | BD49: =+IF(BC49<>"","2nd BOQ App on ISAAC",IF(BB49<>"","Upload 2nd BOQ & BAN Isaac",IF(BA49="DRM","need DRM",IF(BA49<>"","BAN App",IF(AZ49<>"","Engineering Structural Manager App",IF(AY49<>"","2nd BOQ Pass TI",IF(AX49<>"","2nd BOQ Submit","NY Submit"))))))) -> NY Submit | BF49: 45720 | BG49: 45720 | BH49: JSA No.01/TSA/HSE/03/2025 | BI49: 45720 | BJ49: 45720 | BK49: SWP-HSE-24 | BL49: =+IF(BG49<>"","Approved",IF(BF49<>"","Submit","NY Submit")) -> Approved | BM49: =+IF(BJ49<>"","Approved",IF(BI49<>"","Submit","NY Submit")) -> Approved | BN49: 45776 | BO49: 45776 | BP49: Dismantle Tower | BQ49: EMAPO25-000796 | BR49: 45791 | BS49: =IF(AO49="Drop", "Drop", IF(ISBLANK(AV49), 0, IF(ISBLANK(BR49), DATEDIF(AV49,TODAY(),"d"), DATEDIF(AV49,BR49,"d") ) ) ) -> 22 | BV49: =IF(AO49="Drop", "Drop", IF(ISBLANK(BC49), 0, IF(ISBLANK(BU49), DATEDIF(BC49,TODAY(),"d"), DATEDIF(BC49,BU49,"d") ) ) ) -> 0 | BZ49: Complete
A50: 45 | B50: CMI | C50: RLC | D50: Nasional | E50: =+_xlfn.CONCAT(G50,"-",B50,"_",C50,"_",_xlfn.XLOOKUP(BP50,Account!M:M,Account!N:N)) -> #NAME? | F50: 45716 | G50: R5100120 | H50: ID-BA-09700 | I50: PANTAI PANDAWA | J50: 16 | K50: CMI | L50: BALI | M50: Kab. Badung | N50: JL. KARANG PUTIH, BANJAR DESA KUTUH, KEC KUTA SELATAN, KAB BADUNG | O50: -8.84399 | P50: 115.18181 | R50: 9 | S50: IOH | T50: Rooftop | U50: Pole | V50: Dismantle Tower | Y50: Survey | AB50: =IF(AA50="ds","Submit",IF(AA50="","NY Submit",IF(AA50<TODAY(),"Expired",IFERROR(DATEDIF(TODAY(),AA50,"d"),"")))) -> NY Submit | AD50: 45718 | AE50: 45677 | AF50: Drop | AO50: =+IF(AN50<>"","BAST",IF(AI50<>"","Dismantle",IF(AG50<>"","RFD App",IF(AF50="Drop","Drop",IF(AE50<>"","Survey Report",IF(AD50<>"","Survey","NY Survey")))))) -> Drop | AW50: =+IF(AV50<>"","1st BOQ App on ISAAC",IF(AU50<>"","Upload 1st BOQ & BAN Isaac",IF(AT50="DRM","need DRM",IF(AT50<>"","BAN App",IF(AR50<>"","1st BOQ Pass TI",IF(AS50<>"","Engineering Structural Manager App",IF(AQ50<>"","1st BOQ Submit","NY Submit"))))))) -> NY Submit | BD50: =+IF(BC50<>"","2nd BOQ App on ISAAC",IF(BB50<>"","Upload 2nd BOQ & BAN Isaac",IF(BA50="DRM","need DRM",IF(BA50<>"","BAN App",IF(AZ50<>"","Engineering Structural Manager App",IF(AY50<>"","2nd BOQ Pass TI",IF(AX50<>"","2nd BOQ Submit","NY Submit"))))))) -> NY Submit | BF50: 45722 | BG50: 45728 | BH50: JSA No.04/TSA/HSE/03/2025 | BI50: 45722 | BJ50: 45728 | BK50: SWP-HSE-27 | BL50: =+IF(BG50<>"","Approved",IF(BF50<>"","Submit","NY Submit")) -> Approved | BM50: =+IF(BJ50<>"","Approved",IF(BI50<>"","Submit","NY Submit")) -> Approved | BP50: Dismantle Tower | BQ50: Drop | BS50: =IF(AO50="Drop", "Drop", IF(ISBLANK(AV50), 0, IF(ISBLANK(BR50), DATEDIF(AV50,TODAY(),"d"), DATEDIF(AV50,BR50,"d") ) ) ) -> Drop | BV50: =IF(AO50="Drop", "Drop", IF(ISBLANK(BC50), 0, IF(ISBLANK(BU50), DATEDIF(BC50,TODAY(),"d"), DATEDIF(BC50,BU50,"d") ) ) ) -> Drop | BZ50: Drop | CA50: Drop | CB50: Drop | CC50: N/A | CE50: ID-BA-15316 | CF50: PANDAWA KUTA | CG50: -8.84478 | CH50: 115.18544
A51: 46 | B51: CMI | C51: RLC | D51: Nasional | E51: =+_xlfn.CONCAT(G51,"-",B51,"_",C51,"_",_xlfn.XLOOKUP(BP51,Account!M:M,Account!N:N)) -> #NAME? | F51: 45716 | G51: R5100120 | H51: ID-BA-09700 | I51: PANTAI PANDAWA | J51: 16 | K51: CMI | L51: BALI | M51: Kab. Badung | N51: JL. KARANG PUTIH, BANJAR DESA KUTUH, KEC KUTA SELATAN, KAB BADUNG | O51: -8.84399 | P51: 115.18181 | R51: 9 | S51: IOH | T51: Rooftop | U51: Pole | V51: Dismantle Equipment | Y51: Survey | Z51: 45799 | AA51: 45889 | AB51: =IF(AA51="ds","Submit",IF(AA51="","NY Submit",IF(AA51<TODAY(),"Expired",IFERROR(DATEDIF(TODAY(),AA51,"d"),"")))) -> Expired | AD51: 45718 | AE51: 45677 | AH51: 45803 | AM51: 45803 | AO51: =+IF(AM51<>"","ATP App MS",IF(AJ51<>"","Inbound",IF(AH51<>"","Dismantle Perangkat",IF(AF51="Drop","Drop",IF(AE51<>"","Survey Report",IF(AD51<>"","Survey","NY Survey")))))) -> ATP App MS | AQ51: 45722 | AR51: 45722 | AS51: 45728 | AT51: 45728 | AU51: 45733 | AV51: 45733 | AW51: =+IF(AV51<>"","1st BOQ App on ISAAC",IF(AU51<>"","Upload 1st BOQ & BAN Isaac",IF(AT51="DRM","need DRM",IF(AT51<>"","BAN App",IF(AR51<>"","1st BOQ Pass TI",IF(AS51<>"","Engineering Structural Manager App",IF(AQ51<>"","1st BOQ Submit","NY Submit"))))))) -> 1st BOQ App on ISAAC | BD51: =+IF(BC51<>"","2nd BOQ App on ISAAC",IF(BB51<>"","Upload 2nd BOQ & BAN Isaac",IF(BA51="DRM","need DRM",IF(BA51<>"","BAN App",IF(AZ51<>"","Engineering Structural Manager App",IF(AY51<>"","2nd BOQ Pass TI",IF(AX51<>"","2nd BOQ Submit","NY Submit"))))))) -> NY Submit | BF51: 45722 | BG51: 45728 | BH51: JSA No.04/TSA/HSE/03/2025 | BI51: 45777 | BJ51: 45777 | BL51: =+IF(BG51<>"","Approved",IF(BF51<>"","Submit","NY Submit")) -> Approved | BM51: =+IF(BJ51<>"","Approved",IF(BI51<>"","Submit","NY Submit")) -> Approved | BP51: Dismantle Equipment | BQ51: CMIPO25-001886 | BR51: 45791 | BS51: =IF(AO51="Drop", "Drop", IF(ISBLANK(AV51), 0, IF(ISBLANK(BR51), DATEDIF(AV51,TODAY(),"d"), DATEDIF(AV51,BR51,"d") ) ) ) -> 58 | BV51: =IF(AO51="Drop", "Drop", IF(ISBLANK(BC51), 0, IF(ISBLANK(BU51), DATEDIF(BC51,TODAY(),"d"), DATEDIF(BC51,BU51,"d") ) ) ) -> 0 | BZ51: Complete | CE51: ID-BA-15316 | CF51: PANDAWA KUTA | CG51: -8.84478 | CH51: 115.18544 | CI51: CR-20250521-00000262
